{
	"info": {
		"_postman_id": "ccb5d4c5-068d-4a4f-a436-c3c9b3c2965c",
		"name": "mPaaS Core APIs",
		"description": "# Telegent mPaaS RESTful API Endpoints\n\nTelegent's mPaaS RESTful API provides a suite of services for managing telecommunications. The primary services documented in this workspace include:\n\n-   **Authentication**: Handles secure access to the API suite.\n-   **Intelligent Mobile Numbers**: Manages the lifecycle of phone numbers, including provisioning, porting, and configuration.\n-   **Intelligent Messaging**: Configures message routing and enables sending/receiving of messages.\n-   **Intelligent Voice**: Manages voice call handling, including call routing and outbound calls.\n\nAdditional mPaaS services offered or under development by Telegent include:\n\n-   **IoT**: Services related to Internet of Things connectivity and management.\n-   **MVNO (Beta)**: Endpoints supporting Mobile Virtual Network Operator functionalities.\n-   **Campaigns**: (Targeted for addition in February) Services for managing communication campaigns. ",
		"schema": "https://schema.getpostman.com/json/collection/v2.1.0/collection.json",
		"_exporter_id": "44792744",
		"_collection_link": "https://www.postman.com/joonto-mobile-api/workspace/telegent-mpaas-core-prod/collection/9646813-ccb5d4c5-068d-4a4f-a436-c3c9b3c2965c?action=share&source=collection_link&creator=44792744"
	},
	"item": [
		{
			"name": "v1.0",
			"item": [
				{
					"name": "Authentication",
					"item": [
						{
							"name": "Token",
							"request": {
								"method": "POST",
								"header": [],
								"body": {
									"mode": "raw",
									"raw": "{ \n    \"AccountKey\": \"{{AccountKey}}\",\n    \"AccountSecret\":  \"{{AccountSecret}}\",\n    \"ApiEndpoint\": \"https://api.telegent.com/v1.0/message/routes\"\n}",
									"options": {
										"raw": {
											"language": "json"
										}
									}
								},
								"url": {
									"raw": "https://api.telegent.com/v1.0/oauth2/tokens",
									"protocol": "https",
									"host": [
										"api",
										"telegent",
										"com"
									],
									"path": [
										"v1.0",
										"oauth2",
										"tokens"
									]
								},
								"description": "# POST /oauth2/tokens\n\n**Purpose**: Authenticates the user and retrieves an API access token.\n\n**Key Request Body Fields**:\n\n- `AccountKey`: Your account key (e.g., the value stored in a Postman variable like `{{AccountKey}}`).\n    \n- `AccountSecret`: Your account secret (e.g., the value stored in a Postman variable like `{{AccountSecret}}`).\n    \n\n**Key Response Fields**:\n\n- `Token`: The bearer token for API access.\n    \n- `Successful`: Boolean indicating if authentication succeeded.\n    \n- `TokenExpiry`: Timestamp or duration for token validity.\n    \n- `ApiEndpoint`: The base URL for subsequent API calls (e.g., \"[https://api.telegent.com/v1.0/message/routes\"](https://api.telegent.com/v1.0/message/routes)).\n    \n- `Error`: Error message if authentication fails.\n    \n\n**Notes**:\n\n- This is the first call you should make to interact with the API.\n    \n- The returned `Token` must be included in the `Authorization` header (e.g., `Authorization: Bearer` ) for all other API requests."
							},
							"response": [
								{
									"name": "Token",
									"originalRequest": {
										"method": "POST",
										"header": [],
										"body": {
											"mode": "raw",
											"raw": "{ \n    \"AccountKey\": \"{{AccountKey}}\",\n    \"AccountSecret\":  \"{{AccountSecret}}\",\n    \"ApiEndpoint\": \"https://api.telegent.com/v1.0/numbers/availability\"\n}",
											"options": {
												"raw": {
													"language": "json"
												}
											}
										},
										"url": {
											"raw": "https://api.telegent.com/v1.0/oauth2/tokens",
											"protocol": "https",
											"host": [
												"api",
												"telegent",
												"com"
											],
											"path": [
												"v1.0",
												"oauth2",
												"tokens"
											]
										}
									},
									"_postman_previewlanguage": "json",
									"header": [
										{
											"key": "Content-Type",
											"value": "application/json",
											"description": "",
											"type": "text"
										}
									],
									"cookie": [],
									"body": "{\n    \"token\": \"eyJhbGciOiJIUzI1NiIsInR5cCI6IkpXVCJ9.eyJodHRwOi8vc2NoZW1hcy54bWxzb2FwLm9yZy93cy8yMDA1LzA1L2lkZW50aXR5L2NsYWltcy9uYW1laWRlbnRpZmllciI6IkRJRC0xZTg5MzlhYi0zZjNjLTRkYjEtODlkNy05NTZkODBmZDc5M2oiLCJodHRwOi8vc2NoZW1hcy5taWNyb3NvZnQuY29tL3dzLzIwMDgvMDYvaWRlbnRpdHkvY2xhaW1zL3VzZXJkYXRhIjoiNHd2ZStrT2E3YjhIUGk5ODFLek9weGNUSkYwVHNET3F0VXdLWHVmWXVFalBwMm96TkdmMlVHUlFZazJJTkV3T2RDUHVRWm9teFQzWW9yVlo1ZWY4SDJFWmF2WlpmdnNOYmNLc1VEMkd3Z3J6LzlTcGt1WkFYN1MvbVdTTTVjWFZVOVlyZUxhWXFuWTNNWXhrd0diRUZYdHNYS2JLNnBhcGxSRDJlZlhKWlRkcDA4c3hmYWcrTEJtTDFXRk1qZmMwIiwiZXhwIjoxNzQ2MjEwOTczLCJpc3MiOiJodHRwczovL2FwaS50ZWxlZ2VudC5jbyIsImF1ZCI6ImNvbS50ZWxlZ2VudC5jbyJ9.-btpm87tbFgNDmS-InZonSGyjqnfBSnotx9mazhvmE0\",\n    \"successful\": true,\n    \"tokenExpiry\": \"05/02/2025 06:36:13 PM\",\n    \"apiEndpoint\": \"https://api.telegent.com/v1.0/numbers/availability\"\n}"
								}
							]
						}
					],
					"description": "# POST /oauth2/tokens\n\n**Purpose**: Authenticates the user and retrieves an API access token.\n\n**Key Request Body Fields**:\n\n- `AccountKey`: Your account key (e.g., the value stored in a Postman variable like `{{AccountKey}}`).\n    \n- `AccountSecret`: Your account secret (e.g., the value stored in a Postman variable like `{{AccountSecret}}`).\n    \n\n**Key Response Fields**:\n\n- `Token`: The bearer token for API access.\n    \n- `Successful`: Boolean indicating if authentication succeeded.\n    \n- `TokenExpiry`: Timestamp or duration for token validity.\n    \n- `ApiEndpoint`: The base URL for subsequent API calls.\n    \n- `Error`: Error message if authentication fails.\n    \n\n**Notes**:\n\n- This is the first call you should make to interact with the API.\n    \n- The returned `Token` must be included in the `Authorization` header (e.g., `Authorization: Bearer` ) for all other API requests."
				},
				{
					"name": "Intelligent Mobile Numbers",
					"item": [
						{
							"name": "Available Numbers",
							"event": [
								{
									"listen": "prerequest",
									"script": {
										"exec": [
											""
										],
										"type": "text/javascript",
										"packages": {}
									}
								}
							],
							"request": {
								"method": "POST",
								"header": [],
								"body": {
									"mode": "raw",
									"raw": "{\n    \"NumberType\": \"mobile\", //options are \"mobile\" or \"voip\"\n    \"MessageEnabled\": true,\n    \"VoiceEnabled\": true,\n    \"PageNumber\": 1,\n    \"TotalNumbersRequested\": 12, //default is 12 results per request if left blank/null\n    \"AreaCode\": \"201\", //lookup area code first\n    \"ZipCode\": \"\" //if area code unavailable, then system looks at Zipcode options\n    //you may input both, or just one of the two; however Area Code will search first if included. If AreaCode and ZipCode are left blank or NULL, a randomized set of results will be requested.\n}",
									"options": {
										"raw": {
											"language": "json"
										}
									}
								},
								"url": {
									"raw": "https://api.telegent.com/v1.0/numbers/availability",
									"protocol": "https",
									"host": [
										"api",
										"telegent",
										"com"
									],
									"path": [
										"v1.0",
										"numbers",
										"availability"
									]
								},
								"description": "## POST /numbers/availability\n\nChecks the availability of phone numbers based on the specified criteria and returns a paginated list of available numbers matching your requirements.\n\n### Request\n\n#### Headers\n\n```\nContent-Type: application/json\nAuthorization: Bearer {your_api_token}\n\n ```\n\n#### Body Parameters\n\n| Parameter | Type | Required | Description | Example |\n| --- | --- | --- | --- | --- |\n| `NumberType` | string | Yes | Type of phone number requested. Valid values: `mobile`, `landline`, `tollfree` | `\"mobile\"` |\n| `MessageEnabled` | boolean | Yes | Whether SMS/MMS messaging capability is required | `true` |\n| `VoiceEnabled` | boolean | Yes | Whether voice calling capability is required | `true` |\n| `AreaCode` | string | No\\* | 3-digit area code for the number. \\*Required if ZipCode not provided | `\"201\"` |\n| `ZipCode` | string | No\\* | 5-digit zip code for the number. \\*Required if AreaCode not provided | `\"07302\"` |\n| `PageNumber` | integer | No | Page number for paginated results (starts at 1) | `1` |\n| `TotalNumbersRequested` | integer | No | Number of phone numbers to return per page (max: 100) | `20` |\n\n> **Note**: You must provide either `AreaCode` or `ZipCode` to search for available numbers. \n  \n\n### Sample Request\n\n``` json\n{\n  \"NumberType\": \"mobile\",\n  \"MessageEnabled\": true,\n  \"VoiceEnabled\": true,\n  \"AreaCode\": \"201\",\n  \"PageNumber\": 1,\n  \"TotalNumbersRequested\": 15\n}\n\n ```\n\n### Responses\n\n#### 200 OK: Success\n\nReturns a list of available phone numbers matching the specified criteria.\n\n``` json\n{\n  \"RequestId\": \"T-04139\",\n  \"RequestDate\": \"2025-05-14T18:37:18.2408767Z\",\n  \"NumberType\": \"mobile\",\n  \"VoiceEnabled\": true,\n  \"MessageEnabled\": true,\n  \"AreaCode\": \"201\",\n  \"ZipCode\": \"\",\n  \"ResultsTotal\": 7700,\n  \"PageNumber\": 1,\n  \"NumbersAvailable\": [\n    { \"Number\": \"+12013782520\" },\n    { \"Number\": \"+12013782521\" },\n    { \"Number\": \"+12013782522\" },\n    { \"Number\": \"+12013782523\" },\n    { \"Number\": \"+12013782524\" },\n    { \"Number\": \"+12013782525\" },\n    { \"Number\": \"+12013782526\" },\n    { \"Number\": \"+12013782528\" },\n    { \"Number\": \"+12013782530\" },\n    { \"Number\": \"+12013782531\" },\n    { \"Number\": \"+12013782532\" },\n    { \"Number\": \"+12013782533\" }\n  ]\n}\n\n ```\n\n##### Response Fields\n\n| Field | Type | Description |\n| --- | --- | --- |\n| `RequestId` | string | Unique identifier for this request |\n| `RequestDate` | string | Timestamp of the request (ISO 8601 format) |\n| `NumberType` | string | The requested number type |\n| `VoiceEnabled` | boolean | Whether voice capability was requested |\n| `MessageEnabled` | boolean | Whether messaging capability was requested |\n| `AreaCode` | string | The requested area code (if provided) |\n| `ZipCode` | string | The requested zip code (if provided) |\n| `ResultsTotal` | integer | Total number of available phone numbers matching criteria |\n| `PageNumber` | integer | Current page number |\n| `NumbersAvailable` | array | List of available phone numbers |\n\n#### 400 Bad Request: Validation Error\n\n``` json\n{\n  \"Type\": \"https://tools.ietf.org/html/rfc7231#section-6.5.1\",\n  \"Title\": \"One or more validation errors occurred.\",\n  \"Status\": 400,\n  \"Errors\": {\n    \"$.AreaCode\": [\"Area code must be a valid 3-digit code\"]\n  },\n  \"TraceId\": \"00-1234abcd5678efgh-abcdef123456-00\"\n}\n\n ```\n\n#### 401 Unauthorized: Authentication Error\n\n``` json\n{\n  \"Type\": \"https://tools.ietf.org/html/rfc7235#section-3.1\",\n  \"Title\": \"Unauthorized\",\n  \"Status\": 401,\n  \"TraceId\": \"00-1234abcd5678efgh-abcdef123456-00\"\n}\n\n ```\n\n### Usage Notes\n\n- Use this endpoint before attempting to provision numbers to ensure the desired types and quantities are available.\n    \n- Results are paginated. Use the `PageNumber` parameter to navigate through large result sets.\n    \n- For optimal performance, consider using a specific area code or zip code to narrow your search.\n    \n- The API may implement rate limiting. Consider caching results when appropriate.\n    \n\n### Try It\n\n```\ncurl -X POST https://api.telegent.com/numbers/availability \\\n  -H \"Content-Type: application/json\" \\\n  -H \"Authorization: Bearer YOUR_API_TOKEN\" \\\n  -d '{\n    \"NumberType\": \"mobile\",\n    \"MessageEnabled\": true,\n    \"VoiceEnabled\": true,\n    \"AreaCode\": \"201\",\n    \"PageNumber\": 1,\n    \"TotalNumbersRequested\": 15\n  }'\n\n ```"
							},
							"response": [
								{
									"name": "Available Numbers",
									"originalRequest": {
										"method": "POST",
										"header": [],
										"body": {
											"mode": "raw",
											"raw": "{\n    \"NumberType\": \"mobile\", //options are \"mobile\" or \"voip\"\n    \"MessageEnabled\": true,\n    \"VoiceEnabled\": true,\n    \"PageNumber\": 1,\n    \"TotalNumbersRequested\": 12, //default is 12 results per request if left blank/null\n    \"AreaCode\": \"201\", //lookup area code first\n    \"ZipCode\": \"\" //if area code unavailable, then system looks at Zipcode options\n    //you may input both, or just one of the two; however Area Code will search first if included. If AreaCode and ZipCode are left blank or NULL, a randomized set of results will be requested.\n}",
											"options": {
												"raw": {
													"language": "json"
												}
											}
										},
										"url": {
											"raw": "https://api.telegent.com/v1.0/numbers/availability",
											"protocol": "https",
											"host": [
												"api",
												"telegent",
												"com"
											],
											"path": [
												"v1.0",
												"numbers",
												"availability"
											]
										}
									},
									"_postman_previewlanguage": "json",
									"header": [
										{
											"key": "Content-Type",
											"value": "application/json",
											"description": "",
											"type": "text"
										}
									],
									"cookie": [],
									"body": "{\n    \"RequestId\": \"T-04139\",\n    \"RequestDate\": \"2025-05-14T18:37:18.2408767Z\",\n    \"NumberType\": \"mobile\",\n    \"VoiceEnabled\": true,\n    \"MessageEnabled\": true,\n    \"AreaCode\": \"201\",\n    \"ZipCode\": \"\",\n    \"ResultsTotal\": 7700,\n    \"PageNumber\": 1,\n    \"NumbersAvailable\": [\n        {\n            \"Number\": \"+12013782520\"\n        },\n        {\n            \"Number\": \"+12013782521\"\n        },\n        {\n            \"Number\": \"+12013782522\"\n        },\n        {\n            \"Number\": \"+12013782523\"\n        },\n        {\n            \"Number\": \"+12013782524\"\n        },\n        {\n            \"Number\": \"+12013782525\"\n        },\n        {\n            \"Number\": \"+12013782526\"\n        },\n        {\n            \"Number\": \"+12013782528\"\n        },\n        {\n            \"Number\": \"+12013782530\"\n        },\n        {\n            \"Number\": \"+12013782531\"\n        },\n        {\n            \"Number\": \"+12013782532\"\n        },\n        {\n            \"Number\": \"+12013782533\"\n        }\n    ]\n}"
								}
							]
						},
						{
							"name": "Number Provision (Purchase/Order)",
							"event": [
								{
									"listen": "test",
									"script": {
										"exec": [
											"pm.test(\"Response has OrderId\", function () {",
											"    pm.response.to.have.property(\"json\");",
											"    const jsonData = pm.response.json();",
											"    pm.expect(jsonData).to.have.property(\"OrderId\");",
											"});",
											"",
											"pm.test(\"Extract and store OrderId in collection variables\", function () {",
											"    const jsonData = pm.response.json();",
											"    const orderId = jsonData.OrderId;",
											"    pm.collectionVariables.set(\"OrderId\", orderId);",
											"    console.log(\"👉 Stored OrderId:\", orderId);",
											"});",
											"pm.test(\"All output keys are PascalCase\", function () {",
											"    const jsonData = pm.response.json();",
											"    const keys = Object.keys(jsonData);",
											"    keys.forEach(key => {",
											"        pm.expect(key).to.match(/^[A-Z][a-z0-9]*([A-Z][a-z0-9]*)*$/);",
											"    });",
											"});"
										],
										"type": "text/javascript",
										"packages": {}
									}
								}
							],
							"request": {
								"method": "POST",
								"header": [],
								"body": {
									"mode": "raw",
									"raw": "{\n    \"NumberType\": \"mvno\", //options are \"mvno\" or \"iot\" (note: iot numbers can only be provisioned as p2p and never a2p.  Please use mvno NumberType for selecting a2p as MessageType\n    \"MessageType\": \"p2p\", //options are \"p2p\" or \"a2p\"\n    \"MessageEnabled\": true,\n    \"VoiceEnabled\": true,\n    \"MessageRouteId\": \"MRID-73af1e73-d7b3-4696-bdd9-5b407c96fc8a\",\n    \"VoiceRouteId\": \"CRID-4dec6beb-3985-444b-8c06-8baa70dc145\",\n    \"PhoneNumbers\": [\n {\n   \"Number\": \"+12164278934\"\n },\n {\n   \"Number\": \"+12232233156\"\n },\n {\n   \"Number\": \"+12232233122\"\n },\n {\n   \"Number\": \"+12232233111\"\n }\n]\n}\n",
									"options": {
										"raw": {
											"language": "json"
										}
									}
								},
								"url": {
									"raw": "https://api.telegent.com/v1.0/numbers/provision",
									"protocol": "https",
									"host": [
										"api",
										"telegent",
										"com"
									],
									"path": [
										"v1.0",
										"numbers",
										"provision"
									]
								},
								"description": "# Phone Number Provisioning\n\n## POST /numbers/provision\n\nProvisions multiple phone numbers with specified messaging and voice capabilities and assigns them to designated routes.\n\n### Request\n\n#### Headers\n\n```\nContent-Type: application/json\nAuthorization: Bearer {your_api_token}\n\n ```\n\n#### Body Parameters\n\n| Parameter | Type | Required | Description |\n| --- | --- | --- | --- |\n| `NumberType` | string | Yes | Type of phone number to provision. Valid values: `mvno`, `iot` |\n| `MessageType` | string | Yes | Messaging classification. Valid values: `p2p`, `a2p` |\n| `MessageEnabled` | boolean | Yes | Whether to enable SMS/MMS messaging capability |\n| `VoiceEnabled` | boolean | Yes | Whether to enable voice calling capability |\n| `MessageRouteId` | string | Conditional | UUID of the message routing configuration (required if MessageEnabled is true) |\n| `VoiceRouteId` | string | Conditional | UUID of the voice routing configuration (required if VoiceEnabled is true) |\n| `PhoneNumbers` | array | Yes | List of phone numbers to provision |\n\n> **Important Notes**: \n  \n\n### Sample Request\n\n``` json\n{\n    \"NumberType\": \"iot\",\n    \"MessageType\": \"p2p\",\n    \"MessageEnabled\": true,\n    \"VoiceEnabled\": true,\n    \"MessageRouteId\": \"MRID-73af1e73-d7b3-4696-bdd9-5b407c96fc8a\",\n    \"VoiceRouteId\": \"CRID-4dec6beb-3985-444b-8c06-8baa70dc145\",\n    \"PhoneNumbers\": [\n        {\n            \"Number\": \"+12164278934\"\n        },\n        {\n            \"Number\": \"+12232233156\"\n        },\n        {\n            \"Number\": \"+12232233122\"\n        },\n        {\n            \"Number\": \"+12232233111\"\n        }\n    ]\n}\n\n ```\n\n### Responses\n\n#### 200 OK: Success\n\nReturns the order details for the provisioned phone numbers.\n\n``` json\n{\n    \"OrderDate\": \"2025-05-14T18:56:33.0005512+00:00\",\n    \"OrderId\": \"JNUOID-ad65e0d6-dbc6-41bd-bc51-736fb6a1e20a\",\n    \"OrderStatus\": \"Submitted\",\n    \"PhoneNumbersRequested\": [\n        {\n            \"Number\": \"+12164278934\"\n        },\n        {\n            \"Number\": \"+12232233156\"\n        },\n        {\n            \"Number\": \"+12232233122\"\n        },\n        {\n            \"Number\": \"+12232233111\"\n        }\n    ]\n}\n\n ```\n\n##### Response Fields\n\n| Field | Type | Description |\n| --- | --- | --- |\n| `OrderDate` | string | Timestamp when the order was submitted (ISO 8601 format) |\n| `OrderId` | string | Unique identifier for the provisioning order |\n| `OrderStatus` | string | Current status of the order (e.g., \"Submitted\", \"Processing\", \"Completed\") |\n| `PhoneNumbersRequested` | array | List of phone numbers that were requested for provisioning |\n\n#### 400 Bad Request: Validation Error\n\n``` json\n{\n    \"Type\": \"https://tools.ietf.org/html/rfc7231#section-6.5.1\",\n    \"Title\": \"One or more validation errors occurred.\",\n    \"Status\": 400,\n    \"Errors\": {\n        \"$.NumberType\": [\"Invalid NumberType and MessageType combination. IOT numbers can only be provisioned with p2p MessageType.\"]\n    },\n    \"TraceId\": \"00-1234abcd5678efgh-abcdef123456-00\"\n}\n\n ```\n\n#### 401 Unauthorized: Authentication Error\n\n``` json\n{\n    \"Type\": \"https://tools.ietf.org/html/rfc7235#section-3.1\",\n    \"Title\": \"Unauthorized\",\n    \"Status\": 401,\n    \"TraceId\": \"00-1234abcd5678efgh-abcdef123456-00\"\n}\n\n ```\n\n### Usage Notes\n\n- Before provisioning, use the `/numbers/availability` endpoint to check if your desired numbers are available.\n    \n- Provisioning is an asynchronous process. Check the order status using the returned `OrderId`.\n    \n- Both `MessageRouteId` and `VoiceRouteId` must be valid, pre-configured route identifiers in your account.\n    \n- All phone numbers in a single request will have the same configuration (NumberType, MessageType, routes).\n    \n- Number formatting must be in E.164 format (e.g., +12164278934).\n    \n\n### Try It\n\n```\ncurl -X POST https://api.example.com/numbers/provision \\\n  -H \"Content-Type: application/json\" \\\n  -H \"Authorization: Bearer YOUR_API_TOKEN\" \\\n  -d '{\n    \"NumberType\": \"iot\",\n    \"MessageType\": \"p2p\",\n    \"MessageEnabled\": true,\n    \"VoiceEnabled\": true,\n    \"MessageRouteId\": \"MRID-73af1e73-d7b3-4696-bdd9-5b407c96fc8a\",\n    \"VoiceRouteId\": \"CRID-4dec6beb-3985-444b-8c06-8baa70dc145\",\n    \"PhoneNumbers\": [\n        {\n            \"Number\": \"+12164278934\"\n        },\n        {\n            \"Number\": \"+12232233156\"\n        },\n        {\n            \"Number\": \"+12232233122\"\n        },\n        {\n            \"Number\": \"+12232233111\"\n        }\n    ]\n}'\n\n ```"
							},
							"response": [
								{
									"name": "Number Provision - P2P",
									"originalRequest": {
										"method": "POST",
										"header": [],
										"body": {
											"mode": "raw",
											"raw": "{\n    \"NumberType\": \"iot\", //options are \"mvno\" or \"iot\" (note: iot numbers can only be provisioned as p2p and never a2p.  Please use mvno NumberType for selecting a2p as MessageType\n    \"MessageType\": \"p2p\", //options are \"p2p\" or \"a2p\"\n    \"MessageEnabled\": true,\n    \"VoiceEnabled\": true,\n    \"MessageRouteId\": \"MRID-73af1e73-d7b3-4696-bdd9-5b407c96fc8a\",\n    \"VoiceRouteId\": \"CRID-4dec6beb-3985-444b-8c06-8baa70dc145\",\n    \"PhoneNumbers\": [\n {\n   \"Number\": \"+12164278934\"\n },\n {\n   \"Number\": \"+12232233156\"\n },\n {\n   \"Number\": \"+12232233122\"\n },\n {\n   \"Number\": \"+12232233111\"\n }\n]\n}\n\n",
											"options": {
												"raw": {
													"language": "json"
												}
											}
										},
										"url": {
											"raw": "https://api.telegent.com/v1.0/numbers/provision",
											"protocol": "https",
											"host": [
												"api",
												"telegent",
												"com"
											],
											"path": [
												"v1.0",
												"numbers",
												"provision"
											]
										}
									},
									"status": "OK",
									"code": 200,
									"_postman_previewlanguage": "json",
									"header": [
										{
											"key": "Cache-Control",
											"value": "no-cache"
										},
										{
											"key": "Pragma",
											"value": "no-cache"
										},
										{
											"key": "Transfer-Encoding",
											"value": "chunked"
										},
										{
											"key": "Content-Type",
											"value": "application/json"
										},
										{
											"key": "Content-Encoding",
											"value": "gzip"
										},
										{
											"key": "Expires",
											"value": "-1"
										},
										{
											"key": "Vary",
											"value": "Accept-Encoding"
										},
										{
											"key": "Set-Cookie",
											"value": "ARRAffinity=8cb9eb8a9c8e49bb32964ef5e087477636164e3b1bd119e62b62b2d516d04b33;Path=/;HttpOnly;Secure;Domain=prod-04.westus3.logic.azure.com"
										},
										{
											"key": "Set-Cookie",
											"value": "ARRAffinitySameSite=8cb9eb8a9c8e49bb32964ef5e087477636164e3b1bd119e62b62b2d516d04b33;Path=/;HttpOnly;SameSite=None;Secure;Domain=prod-04.westus3.logic.azure.com"
										},
										{
											"key": "Strict-Transport-Security",
											"value": "max-age=31536000; includeSubDomains"
										},
										{
											"key": "x-ms-workflow-run-id",
											"value": "08585023079845210699477700407CU30"
										},
										{
											"key": "x-ms-correlation-id",
											"value": "d2358001-e293-45cd-809f-535faa8bcd47"
										},
										{
											"key": "x-ms-client-tracking-id",
											"value": "08585023079845210699477700407CU30"
										},
										{
											"key": "x-ms-trigger-history-name",
											"value": "08585023079845210699477700407CU30"
										},
										{
											"key": "x-ms-execution-location",
											"value": "westus3"
										},
										{
											"key": "x-ms-workflow-system-id",
											"value": "/locations/westus3/scaleunits/prod-04/workflows/86c7b0688cb44dd6934a78279b875e36"
										},
										{
											"key": "x-ms-workflow-id",
											"value": "86c7b0688cb44dd6934a78279b875e36"
										},
										{
											"key": "x-ms-workflow-version",
											"value": "08585023080253567980"
										},
										{
											"key": "x-ms-workflow-name",
											"value": "Joonto_Numbers_v1.0_Purchase"
										},
										{
											"key": "x-ms-tracking-id",
											"value": "d2358001-e293-45cd-809f-535faa8bcd47"
										},
										{
											"key": "x-ms-ratelimit-burst-remaining-workflow-writes",
											"value": "4499"
										},
										{
											"key": "x-ms-ratelimit-remaining-workflow-download-contentsize",
											"value": "322121551"
										},
										{
											"key": "x-ms-ratelimit-remaining-workflow-upload-contentsize",
											"value": "322121581"
										},
										{
											"key": "x-ms-ratelimit-time-remaining-directapirequests",
											"value": "29999388"
										},
										{
											"key": "x-ms-request-id",
											"value": "westus3:d2358001-e293-45cd-809f-535faa8bcd47"
										},
										{
											"key": "Date",
											"value": "Mon, 06 Nov 2023 19:28:20 GMT"
										}
									],
									"cookie": [],
									"body": "{\n    \"OrderDate\": \"2025-05-14T18:56:33.0005512+00:00\",\n    \"OrderId\": \"JNUOID-ad65e0d6-dbc6-41bd-bc51-736fb6a1e20a\",\n    \"OrderStatus\": \"Submitted\",\n    \"PhoneNumbersRequested\": [\n        {\n            \"Number\": \"+12164278934\"\n        },\n        {\n            \"Number\": \"+12232233156\"\n        },\n        {\n            \"Number\": \"+12232233122\"\n        },\n        {\n            \"Number\": \"+12232233111\"\n        }\n    ]\n}"
								},
								{
									"name": "Number Provision - A2P",
									"originalRequest": {
										"method": "POST",
										"header": [],
										"body": {
											"mode": "raw",
											"raw": "{\n    \"NumberType\": \"mvno\", //options are \"mvno\" or \"iot\" (note: iot numbers can only be provisioned as p2p and never a2p.  Please use mvno NumberType for selecting a2p as MessageType\n    \"MessageType\": \"p2p\", //options are \"p2p\" or \"a2p\"\n    \"MessageEnabled\": true,\n    \"VoiceEnabled\": true,\n    \"MessageRouteId\": \"MRID-73af1e73-d7b3-4696-bdd9-5b407c96fc8a\",\n    \"VoiceRouteId\": \"CRID-4dec6beb-3985-444b-8c06-8baa70dc145\",\n    \"PhoneNumbers\": [\n {\n   \"Number\": \"+12164278934\"\n },\n {\n   \"Number\": \"+12232233156\"\n },\n {\n   \"Number\": \"+12232233122\"\n },\n {\n   \"Number\": \"+12232233111\"\n }\n]\n}\n",
											"options": {
												"raw": {
													"language": "json"
												}
											}
										},
										"url": {
											"raw": "https://api.telegent.com/v1.0/numbers/provision",
											"protocol": "https",
											"host": [
												"api",
												"telegent",
												"com"
											],
											"path": [
												"v1.0",
												"numbers",
												"provision"
											]
										}
									},
									"status": "OK",
									"code": 200,
									"_postman_previewlanguage": "json",
									"header": [
										{
											"key": "Cache-Control",
											"value": "no-cache"
										},
										{
											"key": "Pragma",
											"value": "no-cache"
										},
										{
											"key": "Transfer-Encoding",
											"value": "chunked"
										},
										{
											"key": "Content-Type",
											"value": "application/json"
										},
										{
											"key": "Content-Encoding",
											"value": "gzip"
										},
										{
											"key": "Expires",
											"value": "-1"
										},
										{
											"key": "Vary",
											"value": "Accept-Encoding"
										},
										{
											"key": "Set-Cookie",
											"value": "ARRAffinity=8cb9eb8a9c8e49bb32964ef5e087477636164e3b1bd119e62b62b2d516d04b33;Path=/;HttpOnly;Secure;Domain=prod-04.westus3.logic.azure.com"
										},
										{
											"key": "Set-Cookie",
											"value": "ARRAffinitySameSite=8cb9eb8a9c8e49bb32964ef5e087477636164e3b1bd119e62b62b2d516d04b33;Path=/;HttpOnly;SameSite=None;Secure;Domain=prod-04.westus3.logic.azure.com"
										},
										{
											"key": "Strict-Transport-Security",
											"value": "max-age=31536000; includeSubDomains"
										},
										{
											"key": "x-ms-workflow-run-id",
											"value": "08585023079845210699477700407CU30"
										},
										{
											"key": "x-ms-correlation-id",
											"value": "d2358001-e293-45cd-809f-535faa8bcd47"
										},
										{
											"key": "x-ms-client-tracking-id",
											"value": "08585023079845210699477700407CU30"
										},
										{
											"key": "x-ms-trigger-history-name",
											"value": "08585023079845210699477700407CU30"
										},
										{
											"key": "x-ms-execution-location",
											"value": "westus3"
										},
										{
											"key": "x-ms-workflow-system-id",
											"value": "/locations/westus3/scaleunits/prod-04/workflows/86c7b0688cb44dd6934a78279b875e36"
										},
										{
											"key": "x-ms-workflow-id",
											"value": "86c7b0688cb44dd6934a78279b875e36"
										},
										{
											"key": "x-ms-workflow-version",
											"value": "08585023080253567980"
										},
										{
											"key": "x-ms-workflow-name",
											"value": "Joonto_Numbers_v1.0_Purchase"
										},
										{
											"key": "x-ms-tracking-id",
											"value": "d2358001-e293-45cd-809f-535faa8bcd47"
										},
										{
											"key": "x-ms-ratelimit-burst-remaining-workflow-writes",
											"value": "4499"
										},
										{
											"key": "x-ms-ratelimit-remaining-workflow-download-contentsize",
											"value": "322121551"
										},
										{
											"key": "x-ms-ratelimit-remaining-workflow-upload-contentsize",
											"value": "322121581"
										},
										{
											"key": "x-ms-ratelimit-time-remaining-directapirequests",
											"value": "29999388"
										},
										{
											"key": "x-ms-request-id",
											"value": "westus3:d2358001-e293-45cd-809f-535faa8bcd47"
										},
										{
											"key": "Date",
											"value": "Mon, 06 Nov 2023 19:28:20 GMT"
										}
									],
									"cookie": [],
									"body": "{\n    \"OrderDate\": \"2025-05-14T18:56:33.0005512+00:00\",\n    \"OrderId\": \"JNUOID-ad65e0d6-dbc6-41bd-bc51-736fb6a1e20a\",\n    \"OrderStatus\": \"Submitted\",\n    \"PhoneNumbersRequested\": [\n        {\n            \"Number\": \"+12164278934\"\n        },\n        {\n            \"Number\": \"+12232233156\"\n        },\n        {\n            \"Number\": \"+12232233122\"\n        },\n        {\n            \"Number\": \"+12232233111\"\n        }\n    ]\n}"
								}
							]
						},
						{
							"name": "Numbers - Port In",
							"request": {
								"method": "POST",
								"header": [],
								"body": {
									"mode": "raw",
									"raw": "{\n\"PortInNumber\": \"+17746996223\",\n\"CurrentCarrierName\": \"Verizon\",\n\"CurrentAccountNumber\": \"54321\",\n\"CurrentAccountPassword\" : \"1234\",\n\"CurrentBillingAddress\": {\n\"Street1\": \"2701 N Thanksgiving Way\",\n\"Street2\": \"Suite 202\",\n\"City\": \"Lehi\",\n\"State\": \"UT\",\n\"Zip\": \"84043\"\n    }\n\n}",
									"options": {
										"raw": {
											"language": "json"
										}
									}
								},
								"url": {
									"raw": "https://api.telegent.com/v1.0/numbers/portin",
									"protocol": "https",
									"host": [
										"api",
										"telegent",
										"com"
									],
									"path": [
										"v1.0",
										"numbers",
										"portin"
									]
								},
								"description": "# Phone Number Port-In\n\n## POST /numbers/port-in\n\nInitiates a port-in request to transfer a phone number from another carrier to our service.\n\n### Request\n\n#### Headers\n\n```\nContent-Type: application/json\nAuthorization: Bearer {your_api_token}\n\n ```\n\n#### Body Parameters\n\n| Parameter | Type | Required | Description |\n| --- | --- | --- | --- |\n| `PortInNumber` | string | Yes | Phone number to port in (E.164 format) |\n| `CurrentCarrierName` | string | Yes | Name of the current carrier |\n| `CurrentAccountNumber` | string | Yes | Account number with the current carrier |\n| `CurrentAccountPassword` | string | Yes | Account PIN or password with the current carrier |\n| `CurrentBillingAddress` | object | Yes | Billing address on file with the current carrier |\n| `CurrentBillingAddress.Street1` | string | Yes | Primary street address |\n| `CurrentBillingAddress.Street2` | string | No | Secondary address information (suite, unit, etc.) |\n| `CurrentBillingAddress.City` | string | Yes | City name |\n| `CurrentBillingAddress.State` | string | Yes | State or province (2-letter code for US states) |\n| `CurrentBillingAddress.Zip` | string | Yes | Postal or ZIP code |\n\n### Sample Request\n\n``` json\n{\n    \"PortInNumber\": \"+17746996223\",\n    \"CurrentCarrierName\": \"Verizon\",\n    \"CurrentAccountNumber\": \"54321\",\n    \"CurrentAccountPassword\": \"1234\",\n    \"CurrentBillingAddress\": {\n        \"Street1\": \"2701 N Thanksgiving Way\",\n        \"Street2\": \"Suite 202\",\n        \"City\": \"Lehi\",\n        \"State\": \"UT\",\n        \"Zip\": \"84043\"\n    }\n}\n\n ```\n\n### Responses\n\n#### 200 OK: Success\n\nReturns details about the initiated port-in request.\n\n``` json\n{\n    \"Status\": \"Pending\",\n    \"PhoneNumber\": \"+17746996223\",\n    \"OrderDate\": \"2025-05-15T20:09:57.4274117Z\",\n    \"OrderId\": \"JNUOID-1729cc0b-992e-4e6f-a6ec-3d3a541d8e5d\"\n}\n\n ```\n\n##### Response Fields\n\n| Field | Type | Description |\n| --- | --- | --- |\n| `Status` | string | Current status of the port-in request (e.g., \"Pending\", \"Approved\", \"Rejected\") |\n| `PhoneNumber` | string | The phone number being ported in (E.164 format) |\n| `OrderDate` | string | Timestamp when the port-in request was submitted (ISO 8601 format) |\n| `OrderId` | string | Unique identifier for the port-in request |\n\n#### 400 Bad Request: Validation Error\n\n``` json\n{\n    \"Type\": \"https://tools.ietf.org/html/rfc7231#section-6.5.1\",\n    \"Title\": \"One or more validation errors occurred.\",\n    \"Status\": 400,\n    \"Errors\": {\n        \"$.PortInNumber\": [\"Invalid phone number format. Must be in E.164 format.\"]\n    },\n    \"TraceId\": \"00-1234abcd5678efgh-abcdef123456-00\"\n}\n\n ```\n\n#### 401 Unauthorized: Authentication Error\n\n``` json\n{\n    \"Type\": \"https://tools.ietf.org/html/rfc7235#section-3.1\",\n    \"Title\": \"Unauthorized\",\n    \"Status\": 401,\n    \"TraceId\": \"00-1234abcd5678efgh-abcdef123456-00\"\n}\n\n ```\n\n### Usage Notes\n\n- All account details must precisely match the records of the current carrier to avoid rejection.\n    \n- Port-in requests typically take 2-10 business days to complete depending on the carrier.\n    \n- You will receive notifications about status changes to your port-in request.\n    \n- The phone number will remain active with the current carrier until the port-in is completed.\n    \n- After successful port-in, you will need to configure routing for the number using the MessageRouteId and VoiceRouteId parameters.\n    \n- Port-in requests submitted after 4:00 PM local time may not be processed until the next business day.\n    \n\n### Try It\n\n```\ncurl -X POST https://api.example.com/numbers/port-in \\\n  -H \"Content-Type: application/json\" \\\n  -H \"Authorization: Bearer YOUR_API_TOKEN\" \\\n  -d '{\n    \"PortInNumber\": \"+17746996223\",\n    \"CurrentCarrierName\": \"Verizon\",\n    \"CurrentAccountNumber\": \"54321\",\n    \"CurrentAccountPassword\": \"1234\",\n    \"CurrentBillingAddress\": {\n        \"Street1\": \"2701 N Thanksgiving Way\",\n        \"Street2\": \"Suite 202\",\n        \"City\": \"Lehi\",\n        \"State\": \"UT\",\n        \"Zip\": \"84043\"\n    }\n}'\n\n ```"
							},
							"response": [
								{
									"name": "Numbers - Port In",
									"originalRequest": {
										"method": "POST",
										"header": [],
										"body": {
											"mode": "raw",
											"raw": "{\n\"PortInNumber\": \"+17746996223\",\n\"CurrentCarrierName\": \"Verizon\",\n\"CurrentAccountNumber\": \"54321\",\n\"CurrentAccountPassword\" : \"1234\",\n\"CurrentBillingAddress\": {\n\"Street1\": \"2701 N Thanksgiving Way\",\n\"Street2\": \"Suite 202\",\n\"City\": \"Lehi\",\n\"State\": \"UT\",\n\"Zip\": \"84043\"\n    }\n\n}",
											"options": {
												"raw": {
													"language": "json"
												}
											}
										},
										"url": {
											"raw": "https://api.telegent.com/v1.0/numbers/portin",
											"protocol": "https",
											"host": [
												"api",
												"telegent",
												"com"
											],
											"path": [
												"v1.0",
												"numbers",
												"portin"
											]
										}
									},
									"status": "OK",
									"code": 200,
									"_postman_previewlanguage": "json",
									"header": [
										{
											"key": "Cache-Control",
											"value": "no-cache"
										},
										{
											"key": "Pragma",
											"value": "no-cache"
										},
										{
											"key": "Transfer-Encoding",
											"value": "chunked"
										},
										{
											"key": "Content-Type",
											"value": "application/json"
										},
										{
											"key": "Content-Encoding",
											"value": "gzip"
										},
										{
											"key": "Expires",
											"value": "-1"
										},
										{
											"key": "Vary",
											"value": "Accept-Encoding"
										},
										{
											"key": "Set-Cookie",
											"value": "ARRAffinity=8cb9eb8a9c8e49bb32964ef5e087477636164e3b1bd119e62b62b2d516d04b33;Path=/;HttpOnly;Secure;Domain=prod-04.westus3.logic.azure.com"
										},
										{
											"key": "Set-Cookie",
											"value": "ARRAffinitySameSite=8cb9eb8a9c8e49bb32964ef5e087477636164e3b1bd119e62b62b2d516d04b33;Path=/;HttpOnly;SameSite=None;Secure;Domain=prod-04.westus3.logic.azure.com"
										},
										{
											"key": "Strict-Transport-Security",
											"value": "max-age=31536000; includeSubDomains"
										},
										{
											"key": "x-ms-workflow-run-id",
											"value": "08585023079845210699477700407CU30"
										},
										{
											"key": "x-ms-correlation-id",
											"value": "d2358001-e293-45cd-809f-535faa8bcd47"
										},
										{
											"key": "x-ms-client-tracking-id",
											"value": "08585023079845210699477700407CU30"
										},
										{
											"key": "x-ms-trigger-history-name",
											"value": "08585023079845210699477700407CU30"
										},
										{
											"key": "x-ms-execution-location",
											"value": "westus3"
										},
										{
											"key": "x-ms-workflow-system-id",
											"value": "/locations/westus3/scaleunits/prod-04/workflows/86c7b0688cb44dd6934a78279b875e36"
										},
										{
											"key": "x-ms-workflow-id",
											"value": "86c7b0688cb44dd6934a78279b875e36"
										},
										{
											"key": "x-ms-workflow-version",
											"value": "08585023080253567980"
										},
										{
											"key": "x-ms-workflow-name",
											"value": "Joonto_Numbers_v1.0_Purchase"
										},
										{
											"key": "x-ms-tracking-id",
											"value": "d2358001-e293-45cd-809f-535faa8bcd47"
										},
										{
											"key": "x-ms-ratelimit-burst-remaining-workflow-writes",
											"value": "4499"
										},
										{
											"key": "x-ms-ratelimit-remaining-workflow-download-contentsize",
											"value": "322121551"
										},
										{
											"key": "x-ms-ratelimit-remaining-workflow-upload-contentsize",
											"value": "322121581"
										},
										{
											"key": "x-ms-ratelimit-time-remaining-directapirequests",
											"value": "29999388"
										},
										{
											"key": "x-ms-request-id",
											"value": "westus3:d2358001-e293-45cd-809f-535faa8bcd47"
										},
										{
											"key": "Date",
											"value": "Mon, 06 Nov 2023 19:28:20 GMT"
										}
									],
									"cookie": [],
									"body": "{\n    \"OrderId\": \"JNOID-ddbaad7c-38c8-4cb4-bf0d-87ed9064f021\",\n    \"OrderDate\": \"2025-05-14T18:56:33.0005512+00:00\",\n    \"Status\": \"Pending\",\n    \"PhoneNumber\": \"+17746996223\" \n}\n"
								}
							]
						},
						{
							"name": "Numbers - Port Out",
							"event": [
								{
									"listen": "test",
									"script": {
										"exec": [
											"// Check for Pascal casing on request body properties",
											"pm.test(\"Request body properties are in Pascal case\", function () {",
											"    var requestBody = pm.request.json();",
											"    for (var key in requestBody) {",
											"        pm.expect(/^[A-Z][a-z0-9]*$/.test(key)).to.be.true(`Property \"${key}\" is not in Pascal case`);",
											"    }",
											"});",
											""
										],
										"type": "text/javascript",
										"packages": {}
									}
								}
							],
							"request": {
								"auth": {
									"type": "bearer",
									"bearer": [
										{
											"key": "token",
											"value": "{{Token}}",
											"type": "string"
										}
									]
								},
								"method": "POST",
								"header": [],
								"body": {
									"mode": "raw",
									"raw": "{\n        \"PortOutNumber\": \"+17746996223\",\n        \"PortOutPIN\": \"1234\"\n}",
									"options": {
										"raw": {
											"language": "json"
										}
									}
								},
								"url": {
									"raw": "https://api.telegent.com/v1.0/numbers/portout",
									"protocol": "https",
									"host": [
										"api",
										"telegent",
										"com"
									],
									"path": [
										"v1.0",
										"numbers",
										"portout"
									]
								},
								"description": "# Port Out Number\n\nThis endpoint allows you to initiate a port-out request for a phone number.\n\n## Request\n\n- Method: POST\n    \n- URL: `https://api.telegent.com/v1.0/numbers/portout`\n    \n- Headers:\n    \n    - Content-Type: application/json\n        \n\n### Request Body\n\n- `PortOutNumber` (string): The phone number to be ported out.\n    \n- `PortOutPIN` (string): The PIN for the port-out request.\n    \n\n## Response\n\nThe response is in the form of a JSON schema:\n\n``` json\n{\n  \"type\": \"object\",\n  \"properties\": {\n    \"OrderId\": {\n      \"type\": \"string\"\n    },\n    \"PhoneNumber\": {\n      \"type\": \"string\"\n    },\n    \"Status\": {\n      \"type\": \"string\"\n    },\n    \"OrderDate\": {\n      \"type\": \"string\"\n    }\n  }\n}\n\n ```\n\n## Test\n\nYou can create a test to check for Pascal casing on all inputs and outputs in the request and response."
							},
							"response": [
								{
									"name": "Numbers - Port Out",
									"originalRequest": {
										"method": "POST",
										"header": [],
										"body": {
											"mode": "raw",
											"raw": "{\n        \"PortOutNumber\": \"+17746996223\",\n        \"PortOutPIN\": \"1234\"\n}",
											"options": {
												"raw": {
													"language": "json"
												}
											}
										},
										"url": {
											"raw": "https://api.telegent.com/v1.0/numbers/portout",
											"protocol": "https",
											"host": [
												"api",
												"telegent",
												"com"
											],
											"path": [
												"v1.0",
												"numbers",
												"portout"
											]
										}
									},
									"status": "OK",
									"code": 200,
									"_postman_previewlanguage": "json",
									"header": [
										{
											"key": "Cache-Control",
											"value": "no-cache"
										},
										{
											"key": "Pragma",
											"value": "no-cache"
										},
										{
											"key": "Transfer-Encoding",
											"value": "chunked"
										},
										{
											"key": "Content-Type",
											"value": "application/json"
										},
										{
											"key": "Content-Encoding",
											"value": "gzip"
										},
										{
											"key": "Expires",
											"value": "-1"
										},
										{
											"key": "Vary",
											"value": "Accept-Encoding"
										},
										{
											"key": "Set-Cookie",
											"value": "ARRAffinity=8cb9eb8a9c8e49bb32964ef5e087477636164e3b1bd119e62b62b2d516d04b33;Path=/;HttpOnly;Secure;Domain=prod-04.westus3.logic.azure.com"
										},
										{
											"key": "Set-Cookie",
											"value": "ARRAffinitySameSite=8cb9eb8a9c8e49bb32964ef5e087477636164e3b1bd119e62b62b2d516d04b33;Path=/;HttpOnly;SameSite=None;Secure;Domain=prod-04.westus3.logic.azure.com"
										},
										{
											"key": "Strict-Transport-Security",
											"value": "max-age=31536000; includeSubDomains"
										},
										{
											"key": "x-ms-workflow-run-id",
											"value": "08585023079845210699477700407CU30"
										},
										{
											"key": "x-ms-correlation-id",
											"value": "d2358001-e293-45cd-809f-535faa8bcd47"
										},
										{
											"key": "x-ms-client-tracking-id",
											"value": "08585023079845210699477700407CU30"
										},
										{
											"key": "x-ms-trigger-history-name",
											"value": "08585023079845210699477700407CU30"
										},
										{
											"key": "x-ms-execution-location",
											"value": "westus3"
										},
										{
											"key": "x-ms-workflow-system-id",
											"value": "/locations/westus3/scaleunits/prod-04/workflows/86c7b0688cb44dd6934a78279b875e36"
										},
										{
											"key": "x-ms-workflow-id",
											"value": "86c7b0688cb44dd6934a78279b875e36"
										},
										{
											"key": "x-ms-workflow-version",
											"value": "08585023080253567980"
										},
										{
											"key": "x-ms-workflow-name",
											"value": "Joonto_Numbers_v1.0_Purchase"
										},
										{
											"key": "x-ms-tracking-id",
											"value": "d2358001-e293-45cd-809f-535faa8bcd47"
										},
										{
											"key": "x-ms-ratelimit-burst-remaining-workflow-writes",
											"value": "4499"
										},
										{
											"key": "x-ms-ratelimit-remaining-workflow-download-contentsize",
											"value": "322121551"
										},
										{
											"key": "x-ms-ratelimit-remaining-workflow-upload-contentsize",
											"value": "322121581"
										},
										{
											"key": "x-ms-ratelimit-time-remaining-directapirequests",
											"value": "29999388"
										},
										{
											"key": "x-ms-request-id",
											"value": "westus3:d2358001-e293-45cd-809f-535faa8bcd47"
										},
										{
											"key": "Date",
											"value": "Mon, 06 Nov 2023 19:28:20 GMT"
										}
									],
									"cookie": [],
									"body": "{\n    \"OrderId\": \"JNOID-ddbaad7c-38c8-4cb4-bf0d-87ed9064f021\",\n    \"OrderDate\": \"2025-05-14T18:56:33.0005512+00:00\",\n    \"Status\": \"Pending\",\n    \"PhoneNumber\": \"+17746996223\"\n}"
								}
							]
						},
						{
							"name": "Order ID Details",
							"event": [
								{
									"listen": "test",
									"script": {
										"exec": [
											"pm.test(\"All output keys are PascalCase\", function () {",
											"    const jsonData = pm.response.json();",
											"    const keys = Object.keys(jsonData);",
											"    keys.forEach(key => {",
											"        pm.expect(key).to.match(/^[A-Z][a-z0-9]*([A-Z][a-z0-9]*)*$/);",
											"    });",
											"});"
										],
										"type": "text/javascript",
										"packages": {}
									}
								}
							],
							"request": {
								"method": "GET",
								"header": [],
								"url": {
									"raw": "https://api.telegent.com/v1.0/numbers/order?OrderId=JNUOID-19b3d376-2440-477f-a3dc-c91a36989316",
									"protocol": "https",
									"host": [
										"api",
										"telegent",
										"com"
									],
									"path": [
										"v1.0",
										"numbers",
										"order"
									],
									"query": [
										{
											"key": "OrderId",
											"value": "JNUOID-19b3d376-2440-477f-a3dc-c91a36989316"
										}
									]
								},
								"description": "# Phone Number Order Status\n\n## GET /numbers/order\n\nRetrieves details of a phone number order based on the provided OrderId.\n\n### Request\n\n#### Headers\n\n```\nAuthorization: Bearer {your_api_token}\n```\n\n#### Query Parameters\n\n| Parameter | Type | Required | Description |\n|-----------|------|----------|-------------|\n| `OrderId` | string | Yes | Unique identifier of the order to retrieve |\n\n### Sample Request\n\n```\nGET https://api.telegent.com/v1.0/numbers/order?OrderId=JNUOID-19b3d376-2440-477f-a3dc-c91a36989316\n```\n\n### Responses\n\n#### 200 OK: Success\n\nReturns details about the specified order.\n\n```json\n{\n    \"OrderDate\": \"2025-05-10T15:38:19.113\",\n    \"OrderId\": \"JNUOID-19b3d376-2440-477f-a3dc-c91a36989316\",\n    \"OrderStatus\": \"Submitted\",\n    \"OrderType\": \"Provision\",\n    \"PhoneNumbersOrdered\": [\n        {\n            \"Number\": \"+12164278934\"\n        },\n        {\n            \"Number\": \"+12232233156\"\n        },\n        {\n            \"Number\": \"+12232233122\"\n        },\n        {\n            \"Number\": \"+12232233111\"\n        }\n    ]\n}\n```\n\n##### Response Fields\n\n| Field | Type | Description |\n|-------|------|-------------|\n| `OrderDate` | string | Timestamp when the order was submitted (ISO 8601 format) |\n| `OrderId` | string | Unique identifier for the order |\n| `OrderStatus` | string | Current status of the order (e.g., \"Submitted\", \"Processing\", \"Completed\", \"Failed\") |\n| `OrderType` | string | Type of order (e.g., \"Provision\", \"PortIn\", \"Release\") |\n| `PhoneNumbersOrdered` | array | List of phone numbers included in the order |\n\n#### 404 Not Found: Order Not Found\n\n```json\n{\n    \"Type\": \"https://tools.ietf.org/html/rfc7231#section-6.5.4\",\n    \"Title\": \"Not Found\",\n    \"Status\": 404,\n    \"Detail\": \"Order with ID 'JNUOID-19b3d376-2440-477f-a3dc-c91a36989316' was not found.\",\n    \"TraceId\": \"00-1234abcd5678efgh-abcdef123456-00\"\n}\n```\n\n#### 401 Unauthorized: Authentication Error\n\n```json\n{\n    \"Type\": \"https://tools.ietf.org/html/rfc7235#section-3.1\",\n    \"Title\": \"Unauthorized\",\n    \"Status\": 401,\n    \"TraceId\": \"00-1234abcd5678efgh-abcdef123456-00\"\n}\n```\n\n### Usage Notes\n\n- Use this endpoint to check the status of previously submitted number orders.\n- The `OrderStatus` field indicates the current stage in the order lifecycle.\n- For orders with status \"Failed\", additional error details may be available in the response.\n- Phone numbers in \"Completed\" orders are ready to use with the configured routes.\n- OrderId values are case-sensitive and must be provided exactly as returned from the original order request.\n\n### Try It\n\n```\ncurl -X GET \"https://api.telegent.com/v1.0/numbers/order?OrderId=JNUOID-19b3d376-2440-477f-a3dc-c91a36989316\" \\\n  -H \"Authorization: Bearer YOUR_API_TOKEN\"\n```"
							},
							"response": [
								{
									"name": "Order ID Details",
									"originalRequest": {
										"method": "GET",
										"header": [],
										"url": {
											"raw": "https://api.telegent.com/v1.0/numbers/order?OrderId=JNOID-ddbaad7c-38c8-4cb4-bf0d-87ed9064f021",
											"protocol": "https",
											"host": [
												"api",
												"telegent",
												"com"
											],
											"path": [
												"v1.0",
												"numbers",
												"order"
											],
											"query": [
												{
													"key": "OrderId",
													"value": "JNOID-ddbaad7c-38c8-4cb4-bf0d-87ed9064f021"
												}
											]
										}
									},
									"status": "OK",
									"code": 200,
									"_postman_previewlanguage": "json",
									"header": [
										{
											"key": "Cache-Control",
											"value": "no-cache"
										},
										{
											"key": "Pragma",
											"value": "no-cache"
										},
										{
											"key": "Transfer-Encoding",
											"value": "chunked"
										},
										{
											"key": "Content-Type",
											"value": "application/json"
										},
										{
											"key": "Content-Encoding",
											"value": "gzip"
										},
										{
											"key": "Expires",
											"value": "-1"
										},
										{
											"key": "Vary",
											"value": "Accept-Encoding"
										},
										{
											"key": "Set-Cookie",
											"value": "ARRAffinity=4e578cbe1efe6783ea8ca73836b126e532ae76861f661df353db6f787c115815;Path=/;HttpOnly;Secure;Domain=prod-04.westus3.logic.azure.com"
										},
										{
											"key": "Set-Cookie",
											"value": "ARRAffinitySameSite=4e578cbe1efe6783ea8ca73836b126e532ae76861f661df353db6f787c115815;Path=/;HttpOnly;SameSite=None;Secure;Domain=prod-04.westus3.logic.azure.com"
										},
										{
											"key": "Strict-Transport-Security",
											"value": "max-age=31536000; includeSubDomains"
										},
										{
											"key": "x-ms-workflow-run-id",
											"value": "08585023406819457708984635338CU03"
										},
										{
											"key": "x-ms-correlation-id",
											"value": "2ce040ab-df97-45c7-b24f-9b61851c6048"
										},
										{
											"key": "x-ms-client-tracking-id",
											"value": "08585023406819457708984635338CU03"
										},
										{
											"key": "x-ms-trigger-history-name",
											"value": "08585023406819457708984635338CU03"
										},
										{
											"key": "x-ms-execution-location",
											"value": "westus3"
										},
										{
											"key": "x-ms-workflow-system-id",
											"value": "/locations/westus3/scaleunits/prod-04/workflows/86c7b0688cb44dd6934a78279b875e36"
										},
										{
											"key": "x-ms-workflow-id",
											"value": "86c7b0688cb44dd6934a78279b875e36"
										},
										{
											"key": "x-ms-workflow-version",
											"value": "08585023407143927890"
										},
										{
											"key": "x-ms-workflow-name",
											"value": "Joonto_Numbers_v1.0_Purchase"
										},
										{
											"key": "x-ms-tracking-id",
											"value": "2ce040ab-df97-45c7-b24f-9b61851c6048"
										},
										{
											"key": "x-ms-ratelimit-burst-remaining-workflow-writes",
											"value": "4499"
										},
										{
											"key": "x-ms-ratelimit-remaining-workflow-download-contentsize",
											"value": "322121611"
										},
										{
											"key": "x-ms-ratelimit-remaining-workflow-upload-contentsize",
											"value": "322121532"
										},
										{
											"key": "x-ms-ratelimit-time-remaining-directapirequests",
											"value": "29999093"
										},
										{
											"key": "x-ms-request-id",
											"value": "westus3:2ce040ab-df97-45c7-b24f-9b61851c6048"
										},
										{
											"key": "Date",
											"value": "Mon, 06 Nov 2023 10:23:24 GMT"
										}
									],
									"cookie": [],
									"body": "{\n    \"OrderDate\": \"2025-05-10T15:38:19.113\",\n    \"OrderId\": \"JNUOID-19b3d376-2440-477f-a3dc-c91a36989316\",\n    \"OrderStatus\": \"Submitted\",\n    \"OrderType\": \"Provision\",\n    \"PhoneNumbersOrdered\": [\n        {\n            \"Number\": \"+12164278934\"\n        },\n        {\n            \"Number\": \"+12232233156\"\n        },\n        {\n            \"Number\": \"+12232233122\"\n        },\n        {\n            \"Number\": \"+12232233111\"\n        }\n    ]\n}"
								}
							]
						},
						{
							"name": "Numbers Inventory",
							"request": {
								"method": "GET",
								"header": [],
								"url": {
									"raw": "https://api.telegent.com/v1.0/numbers/inventory?Filter=All",
									"protocol": "https",
									"host": [
										"api",
										"telegent",
										"com"
									],
									"path": [
										"v1.0",
										"numbers",
										"inventory"
									],
									"query": [
										{
											"key": "Filter",
											"value": "All"
										}
									]
								},
								"description": "# Get Numbers Inventory\n\nThis endpoint retrieves the inventory of phone numbers based on the specified filter.\n\n## Request\n\n- Method: `GET`\n    \n- URL: `https://api.telegent.com/v1.0/numbers/inventory`\n    \n- Query Parameter:\n    \n    - Filter (string, required): Specifies the filter to be applied to the inventory. Possible values include \"All\".\n        \n\n## Response\n\n- AccountId (number): The ID of the account.\n    \n- TotalCount (number): The total count of phone numbers in the inventory.\n    \n- Filter (string): The filter applied to the inventory.\n    \n- PhoneNumbers (array): An array of phone number objects with the following properties:\n    \n    - Number (number): The phone number.\n        \n    - Jnid (string): The JNID associated with the number.\n        \n    - OrderId (string): The order ID associated with the number.\n        \n    - NumberType (string): The type of the number.\n        \n    - SmsEnabled (string): Indicates if SMS is enabled for the number.\n        \n    - ProductId (string): The product ID associated with the number.\n        \n    - VoiceEnabled (string): Indicates if voice is enabled for the number.\n        \n    - SmsUrl (string): The URL for SMS.\n        \n    - SmsUrlMethod (string): The method for SMS URL.\n        \n    - VoiceRouteId (string): The route ID for voice.\n        \n    - Status (string): The status of the number.\n        \n    - DatePurchased (string): The date when the number was purchased.\n        \n\n## Test\n\nThe test should validate that all input and output properties are in PascalCase format."
							},
							"response": [
								{
									"name": "Numbers Inventory",
									"originalRequest": {
										"method": "GET",
										"header": [],
										"url": {
											"raw": "https://api.telegent.com/v1.0/numbers/inventory?filter=All",
											"protocol": "https",
											"host": [
												"api",
												"telegent",
												"com"
											],
											"path": [
												"v1.0",
												"numbers",
												"inventory"
											],
											"query": [
												{
													"key": "filter",
													"value": "All"
												}
											]
										}
									},
									"status": "OK",
									"code": 200,
									"_postman_previewlanguage": "json",
									"header": [
										{
											"key": "Cache-Control",
											"value": "no-cache"
										},
										{
											"key": "Pragma",
											"value": "no-cache"
										},
										{
											"key": "Transfer-Encoding",
											"value": "chunked"
										},
										{
											"key": "Content-Type",
											"value": "application/json"
										},
										{
											"key": "Content-Encoding",
											"value": "gzip"
										},
										{
											"key": "Expires",
											"value": "-1"
										},
										{
											"key": "Vary",
											"value": "Accept-Encoding"
										},
										{
											"key": "Set-Cookie",
											"value": "ARRAffinity=4e578cbe1efe6783ea8ca73836b126e532ae76861f661df353db6f787c115815;Path=/;HttpOnly;Secure;Domain=prod-04.westus3.logic.azure.com"
										},
										{
											"key": "Set-Cookie",
											"value": "ARRAffinitySameSite=4e578cbe1efe6783ea8ca73836b126e532ae76861f661df353db6f787c115815;Path=/;HttpOnly;SameSite=None;Secure;Domain=prod-04.westus3.logic.azure.com"
										},
										{
											"key": "Strict-Transport-Security",
											"value": "max-age=31536000; includeSubDomains"
										},
										{
											"key": "x-ms-workflow-run-id",
											"value": "08585023406819457708984635338CU03"
										},
										{
											"key": "x-ms-correlation-id",
											"value": "2ce040ab-df97-45c7-b24f-9b61851c6048"
										},
										{
											"key": "x-ms-client-tracking-id",
											"value": "08585023406819457708984635338CU03"
										},
										{
											"key": "x-ms-trigger-history-name",
											"value": "08585023406819457708984635338CU03"
										},
										{
											"key": "x-ms-execution-location",
											"value": "westus3"
										},
										{
											"key": "x-ms-workflow-system-id",
											"value": "/locations/westus3/scaleunits/prod-04/workflows/86c7b0688cb44dd6934a78279b875e36"
										},
										{
											"key": "x-ms-workflow-id",
											"value": "86c7b0688cb44dd6934a78279b875e36"
										},
										{
											"key": "x-ms-workflow-version",
											"value": "08585023407143927890"
										},
										{
											"key": "x-ms-workflow-name",
											"value": "Joonto_Numbers_v1.0_Purchase"
										},
										{
											"key": "x-ms-tracking-id",
											"value": "2ce040ab-df97-45c7-b24f-9b61851c6048"
										},
										{
											"key": "x-ms-ratelimit-burst-remaining-workflow-writes",
											"value": "4499"
										},
										{
											"key": "x-ms-ratelimit-remaining-workflow-download-contentsize",
											"value": "322121611"
										},
										{
											"key": "x-ms-ratelimit-remaining-workflow-upload-contentsize",
											"value": "322121532"
										},
										{
											"key": "x-ms-ratelimit-time-remaining-directapirequests",
											"value": "29999093"
										},
										{
											"key": "x-ms-request-id",
											"value": "westus3:2ce040ab-df97-45c7-b24f-9b61851c6048"
										},
										{
											"key": "Date",
											"value": "Mon, 06 Nov 2023 10:23:24 GMT"
										}
									],
									"cookie": [],
									"body": "{\n    \"AccountId\": \"DID-1e8939ab-3f3c-4db1-89d7-956d80fdfse88\",\n    \"TotalResults\": 346,\n    \"PageNumber\": 1,\n    \"Filter\": \"Active\",\n    \"PhoneNumbers\": [\n        {\n            \"Number\": \"+18015555555\",\n            \"Tnid\": \"TNID-9772956561858\",\n            \"OrderId\": \"TNOID-ddbaad7c-38c8-4cb4-bf0d-87ed9064f021\",\n            \"NumberType\": \"mobile\",\n            \"MessageEnabled\": true,\n            \"MessageType\": \"p2p\",\n            \"Classification\": \"MVNO\",\n            \"VoiceEnabled\": true,\n            \"MessageRouteId\": \"MRID-73af1e73-d7b3-4696-bdd9-5b407d9e99ee\",\n            \"VoiceRouteId\": \"CRID-4dec6beb-3985-444b-8c06-8baa5jjvawe\",\n            \"Status\": \"Active\",\n            \"OriginalDatePurchased\": \"02/05/2023\",\n            \"AssignedSubscriberId\": \"SID-d7b3-4696-bdd9-5b407d9e99ee-3985-444b8d\",\n            \"Iccid\": \"8901240397190556232\",\n            \"Cnam\": \"ABC Corp\"\n        },\n        {\n            \"Number\": \"+18015555556\",\n            \"Tnid\": \"TNID-8772956561858\",\n            \"OrderId\": \"TNOID-ddbaad7c-38c8-4cb4-bf0d-87ed9064f021\",\n            \"NumberType\": \"mobile\",\n            \"MessageEnabled\": \"true\",\n            \"MessageType\": \"a2p\",\n            \"Classification\": \"MVNO\",\n            \"VoiceEnabled\": \"true\",\n            \"MessageRouteId\": \"MRID-73af1e73-d7b3-4696-bdd9-5b407d9e99ee\",\n            \"VoiceRouteId\": \"CRID-4dec6beb-3985-444b-8c06-8baa5jjvawe\",\n            \"Status\": \"Active\",\n            \"OriginalDatePurchased\": \"02/05/2023\",\n            \"AssignedSubscriberId\": \"SID-d7b3-4696-bdd9-5b407d9e99ee-3985-444b7d\",\n            \"Iccid\": \"8901240397190555232\",\n            \"Cnam\": \"ABC Corp\"\n        }\n    ]\n}"
								}
							]
						},
						{
							"name": "Number Details",
							"request": {
								"method": "GET",
								"header": [],
								"url": {
									"raw": "https://api.telegent.com/v1.0/numbers?PhoneNumber=+18018018011",
									"protocol": "https",
									"host": [
										"api",
										"telegent",
										"com"
									],
									"path": [
										"v1.0",
										"numbers"
									],
									"query": [
										{
											"key": "PhoneNumber",
											"value": "+18018018011"
										}
									]
								},
								"description": "# Phone Number Details\n\n## GET /numbers\n\nRetrieves detailed information about a specific phone number in your inventory.\n\n### Request\n\n#### Headers\n\n```\nAuthorization: Bearer {your_api_token}\n```\n\n#### Query Parameters\n\n| Parameter | Type | Required | Description |\n|-----------|------|----------|-------------|\n| `PhoneNumber` | string | Yes | The phone number to retrieve details for (in E.164 format) |\n\n### Sample Request\n\n```\nGET https://api.telegent.com/v1.0/numbers?PhoneNumber=+18018018011\n```\n\n### Responses\n\n#### 200 OK: Success\n\nReturns detailed information about the specified phone number.\n\n```json\n{\n    \"Number\": \"+18018018011\",\n    \"TNID\": \"TNID-kasjfljljlsadlfjlkhlkdhf\",\n    \"OrderId\": \"TNOID-ijljqljildfiiuoieui\",\n    \"NumberType\": \"Mobile\",\n    \"MessageEnabled\": true,\n    \"MessageRouteId\": \"MRID-6575d4d9-a10a-4b18-8936-4ac6dac73ac4\",\n    \"VoiceEnabled\": true,\n    \"Classification\": \"MVNO\",\n    \"MessageType\": \"A2P\",\n    \"VoiceRouteId\": \"T9992774\",\n    \"Status\": \"Active\",\n    \"OriginalDatePurchased\": null,\n    \"AssignedSubscriberId\": null,\n    \"Iccid\": \"8901240397190557414F\",\n    \"Cnam\": \"Bob's Shake Shack\"\n}\n```\n\n##### Response Fields\n\n| Field | Type | Description |\n|-------|------|-------------|\n| `Number` | string | The phone number in E.164 format |\n| `TNID` | string | Unique telephone number identifier |\n| `OrderId` | string | ID of the order that provisioned this number |\n| `NumberType` | string | Type of phone number (Mobile, Landline, Tollfree) |\n| `MessageEnabled` | boolean | Whether SMS/MMS messaging is enabled |\n| `MessageRouteId` | string | ID of the message routing configuration |\n| `VoiceEnabled` | boolean | Whether voice calling is enabled |\n| `Classification` | string | Carrier classification (MVNO, IOT) |\n| `MessageType` | string | Message classification (P2P, A2P) |\n| `VoiceRouteId` | string | ID of the voice routing configuration |\n| `Status` | string | Current status of the phone number |\n| `OriginalDatePurchased` | string | Date when the number was first provisioned (may be null) |\n| `AssignedSubscriberId` | string | ID of the subscriber assigned to this number (may be null) |\n| `Iccid` | string | SIM card identifier (if applicable) |\n| `Cnam` | string | Caller ID name associated with the number |\n\n#### 404 Not Found: Phone Number Not Found\n\n```json\n{\n    \"Type\": \"https://tools.ietf.org/html/rfc7231#section-6.5.4\",\n    \"Title\": \"Not Found\",\n    \"Status\": 404,\n    \"Detail\": \"Phone number '+18018018011' was not found in your inventory.\",\n    \"TraceId\": \"00-1234abcd5678efgh-abcdef123456-00\"\n}\n```\n\n#### 401 Unauthorized: Authentication Error\n\n```json\n{\n    \"Type\": \"https://tools.ietf.org/html/rfc7235#section-3.1\",\n    \"Title\": \"Unauthorized\",\n    \"Status\": 401,\n    \"TraceId\": \"00-1234abcd5678efgh-abcdef123456-00\"\n}\n```\n\n### Usage Notes\n\n- Use this endpoint to retrieve comprehensive details about a specific number in your inventory.\n- The phone number must be provided in E.164 format (with the country code and no spaces or special characters).\n- The `TNID` is a unique identifier for the telephone number that can be used in other API operations.\n- The `MessageRouteId` and `VoiceRouteId` identify the routing configurations for SMS/MMS and voice respectively.\n- The `Cnam` field shows the Caller ID name that will be displayed to recipients of calls from this number.\n\n### Try It\n\n```\ncurl -X GET \"https://api.telegent.com/v1.0/numbers?PhoneNumber=+18018018011\" \\\n  -H \"Authorization: Bearer YOUR_API_TOKEN\"\n```"
							},
							"response": [
								{
									"name": "Number Details",
									"originalRequest": {
										"method": "GET",
										"header": [],
										"url": {
											"raw": "https://api.telegent.com/v1.0/numbers?PhoneNumber=+18018018011",
											"protocol": "https",
											"host": [
												"api",
												"telegent",
												"com"
											],
											"path": [
												"v1.0",
												"numbers"
											],
											"query": [
												{
													"key": "PhoneNumber",
													"value": "+18018018011"
												}
											]
										}
									},
									"status": "OK",
									"code": 200,
									"_postman_previewlanguage": "json",
									"header": [
										{
											"key": "Cache-Control",
											"value": "no-cache"
										},
										{
											"key": "Pragma",
											"value": "no-cache"
										},
										{
											"key": "Transfer-Encoding",
											"value": "chunked"
										},
										{
											"key": "Content-Type",
											"value": "application/json"
										},
										{
											"key": "Content-Encoding",
											"value": "gzip"
										},
										{
											"key": "Expires",
											"value": "-1"
										},
										{
											"key": "Vary",
											"value": "Accept-Encoding"
										},
										{
											"key": "Set-Cookie",
											"value": "ARRAffinity=8cb9eb8a9c8e49bb32964ef5e087477636164e3b1bd119e62b62b2d516d04b33;Path=/;HttpOnly;Secure;Domain=prod-04.westus3.logic.azure.com"
										},
										{
											"key": "Set-Cookie",
											"value": "ARRAffinitySameSite=8cb9eb8a9c8e49bb32964ef5e087477636164e3b1bd119e62b62b2d516d04b33;Path=/;HttpOnly;SameSite=None;Secure;Domain=prod-04.westus3.logic.azure.com"
										},
										{
											"key": "Strict-Transport-Security",
											"value": "max-age=31536000; includeSubDomains"
										},
										{
											"key": "x-ms-workflow-run-id",
											"value": "08585023079845210699477700407CU30"
										},
										{
											"key": "x-ms-correlation-id",
											"value": "d2358001-e293-45cd-809f-535faa8bcd47"
										},
										{
											"key": "x-ms-client-tracking-id",
											"value": "08585023079845210699477700407CU30"
										},
										{
											"key": "x-ms-trigger-history-name",
											"value": "08585023079845210699477700407CU30"
										},
										{
											"key": "x-ms-execution-location",
											"value": "westus3"
										},
										{
											"key": "x-ms-workflow-system-id",
											"value": "/locations/westus3/scaleunits/prod-04/workflows/86c7b0688cb44dd6934a78279b875e36"
										},
										{
											"key": "x-ms-workflow-id",
											"value": "86c7b0688cb44dd6934a78279b875e36"
										},
										{
											"key": "x-ms-workflow-version",
											"value": "08585023080253567980"
										},
										{
											"key": "x-ms-workflow-name",
											"value": "Joonto_Numbers_v1.0_Purchase"
										},
										{
											"key": "x-ms-tracking-id",
											"value": "d2358001-e293-45cd-809f-535faa8bcd47"
										},
										{
											"key": "x-ms-ratelimit-burst-remaining-workflow-writes",
											"value": "4499"
										},
										{
											"key": "x-ms-ratelimit-remaining-workflow-download-contentsize",
											"value": "322121551"
										},
										{
											"key": "x-ms-ratelimit-remaining-workflow-upload-contentsize",
											"value": "322121581"
										},
										{
											"key": "x-ms-ratelimit-time-remaining-directapirequests",
											"value": "29999388"
										},
										{
											"key": "x-ms-request-id",
											"value": "westus3:d2358001-e293-45cd-809f-535faa8bcd47"
										},
										{
											"key": "Date",
											"value": "Mon, 06 Nov 2023 19:28:20 GMT"
										}
									],
									"cookie": [],
									"body": "{\n    \"Number\": \"+18018018011\",\n    \"TNID\": \"TNID-kasjfljljlsadlfjlkhlkdhf\",\n    \"OrderId\": \"TNOID-ijljqljildfiiuoieui\",\n    \"NumberType\": \"Mobile\",\n    \"MessageEnabled\": true,\n    \"MessageRouteId\": \"MRID-6575d4d9-a10a-4b18-8936-4ac6dac73ac4\",\n    \"VoiceEnabled\": true,\n    \"Classification\": \"MVNO\",\n    \"MessageType\": \"A2P\",\n    \"VoiceRouteId\": \"T9992774\",\n    \"Status\": \"Active\",\n    \"OriginalDatePurchased\": null,\n    \"AssignedSubscriberId\": null,\n    \"Iccid\": \"8901240397190557414F\",\n    \"Cnam\": \"Bob's Shake Shack\"\n}"
								}
							]
						},
						{
							"name": "Numbers Update",
							"request": {
								"method": "POST",
								"header": [],
								"body": {
									"mode": "raw",
									"raw": "{\n    \"Number\": \"+18018018011\", //required for updating specific number\n    \"MessageEnabled\": true,\n    \"MessageType\": \"p2p\",\n    \"Classification\": \"MVNO\",\n    \"VoiceEnabled\": true,\n    \"MessageRouteId\": \"MRID-73af1e73-d7b3-4696-bdd9-5b407d9e99ee\",\n    \"VoiceRouteId\": \"CRID-4dec6beb-3985-444b-8c06-8baa5jjvawe\",\n    \"AssignedSubscriberId\": \"SID-d7b3-4696-bdd9-5b407d9e99ee-3985-444b8d\",\n    \"Iccid\": \"8901240397190556232\",\n    \"Cnam\": \"ABC Corp\"\n}",
									"options": {
										"raw": {
											"language": "json"
										}
									}
								},
								"url": {
									"raw": "https://api.telegent.com/v1.0/numbers/update",
									"protocol": "https",
									"host": [
										"api",
										"telegent",
										"com"
									],
									"path": [
										"v1.0",
										"numbers",
										"update"
									]
								},
								"description": "# Phone Number Update\n\n## PUT /numbers/update\n\nUpdates the configuration and settings for a specific phone number in your inventory.\n\n### Request\n\n#### Headers\n\n```\nContent-Type: application/json\nAuthorization: Bearer {your_api_token}\n\n ```\n\n#### Body Parameters\n\n| Parameter | Type | Required | Description |\n| --- | --- | --- | --- |\n| `Number` | string | Yes | Phone number to update (in E.164 format) |\n| `MessageEnabled` | boolean | No | Whether to enable SMS/MMS messaging capability |\n| `MessageType` | string | No | Messaging classification. Valid values: `p2p`, `a2p` |\n| `Classification` | string | No | Carrier classification. Valid values: `MVNO`, `IOT` |\n| `VoiceEnabled` | boolean | No | Whether to enable voice calling capability |\n| `MessageRouteId` | string | Conditional | UUID of the message routing configuration (required if MessageEnabled is true) |\n| `VoiceRouteId` | string | Conditional | UUID of the voice routing configuration (required if VoiceEnabled is true) |\n| `AssignedSubscriberId` | string | No | ID of the subscriber to assign to this number |\n| `Iccid` | string | No | SIM card identifier to associate with this number |\n| `Cnam` | string | No | Caller ID name to display for outbound calls |\n\n### Sample Request\n\n``` json\n{\n    \"Number\": \"+18018018011\",\n    \"MessageEnabled\": true,\n    \"MessageType\": \"p2p\",\n    \"Classification\": \"MVNO\",\n    \"VoiceEnabled\": true,\n    \"MessageRouteId\": \"MRID-73af1e73-d7b3-4696-bdd9-5b407d9e99ee\",\n    \"VoiceRouteId\": \"CRID-4dec6beb-3985-444b-8c06-8baa5jjvawe\",\n    \"AssignedSubscriberId\": \"SID-d7b3-4696-bdd9-5b407d9e99ee-3985-444b8d\",\n    \"Iccid\": \"8901240397190556232\",\n    \"Cnam\": \"ABC Corp\"\n}\n\n ```\n\n### Responses\n\n#### 200 OK: Success\n\nReturns the updated phone number details and the status of the update order.\n\n``` json\n{\n    \"Number\": \"+18018018011\",\n    \"Tnid\": null,\n    \"UpdateOrderId\": \"JNUOID-2b6c1d07-c64f-4954-867e-3fa85583bc90\",\n    \"UpdateOrderDate\": \"2025-05-15T20:32:06.7977854+00:00\",\n    \"UpdateOrderStatus\": \"Complete\",\n    \"MessageType\": \"p2p\",\n    \"MessageEnabled\": true,\n    \"Classification\": \"MVNO\",\n    \"VoiceEnabled\": true,\n    \"MessageRouteId\": \"MRID-73af1e73-d7b3-4696-bdd9-5b407d9e99ee\",\n    \"VoiceRouteId\": \"CRID-4dec6beb-3985-444b-8c06-8baa5jjvawe\",\n    \"Iccid\": \"8901240397190557414F\",\n    \"Cnam\": \"ABC Corp\"\n}\n\n ```\n\n##### Response Fields\n\n| Field | Type | Description |\n| --- | --- | --- |\n| `Number` | string | The phone number in E.164 format |\n| `Tnid` | string | Unique telephone number identifier |\n| `UpdateOrderId` | string | Unique identifier for the update order |\n| `UpdateOrderDate` | string | Timestamp when the update was submitted (ISO 8601 format) |\n| `UpdateOrderStatus` | string | Status of the update order (e.g., \"Complete\", \"Pending\", \"Failed\") |\n| `MessageType` | string | Updated message classification (P2P, A2P) |\n| `MessageEnabled` | boolean | Updated messaging capability status |\n| `Classification` | string | Updated carrier classification |\n| `VoiceEnabled` | boolean | Updated voice capability status |\n| `MessageRouteId` | string | Updated message routing configuration ID |\n| `VoiceRouteId` | string | Updated voice routing configuration ID |\n| `Iccid` | string | Updated SIM card identifier |\n| `Cnam` | string | Updated Caller ID name |\n\n#### 400 Bad Request: Validation Error\n\n``` json\n{\n    \"Type\": \"https://tools.ietf.org/html/rfc7231#section-6.5.1\",\n    \"Title\": \"One or more validation errors occurred.\",\n    \"Status\": 400,\n    \"Errors\": {\n        \"$.MessageType\": [\"Invalid MessageType for the specified Classification. IOT numbers can only use p2p MessageType.\"]\n    },\n    \"TraceId\": \"00-1234abcd5678efgh-abcdef123456-00\"\n}\n\n ```\n\n#### 404 Not Found: Phone Number Not Found\n\n``` json\n{\n    \"Type\": \"https://tools.ietf.org/html/rfc7231#section-6.5.4\",\n    \"Title\": \"Not Found\",\n    \"Status\": 404,\n    \"Detail\": \"Phone number '+18018018011' was not found in your inventory.\",\n    \"TraceId\": \"00-1234abcd5678efgh-abcdef123456-00\"\n}\n\n ```\n\n#### 401 Unauthorized: Authentication Error\n\n``` json\n{\n    \"Type\": \"https://tools.ietf.org/html/rfc7235#section-3.1\",\n    \"Title\": \"Unauthorized\",\n    \"Status\": 401,\n    \"TraceId\": \"00-1234abcd5678efgh-abcdef123456-00\"\n}\n\n ```\n\n### Usage Notes\n\n- You only need to include the parameters you want to update in the request body.\n    \n- If updating routing configurations, ensure that the MessageRouteId and VoiceRouteId are valid IDs in your account.\n    \n- When changing MessageType between p2p and a2p, make sure the Classification supports the requested MessageType.\n    \n- Some updates may require a few moments to propagate through the system.\n    \n- The `UpdateOrderStatus` indicates whether the changes have been applied.\n    \n- CNAM updates may take 24-48 hours to propagate across all carrier networks.\n    \n- You cannot update the NumberType of an existing number; you would need to provision a new number instead.\n    \n\n### Try It\n\n```\ncurl -X PUT \"https://api.telegent.com/v1.0/numbers/update\" \\\n  -H \"Content-Type: application/json\" \\\n  -H \"Authorization: Bearer YOUR_API_TOKEN\" \\\n  -d '{\n    \"Number\": \"+18018018011\",\n    \"MessageEnabled\": true,\n    \"MessageType\": \"p2p\",\n    \"VoiceEnabled\": true,\n    \"MessageRouteId\": \"MRID-73af1e73-d7b3-4696-bdd9-5b407d9e99ee\",\n    \"VoiceRouteId\": \"CRID-4dec6beb-3985-444b-8c06-8baa5jjvawe\",\n    \"Cnam\": \"ABC Corp\"\n}'\n\n ```"
							},
							"response": [
								{
									"name": "Numbers Update",
									"originalRequest": {
										"method": "POST",
										"header": [],
										"body": {
											"mode": "raw",
											"raw": "{\n    \"Number\": \"+18018018011\", //required for updating specific number\n    \"MessageEnabled\": true,\n    \"MessageType\": \"p2p\",\n    \"Classification\": \"MVNO\",\n    \"VoiceEnabled\": true,\n    \"MessageRouteId\": \"MRID-73af1e73-d7b3-4696-bdd9-5b407d9e99ee\",\n    \"VoiceRouteId\": \"CRID-4dec6beb-3985-444b-8c06-8baa5jjvawe\",\n    \"AssignedSubscriberId\": \"SID-d7b3-4696-bdd9-5b407d9e99ee-3985-444b8d\",\n    \"Iccid\": \"8901240397190556232\",\n    \"Cnam\": \"ABC Corp\"\n}",
											"options": {
												"raw": {
													"language": "json"
												}
											}
										},
										"url": {
											"raw": "https://api.telegent.com/v1.0/numbers/update",
											"protocol": "https",
											"host": [
												"api",
												"telegent",
												"com"
											],
											"path": [
												"v1.0",
												"numbers",
												"update"
											]
										}
									},
									"status": "OK",
									"code": 200,
									"_postman_previewlanguage": "json",
									"header": [
										{
											"key": "Cache-Control",
											"value": "no-cache"
										},
										{
											"key": "Pragma",
											"value": "no-cache"
										},
										{
											"key": "Transfer-Encoding",
											"value": "chunked"
										},
										{
											"key": "Content-Type",
											"value": "application/json"
										},
										{
											"key": "Content-Encoding",
											"value": "gzip"
										},
										{
											"key": "Expires",
											"value": "-1"
										},
										{
											"key": "Vary",
											"value": "Accept-Encoding"
										},
										{
											"key": "Set-Cookie",
											"value": "ARRAffinity=1bf1fa7ef58a2ee2d7a44c3046cbe5c763c69a7c47c896aacbb04ba8a00ffc3b;Path=/;HttpOnly;Secure;Domain=prod-04.westus3.logic.azure.com"
										},
										{
											"key": "Set-Cookie",
											"value": "ARRAffinitySameSite=1bf1fa7ef58a2ee2d7a44c3046cbe5c763c69a7c47c896aacbb04ba8a00ffc3b;Path=/;HttpOnly;SameSite=None;Secure;Domain=prod-04.westus3.logic.azure.com"
										},
										{
											"key": "Strict-Transport-Security",
											"value": "max-age=31536000; includeSubDomains"
										},
										{
											"key": "x-ms-workflow-run-id",
											"value": "08585023406398455715829928640CU13"
										},
										{
											"key": "x-ms-correlation-id",
											"value": "38a759cd-c86a-45a1-b36d-0e4bc4bd6b7f"
										},
										{
											"key": "x-ms-client-tracking-id",
											"value": "08585023406398455715829928640CU13"
										},
										{
											"key": "x-ms-trigger-history-name",
											"value": "08585023406398455715829928640CU13"
										},
										{
											"key": "x-ms-execution-location",
											"value": "westus3"
										},
										{
											"key": "x-ms-workflow-system-id",
											"value": "/locations/westus3/scaleunits/prod-04/workflows/86c7b0688cb44dd6934a78279b875e36"
										},
										{
											"key": "x-ms-workflow-id",
											"value": "86c7b0688cb44dd6934a78279b875e36"
										},
										{
											"key": "x-ms-workflow-version",
											"value": "08585023407143927890"
										},
										{
											"key": "x-ms-workflow-name",
											"value": "Joonto_Numbers_v1.0_Purchase"
										},
										{
											"key": "x-ms-tracking-id",
											"value": "38a759cd-c86a-45a1-b36d-0e4bc4bd6b7f"
										},
										{
											"key": "x-ms-ratelimit-burst-remaining-workflow-writes",
											"value": "4499"
										},
										{
											"key": "x-ms-ratelimit-remaining-workflow-download-contentsize",
											"value": "322121611"
										},
										{
											"key": "x-ms-ratelimit-remaining-workflow-upload-contentsize",
											"value": "322121532"
										},
										{
											"key": "x-ms-ratelimit-time-remaining-directapirequests",
											"value": "29999368"
										},
										{
											"key": "x-ms-request-id",
											"value": "westus3:38a759cd-c86a-45a1-b36d-0e4bc4bd6b7f"
										},
										{
											"key": "Date",
											"value": "Mon, 06 Nov 2023 10:24:06 GMT"
										}
									],
									"cookie": [],
									"body": "{\n    \"Number\": \"+18018018011\",\n    \"Tnid\": null,\n    \"UpdateOrderId\": \"JNUOID-9ac74103-bf27-474a-8a1a-9f4ff74af187\",\n    \"UpdateOrderDate\": \"2025-05-14T22:21:08.2813656+00:00\",\n    \"UpdateOrderStatus\": \"Complete\",\n    \"MessageType\": \"p2p\",\n    \"MessageEnabled\": true,\n    \"Classification\": \"MVNO\",\n    \"VoiceEnabled\": true,\n    \"MessageRouteId\": \"MRID-73af1e73-d7b3-4696-bdd9-5b407d9e99ee\",\n    \"VoiceRouteId\": \"CRID-4dec6beb-3985-444b-8c06-8baa5jjvawe\",\n    \"Iccid\": \"8901240397190557414F\",\n    \"Cnam\": \"ABC Corp\"\n}"
								}
							]
						},
						{
							"name": "Numbers Status",
							"request": {
								"method": "POST",
								"header": [],
								"body": {
									"mode": "raw",
									"raw": "{\n\"StatusChange\": \"replace\", //options can be 'cancel', 'swap', 'replace' and 'park'\n\"EffectiveDate\": \"12/31/2023\",\n\"PhoneNumbers\": \n    [\n        {\n        \"Number\": \"+12016093801\"\n        },\n        {\n        \"Number\": \"+12232233180\"\n        }\n    ]\n}\n",
									"options": {
										"raw": {
											"language": "json"
										}
									}
								},
								"url": {
									"raw": "https://api.telegent.com/v1.0/numbers/status",
									"protocol": "https",
									"host": [
										"api",
										"telegent",
										"com"
									],
									"path": [
										"v1.0",
										"numbers",
										"status"
									]
								},
								"description": "# Phone Number Status Change\n\n## POST /numbers/status\n\nChanges the status of one or more phone numbers in your inventory by cancellation, parking, swapping, or replacement.\n\n### Request\n\n#### Headers\n\n```\nContent-Type: application/json\nAuthorization: Bearer {your_api_token}\n\n ```\n\n#### Body Parameters\n\n| Parameter | Type | Required | Description |\n| --- | --- | --- | --- |\n| `StatusChange` | string | Yes | Type of status change to perform. Valid values: `cancel`, `park`, `swap`, `replace` |\n| `EffectiveDate` | string | Yes | Date when the status change should take effect (MM/DD/YYYY) |\n| `PhoneNumbers` | array | Yes | List of phone numbers to change status |\n| `PhoneNumbers[].Number` | string | Yes | Phone number in E.164 format |\n\n### Sample Request\n\n``` json\n{\n    \"StatusChange\": \"replace\",\n    \"EffectiveDate\": \"12/31/2023\",\n    \"PhoneNumbers\": [\n        {\n            \"Number\": \"+12016093801\"\n        },\n        {\n            \"Number\": \"+12232233180\"\n        }\n    ]\n}\n\n ```\n\n### Responses\n\n#### 200 OK: Success (Cancel)\n\nResponse when canceling phone numbers:\n\n``` json\n{\n    \"OrderId\": \"JNUOID-d2862353-fccc-4481-a65a-89dc563bee8e\",\n    \"OrderDate\": \"2025-05-14T22:38:19.6412831Z\",\n    \"OrderStatus\": \"Pending\",\n    \"ChangeType\": \"cancel\",\n    \"EffectiveDate\": \"2023-12-31T00:00:00\",\n    \"NumbersChange\": [\n        {\n            \"Number\": \"+12016093801\",\n            \"ChargeFee\": 2.25\n        },\n        {\n            \"Number\": \"+12232233180\",\n            \"ChargeFee\": 2.25\n        }\n    ]\n}\n\n ```\n\n#### 200 OK: Success (Park)\n\nResponse when parking phone numbers:\n\n``` json\n{\n    \"OrderId\": \"TNOID-ddbaafffa-d7c-38c8-4cb4-bf0dd9064f021\",\n    \"OrderDate\": \"11/01/2024\",\n    \"OrderStatus\": \"Pending\",\n    \"ChangeType\": \"park\",\n    \"EffectiveDate\": \"2023-12-31T00:00:00\",\n    \"NumbersChanged\": [\n        {\n            \"Number\": \"+12016093801\",\n            \"ChangeFee\": 1.00\n        },\n        {\n            \"Number\": \"+12232233180\",\n            \"ChangeFee\": 1.00\n        }\n    ]\n}\n\n ```\n\n#### 200 OK: Success (Swap)\n\nResponse when swapping phone numbers:\n\n``` json\n{\n    \"OrderId\": \"JNUOID-9df281cc-82ac-48fc-b8bf-edc0a5547f04\",\n    \"OrderDate\": \"2025-05-15T18:20:58.5133475Z\",\n    \"OrderStatus\": \"Pending\",\n    \"ChangeType\": \"swap\",\n    \"EffectiveDate\": \"2023-12-31T00:00:00\",\n    \"NumbersChange\": [\n        {\n            \"OriginalNumber\": \"+12016093801\",\n            \"NewNumber\": \"+12013782522\",\n            \"ChargeFee\": 0\n        },\n        {\n            \"OriginalNumber\": \"+12232233180\",\n            \"NewNumber\": \"+12232233547\",\n            \"ChargeFee\": 0\n        }\n    ]\n}\n\n ```\n\n#### 200 OK: Success (Replace)\n\nResponse when replacing phone numbers:\n\n``` json\n{\n    \"OrderId\": \"JNUOID-9df281cc-82ac-48fc-b8bf-edc0a5547f04\",\n    \"OrderDate\": \"2025-05-15T18:20:58.5133475Z\",\n    \"OrderStatus\": \"Pending\",\n    \"ChangeType\": \"replace\",\n    \"EffectiveDate\": \"2023-12-31T00:00:00\",\n    \"NumbersChange\": [\n        {\n            \"OriginalNumber\": \"+12016093801\",\n            \"NewNumber\": \"+12013782522\",\n            \"ChargeFee\": 0\n        },\n        {\n            \"OriginalNumber\": \"+12232233180\",\n            \"NewNumber\": \"+12232233547\",\n            \"ChargeFee\": 0\n        }\n    ]\n}\n\n ```\n\n##### Response Fields\n\n| Field | Type | Description |\n| --- | --- | --- |\n| `OrderId` | string | Unique identifier for the status change order |\n| `OrderDate` | string | Timestamp when the order was submitted |\n| `OrderStatus` | string | Current status of the order (Pending, Completed, Failed) |\n| `ChangeType` | string | Type of status change performed |\n| `EffectiveDate` | string | Date when the status change will take effect |\n| `NumbersChange`/`NumbersChanged` | array | List of phone numbers affected by the status change |\n| `NumbersChange[].Number` | string | Phone number for cancel/park operations |\n| `NumbersChange[].OriginalNumber` | string | Original phone number for swap/replace operations |\n| `NumbersChange[].NewNumber` | string | New phone number for swap/replace operations |\n| `NumbersChange[].ChargeFee`/`ChangeFee` | number | Fee charged for the status change operation |\n\n#### 400 Bad Request: Validation Error\n\n``` json\n{\n    \"Type\": \"https://tools.ietf.org/html/rfc7231#section-6.5.1\",\n    \"Title\": \"One or more validation errors occurred.\",\n    \"Status\": 400,\n    \"Errors\": {\n        \"$.StatusChange\": [\"Invalid status change type. Must be one of: cancel, park, swap, replace.\"]\n    },\n    \"TraceId\": \"00-1234abcd5678efgh-abcdef123456-00\"\n}\n\n ```\n\n#### 401 Unauthorized: Authentication Error\n\n``` json\n{\n    \"Type\": \"https://tools.ietf.org/html/rfc7235#section-3.1\",\n    \"Title\": \"Unauthorized\",\n    \"Status\": 401,\n    \"TraceId\": \"00-1234abcd5678efgh-abcdef123456-00\"\n}\n\n ```\n\n### Usage Notes\n\n- **Cancel**: Terminates a phone number and removes it from your inventory. Cancellation fees may apply.\n    \n- **Park**: Places a phone number in a suspended state while maintaining ownership. Useful for temporarily disabling service.\n    \n- **Swap**: Exchanges existing phone numbers with different ones while preserving configurations and routing.\n    \n- **Replace**: Similar to swap but may involve different internal processing for regulatory compliance.\n    \n- Status changes are not immediate and follow the specified effective date.\n    \n- Some status changes may incur fees as indicated in the response.\n    \n- You can check the status of a change order using the `/numbers/order` endpoint with the returned OrderId.\n    \n- For swap and replace operations, the system automatically assigns new numbers based on availability and similarity.\n    \n\n### Try It\n\n```\ncurl -X POST \"https://api.telegent.com/v1.0/numbers/status\" \\\n  -H \"Content-Type: application/json\" \\\n  -H \"Authorization: Bearer YOUR_API_TOKEN\" \\\n  -d '{\n    \"StatusChange\": \"cancel\",\n    \"EffectiveDate\": \"12/31/2023\",\n    \"PhoneNumbers\": [\n        {\n            \"Number\": \"+12016093801\"\n        },\n        {\n            \"Number\": \"+12232233180\"\n        }\n    ]\n}'\n\n ```"
							},
							"response": [
								{
									"name": "Numbers Cancel",
									"originalRequest": {
										"method": "POST",
										"header": [],
										"body": {
											"mode": "raw",
											"raw": "{\n\"StatusChange\": \"cancel\", //options can be 'cancel', 'swap', 'replace' and 'park'\n\"EffectiveDate\": \"12/31/2023\",\n\"PhoneNumbers\": \n    [\n        {\n        \"Number\": \"+12016093801\"\n        },\n        {\n        \"Number\": \"+12232233180\"\n        }\n    ]\n}\n",
											"options": {
												"raw": {
													"language": "json"
												}
											}
										},
										"url": {
											"raw": "https://api.telegent.com/v1.0/numbers/status",
											"protocol": "https",
											"host": [
												"api",
												"telegent",
												"com"
											],
											"path": [
												"v1.0",
												"numbers",
												"status"
											]
										}
									},
									"status": "OK",
									"code": 200,
									"_postman_previewlanguage": "json",
									"header": [
										{
											"key": "Cache-Control",
											"value": "no-cache"
										},
										{
											"key": "Pragma",
											"value": "no-cache"
										},
										{
											"key": "Transfer-Encoding",
											"value": "chunked"
										},
										{
											"key": "Content-Type",
											"value": "application/json"
										},
										{
											"key": "Content-Encoding",
											"value": "gzip"
										},
										{
											"key": "Expires",
											"value": "-1"
										},
										{
											"key": "Vary",
											"value": "Accept-Encoding"
										},
										{
											"key": "Set-Cookie",
											"value": "ARRAffinity=1bf1fa7ef58a2ee2d7a44c3046cbe5c763c69a7c47c896aacbb04ba8a00ffc3b;Path=/;HttpOnly;Secure;Domain=prod-04.westus3.logic.azure.com"
										},
										{
											"key": "Set-Cookie",
											"value": "ARRAffinitySameSite=1bf1fa7ef58a2ee2d7a44c3046cbe5c763c69a7c47c896aacbb04ba8a00ffc3b;Path=/;HttpOnly;SameSite=None;Secure;Domain=prod-04.westus3.logic.azure.com"
										},
										{
											"key": "Strict-Transport-Security",
											"value": "max-age=31536000; includeSubDomains"
										},
										{
											"key": "x-ms-workflow-run-id",
											"value": "08585023406398455715829928640CU13"
										},
										{
											"key": "x-ms-correlation-id",
											"value": "38a759cd-c86a-45a1-b36d-0e4bc4bd6b7f"
										},
										{
											"key": "x-ms-client-tracking-id",
											"value": "08585023406398455715829928640CU13"
										},
										{
											"key": "x-ms-trigger-history-name",
											"value": "08585023406398455715829928640CU13"
										},
										{
											"key": "x-ms-execution-location",
											"value": "westus3"
										},
										{
											"key": "x-ms-workflow-system-id",
											"value": "/locations/westus3/scaleunits/prod-04/workflows/86c7b0688cb44dd6934a78279b875e36"
										},
										{
											"key": "x-ms-workflow-id",
											"value": "86c7b0688cb44dd6934a78279b875e36"
										},
										{
											"key": "x-ms-workflow-version",
											"value": "08585023407143927890"
										},
										{
											"key": "x-ms-workflow-name",
											"value": "Joonto_Numbers_v1.0_Purchase"
										},
										{
											"key": "x-ms-tracking-id",
											"value": "38a759cd-c86a-45a1-b36d-0e4bc4bd6b7f"
										},
										{
											"key": "x-ms-ratelimit-burst-remaining-workflow-writes",
											"value": "4499"
										},
										{
											"key": "x-ms-ratelimit-remaining-workflow-download-contentsize",
											"value": "322121611"
										},
										{
											"key": "x-ms-ratelimit-remaining-workflow-upload-contentsize",
											"value": "322121532"
										},
										{
											"key": "x-ms-ratelimit-time-remaining-directapirequests",
											"value": "29999368"
										},
										{
											"key": "x-ms-request-id",
											"value": "westus3:38a759cd-c86a-45a1-b36d-0e4bc4bd6b7f"
										},
										{
											"key": "Date",
											"value": "Mon, 06 Nov 2023 10:24:06 GMT"
										}
									],
									"cookie": [],
									"body": "{\n    \"OrderId\": \"JNUOID-d2862353-fccc-4481-a65a-89dc563bee8e\",\n    \"OrderDate\": \"2025-05-14T22:38:19.6412831Z\",\n    \"OrderStatus\": \"Pending\",\n    \"ChangeType\": \"cancel\",\n    \"EffectiveDate\": \"2023-12-31T00:00:00\",\n    \"NumbersChange\": \n    [\n        {\n            \"Number\": \"+12016093801\",\n            \"ChargeFee\": 2.25\n        },\n        {\n            \"Number\": \"+12232233180\",\n            \"ChargeFee\": 2.25\n        }\n    ]\n}"
								},
								{
									"name": "Numbers Park",
									"originalRequest": {
										"method": "POST",
										"header": [],
										"body": {
											"mode": "raw",
											"raw": "{\n\"ChangeType\": \"park\", //options can be 'cancel', 'swap', 'replace' and 'park'\n\"EffectiveDate\": \"12/31/2023\",\n\"PhoneNumbers\": \n    [\n        {\n        \"Number\": \"+12016093801\"\n        },\n        {\n        \"Number\": \"+12232233180\"\n        }\n    ]\n}",
											"options": {
												"raw": {
													"language": "json"
												}
											}
										},
										"url": {
											"raw": "https://api.telegent.com/v1.0/numbers/update",
											"protocol": "https",
											"host": [
												"api",
												"telegent",
												"com"
											],
											"path": [
												"v1.0",
												"numbers",
												"update"
											]
										}
									},
									"status": "OK",
									"code": 200,
									"_postman_previewlanguage": "json",
									"header": [
										{
											"key": "Cache-Control",
											"value": "no-cache"
										},
										{
											"key": "Pragma",
											"value": "no-cache"
										},
										{
											"key": "Transfer-Encoding",
											"value": "chunked"
										},
										{
											"key": "Content-Type",
											"value": "application/json"
										},
										{
											"key": "Content-Encoding",
											"value": "gzip"
										},
										{
											"key": "Expires",
											"value": "-1"
										},
										{
											"key": "Vary",
											"value": "Accept-Encoding"
										},
										{
											"key": "Set-Cookie",
											"value": "ARRAffinity=1bf1fa7ef58a2ee2d7a44c3046cbe5c763c69a7c47c896aacbb04ba8a00ffc3b;Path=/;HttpOnly;Secure;Domain=prod-04.westus3.logic.azure.com"
										},
										{
											"key": "Set-Cookie",
											"value": "ARRAffinitySameSite=1bf1fa7ef58a2ee2d7a44c3046cbe5c763c69a7c47c896aacbb04ba8a00ffc3b;Path=/;HttpOnly;SameSite=None;Secure;Domain=prod-04.westus3.logic.azure.com"
										},
										{
											"key": "Strict-Transport-Security",
											"value": "max-age=31536000; includeSubDomains"
										},
										{
											"key": "x-ms-workflow-run-id",
											"value": "08585023406398455715829928640CU13"
										},
										{
											"key": "x-ms-correlation-id",
											"value": "38a759cd-c86a-45a1-b36d-0e4bc4bd6b7f"
										},
										{
											"key": "x-ms-client-tracking-id",
											"value": "08585023406398455715829928640CU13"
										},
										{
											"key": "x-ms-trigger-history-name",
											"value": "08585023406398455715829928640CU13"
										},
										{
											"key": "x-ms-execution-location",
											"value": "westus3"
										},
										{
											"key": "x-ms-workflow-system-id",
											"value": "/locations/westus3/scaleunits/prod-04/workflows/86c7b0688cb44dd6934a78279b875e36"
										},
										{
											"key": "x-ms-workflow-id",
											"value": "86c7b0688cb44dd6934a78279b875e36"
										},
										{
											"key": "x-ms-workflow-version",
											"value": "08585023407143927890"
										},
										{
											"key": "x-ms-workflow-name",
											"value": "Joonto_Numbers_v1.0_Purchase"
										},
										{
											"key": "x-ms-tracking-id",
											"value": "38a759cd-c86a-45a1-b36d-0e4bc4bd6b7f"
										},
										{
											"key": "x-ms-ratelimit-burst-remaining-workflow-writes",
											"value": "4499"
										},
										{
											"key": "x-ms-ratelimit-remaining-workflow-download-contentsize",
											"value": "322121611"
										},
										{
											"key": "x-ms-ratelimit-remaining-workflow-upload-contentsize",
											"value": "322121532"
										},
										{
											"key": "x-ms-ratelimit-time-remaining-directapirequests",
											"value": "29999368"
										},
										{
											"key": "x-ms-request-id",
											"value": "westus3:38a759cd-c86a-45a1-b36d-0e4bc4bd6b7f"
										},
										{
											"key": "Date",
											"value": "Mon, 06 Nov 2023 10:24:06 GMT"
										}
									],
									"cookie": [],
									"body": "{\n    \"OrderId\": \"TNOID-ddbaafffa-d7c-38c8-4cb4-bf0dd9064f021\",\n    \"OrderDate\": \"11/01/2024\",\n    \"OrderStatus\": \"Pending\", //options are: \"Pending\", \"Completed\", \"Failed\"\n    \"ChangeType\": \"park\", //options are \"Cancellation\", \"Swap\", \"Replace\", \"Park\"\n    \"EffectiveDate\": \"2023-12-31T00:00:00\",\n    \"NumbersChanged\": \n    [\n        {\n            \"Number\": \"+12016093801\",\n            \"ChangeFee\": 1.00\n        },\n        {\n            \"Number\": \"+12232233180\",\n            \"ChangeFee\": 1.00\n        }\n    ]\n}"
								},
								{
									"name": "Numbers Swap",
									"originalRequest": {
										"method": "POST",
										"header": [],
										"body": {
											"mode": "raw",
											"raw": "{\n\"ChangeType\": \"swap\", //options can be 'cancel', 'swap', 'replace' and 'park'\n\"EffectiveDate\": \"12/31/2023\",\n\"PhoneNumbers\": \n    [\n        {\n        \"Number\": \"+12016093801\"\n        },\n        {\n        \"Number\": \"+12232233180\"\n        }\n    ]\n}",
											"options": {
												"raw": {
													"language": "json"
												}
											}
										},
										"url": {
											"raw": "https://api.telegent.com/v1.0/numbers/update",
											"protocol": "https",
											"host": [
												"api",
												"telegent",
												"com"
											],
											"path": [
												"v1.0",
												"numbers",
												"update"
											]
										}
									},
									"status": "OK",
									"code": 200,
									"_postman_previewlanguage": "json",
									"header": [
										{
											"key": "Cache-Control",
											"value": "no-cache"
										},
										{
											"key": "Pragma",
											"value": "no-cache"
										},
										{
											"key": "Transfer-Encoding",
											"value": "chunked"
										},
										{
											"key": "Content-Type",
											"value": "application/json"
										},
										{
											"key": "Content-Encoding",
											"value": "gzip"
										},
										{
											"key": "Expires",
											"value": "-1"
										},
										{
											"key": "Vary",
											"value": "Accept-Encoding"
										},
										{
											"key": "Set-Cookie",
											"value": "ARRAffinity=1bf1fa7ef58a2ee2d7a44c3046cbe5c763c69a7c47c896aacbb04ba8a00ffc3b;Path=/;HttpOnly;Secure;Domain=prod-04.westus3.logic.azure.com"
										},
										{
											"key": "Set-Cookie",
											"value": "ARRAffinitySameSite=1bf1fa7ef58a2ee2d7a44c3046cbe5c763c69a7c47c896aacbb04ba8a00ffc3b;Path=/;HttpOnly;SameSite=None;Secure;Domain=prod-04.westus3.logic.azure.com"
										},
										{
											"key": "Strict-Transport-Security",
											"value": "max-age=31536000; includeSubDomains"
										},
										{
											"key": "x-ms-workflow-run-id",
											"value": "08585023406398455715829928640CU13"
										},
										{
											"key": "x-ms-correlation-id",
											"value": "38a759cd-c86a-45a1-b36d-0e4bc4bd6b7f"
										},
										{
											"key": "x-ms-client-tracking-id",
											"value": "08585023406398455715829928640CU13"
										},
										{
											"key": "x-ms-trigger-history-name",
											"value": "08585023406398455715829928640CU13"
										},
										{
											"key": "x-ms-execution-location",
											"value": "westus3"
										},
										{
											"key": "x-ms-workflow-system-id",
											"value": "/locations/westus3/scaleunits/prod-04/workflows/86c7b0688cb44dd6934a78279b875e36"
										},
										{
											"key": "x-ms-workflow-id",
											"value": "86c7b0688cb44dd6934a78279b875e36"
										},
										{
											"key": "x-ms-workflow-version",
											"value": "08585023407143927890"
										},
										{
											"key": "x-ms-workflow-name",
											"value": "Joonto_Numbers_v1.0_Purchase"
										},
										{
											"key": "x-ms-tracking-id",
											"value": "38a759cd-c86a-45a1-b36d-0e4bc4bd6b7f"
										},
										{
											"key": "x-ms-ratelimit-burst-remaining-workflow-writes",
											"value": "4499"
										},
										{
											"key": "x-ms-ratelimit-remaining-workflow-download-contentsize",
											"value": "322121611"
										},
										{
											"key": "x-ms-ratelimit-remaining-workflow-upload-contentsize",
											"value": "322121532"
										},
										{
											"key": "x-ms-ratelimit-time-remaining-directapirequests",
											"value": "29999368"
										},
										{
											"key": "x-ms-request-id",
											"value": "westus3:38a759cd-c86a-45a1-b36d-0e4bc4bd6b7f"
										},
										{
											"key": "Date",
											"value": "Mon, 06 Nov 2023 10:24:06 GMT"
										}
									],
									"cookie": [],
									"body": "{\n    \"OrderId\": \"JNUOID-9df281cc-82ac-48fc-b8bf-edc0a5547f04\",\n    \"OrderDate\": \"2025-05-15T18:20:58.5133475Z\",\n    \"OrderStatus\": \"Pending\",\n    \"ChangeType\": \"swap\",\n    \"EffectiveDate\": \"2023-12-31T00:00:00\",\n    \"NumbersChange\": [\n        {\n            \"OriginalNumber\": \"+12016093801\",\n            \"NewNumber\": \"+12013782522\",\n            \"ChargeFee\": 0\n        },\n        {\n            \"OriginalNumber\": \"+12232233180\",\n            \"NewNumber\": \"+12232233547\",\n            \"ChargeFee\": 0\n        }\n    ]\n}"
								},
								{
									"name": "Numbers Replace",
									"originalRequest": {
										"method": "POST",
										"header": [],
										"body": {
											"mode": "raw",
											"raw": "{\n\"ChangeType\": \"replace\", //options can be 'cancel', 'swap', 'replace' and 'park'\n\"EffectiveDate\": \"12/31/2023\",\n\"PhoneNumbers\": \n    [\n        {\n        \"Number\": \"+12016093801\"\n        },\n        {\n        \"Number\": \"+12232233180\"\n        }\n    ]\n}",
											"options": {
												"raw": {
													"language": "json"
												}
											}
										},
										"url": {
											"raw": "https://api.telegent.com/v1.0/numbers/update",
											"protocol": "https",
											"host": [
												"api",
												"telegent",
												"com"
											],
											"path": [
												"v1.0",
												"numbers",
												"update"
											]
										}
									},
									"status": "OK",
									"code": 200,
									"_postman_previewlanguage": "json",
									"header": [
										{
											"key": "Cache-Control",
											"value": "no-cache"
										},
										{
											"key": "Pragma",
											"value": "no-cache"
										},
										{
											"key": "Transfer-Encoding",
											"value": "chunked"
										},
										{
											"key": "Content-Type",
											"value": "application/json"
										},
										{
											"key": "Content-Encoding",
											"value": "gzip"
										},
										{
											"key": "Expires",
											"value": "-1"
										},
										{
											"key": "Vary",
											"value": "Accept-Encoding"
										},
										{
											"key": "Set-Cookie",
											"value": "ARRAffinity=1bf1fa7ef58a2ee2d7a44c3046cbe5c763c69a7c47c896aacbb04ba8a00ffc3b;Path=/;HttpOnly;Secure;Domain=prod-04.westus3.logic.azure.com"
										},
										{
											"key": "Set-Cookie",
											"value": "ARRAffinitySameSite=1bf1fa7ef58a2ee2d7a44c3046cbe5c763c69a7c47c896aacbb04ba8a00ffc3b;Path=/;HttpOnly;SameSite=None;Secure;Domain=prod-04.westus3.logic.azure.com"
										},
										{
											"key": "Strict-Transport-Security",
											"value": "max-age=31536000; includeSubDomains"
										},
										{
											"key": "x-ms-workflow-run-id",
											"value": "08585023406398455715829928640CU13"
										},
										{
											"key": "x-ms-correlation-id",
											"value": "38a759cd-c86a-45a1-b36d-0e4bc4bd6b7f"
										},
										{
											"key": "x-ms-client-tracking-id",
											"value": "08585023406398455715829928640CU13"
										},
										{
											"key": "x-ms-trigger-history-name",
											"value": "08585023406398455715829928640CU13"
										},
										{
											"key": "x-ms-execution-location",
											"value": "westus3"
										},
										{
											"key": "x-ms-workflow-system-id",
											"value": "/locations/westus3/scaleunits/prod-04/workflows/86c7b0688cb44dd6934a78279b875e36"
										},
										{
											"key": "x-ms-workflow-id",
											"value": "86c7b0688cb44dd6934a78279b875e36"
										},
										{
											"key": "x-ms-workflow-version",
											"value": "08585023407143927890"
										},
										{
											"key": "x-ms-workflow-name",
											"value": "Joonto_Numbers_v1.0_Purchase"
										},
										{
											"key": "x-ms-tracking-id",
											"value": "38a759cd-c86a-45a1-b36d-0e4bc4bd6b7f"
										},
										{
											"key": "x-ms-ratelimit-burst-remaining-workflow-writes",
											"value": "4499"
										},
										{
											"key": "x-ms-ratelimit-remaining-workflow-download-contentsize",
											"value": "322121611"
										},
										{
											"key": "x-ms-ratelimit-remaining-workflow-upload-contentsize",
											"value": "322121532"
										},
										{
											"key": "x-ms-ratelimit-time-remaining-directapirequests",
											"value": "29999368"
										},
										{
											"key": "x-ms-request-id",
											"value": "westus3:38a759cd-c86a-45a1-b36d-0e4bc4bd6b7f"
										},
										{
											"key": "Date",
											"value": "Mon, 06 Nov 2023 10:24:06 GMT"
										}
									],
									"cookie": [],
									"body": "{\n    \"OrderId\": \"JNUOID-9df281cc-82ac-48fc-b8bf-edc0a5547f04\",\n    \"OrderDate\": \"2025-05-15T18:20:58.5133475Z\",\n    \"OrderStatus\": \"Pending\",\n    \"ChangeType\": \"replace\",\n    \"EffectiveDate\": \"2023-12-31T00:00:00\",\n    \"NumbersChange\": [\n        {\n            \"OriginalNumber\": \"+12016093801\",\n            \"NewNumber\": \"+12013782522\",\n            \"ChargeFee\": 0\n        },\n        {\n            \"OriginalNumber\": \"+12232233180\",\n            \"NewNumber\": \"+12232233547\",\n            \"ChargeFee\": 0\n        }\n    ]\n}"
								}
							]
						}
					],
					"description": "# Intelligent Mobile Numbers API Documentation\n\nThis section details the management of intelligent mobile numbers, including provisioning, configuration, and querying.  \n  \n  \nTLDR:  \n  \nIntelligent Mobile Numbers API - Summary\n\n## Key Workflow\n\n1. **Before provisioning/updating numbers:**\n    \n    - Create a Voice Route to get a `CallRouteId`\n        \n    - Create a Message Route to get a `MessageRouteId`\n        \n    - Use these IDs when provisioning or updating numbers\n        \n\n## Main Endpoints\n\n- **Check availability**: `POST /numbers/availability`\n    \n- **Provision numbers**: `POST /numbers/provision` (include route IDs)\n    \n- **Port numbers**: `POST /numbers/portin` and `POST /numbers/portout`\n    \n- **View orders**: `GET /numbers/order?OrderId={OrderId}`\n    \n- **View inventory**: `GET /numbers/inventory?Filter={Filter}`\n    \n- **Get number details**: `GET /numbers?PhoneNumber={PhoneNumber}`\n    \n- **Update configuration**: `POST /numbers/update`\n    \n- **Check status**: `POST /numbers/status      TLDR END:`\n    \n\n## Key Recommendation: Workflow for Number Configuration\n\n**Before provisioning new numbers or updating existing ones with specific voice and messaging capabilities, it is highly recommended to perform the following prerequisite steps:**\n\n1. **Create a Voice Route**: Navigate to the \"v1.0 / Intelligent Voice\" section and use the `Create Voice Route` endpoint. This will provIde a `CallRouteId` in the response (often stored as `CRID` in Postman). This Id value is what you'll use to associate with a number.\n    \n2. **Create a Message Route**: Navigate to the \"v1.0 / Intelligent Messaging\" section and use the `Create Message Route` endpoint. This will provIde a `MessageRouteId`. This Id defines how incoming and outgoing messages for a number will be processed.\n    \n\nOnce you have obtained these Id values, you can use them when:\n\n- Provisioning a new number via `POST /numbers/provision` (your request body should include a `CallRouteId` field and a `MessageRouteId` field, using the respective Id values obtained).\n    \n- Updating an existing number's configuration via `POST /numbers/update` (similarly, your request body should include a `CallRouteId` field and/or `MessageRouteId` field).\n    \n\nThis ensures that your numbers are immediately associated with the desired voice and messaging behaviors upon provisioning or update.\n\n## Endpoints Overview\n\n- **Available Numbers (****`POST /numbers/availability`****)**: Use this to check for the availability of numbers based on specified criteria before attempting to provision them.\n    \n- **Number Provision (Purchase/Order) (****`POST /numbers/provision`****)**: This endpoint allows you to order or purchase new phone numbers.\n    \n    - **Important**: Remember to include a `CallRouteId` field and a `MessageRouteId` field in your request body if you want to pre-configure the number during provisioning.\n        \n    - A successful provisioning request typically returns an `OrderId`. This `OrderId` is a reference to your provisioning transaction and can be used to track its status or retrieve details using the \"Order Id Details\" endpoint.\n        \n- **Numbers - Port In (****`POST /numbers/portin`****)**: Manages the process of porting an existing number from another carrier into your account.\n    \n- **Numbers - Port Out (****`POST /numbers/portout`****)**: Manages the process of porting one of your numbers out to another carrier.\n    \n- **Order Id Details (****`GET /numbers/order?OrderId={OrderId}`****)**: Retrieves the status and details of a specific number provisioning order, using the `OrderId` obtained from the provision request.\n    \n- **Numbers Inventory (****`GET /numbers/inventory?Filter={Filter}`****)**: Fetches a list of numbers in your account. The `Filter` parameter can be used to narrow down the results (e.g., `All`, `Active`, specific capabilities).\n    \n- **Number Details (****`GET /numbers?PhoneNumber={PhoneNumber}`****)**: Retrieves detailed configuration and status information for a specific phone number.\n    \n- **Numbers Update (****`POST /numbers/update`****)**: Allows you to modify the configuration of an existing number. This is where you would typically use fields like `CallRouteId` and `MessageRouteId` in your request body to assign or change the respective routes, using the Id values obtained from creating those routes.\n    \n- **Numbers Status (****`POST /numbers/status`****)**: ProvIdes the current operational status of a specific number.",
					"event": [
						{
							"listen": "prerequest",
							"script": {
								"type": "text/javascript",
								"packages": {},
								"exec": [
									""
								]
							}
						},
						{
							"listen": "test",
							"script": {
								"type": "text/javascript",
								"packages": {},
								"exec": [
									""
								]
							}
						}
					]
				},
				{
					"name": "Intelligent Messaging",
					"item": [
						{
							"name": "Create Message Route",
							"event": [
								{
									"listen": "test",
									"script": {
										"exec": [
											"pm.test(\"Response has MessageRouteId\", function () {",
											"    pm.response.to.have.property(\"json\");",
											"    const jsonData = pm.response.json();",
											"    pm.expect(jsonData).to.have.property(\"MessageRouteId\");",
											"});",
											"",
											"pm.test(\"Extract and store MRID in collection variables\", function () {",
											"    const jsonData = pm.response.json();",
											"    const MessageRouteId = jsonData.MessageRouteId;",
											"    pm.collectionVariables.set(\"MessageRouteId\", MessageRouteId);",
											"    console.log(\"👉 Stored MessageRouteId:\", MessageRouteId);",
											"});",
											"",
											"pm.test(\"All output keys are PascalCase\", function () {",
											"    const jsonData = pm.response.json();",
											"    const keys = Object.keys(jsonData);",
											"    keys.forEach(key => {",
											"        pm.expect(key).to.match(/^[A-Z][a-z0-9]*([A-Z][a-z0-9]*)*$/);",
											"    });",
											"});"
										],
										"type": "text/javascript",
										"packages": {}
									}
								}
							],
							"request": {
								"method": "POST",
								"header": [],
								"body": {
									"mode": "raw",
									"raw": "{\n    \"RouteName\": \"Main SMS Webhook\",\n    \"MessageUrl\": \"https://apiendpoint.com\",\n    \"MessageUrlMethod\": \"POST\",\n    \"MessageRouteEnabled\": true,\n    \"MessageAuthenticationType\": \"Basic\",\n    \"MessageUsername\": \"admin\",\n    \"MessagePasswordToken\": \"passwordORbearerToken\",\n    \"CallbackMessageUrl\": \"https://apiendpoint.com\",\n    \"CallbackMessageUrlMethod\": \"POST\",\n    \"CallbackMessageAuthenticationType\": \"Basic\",\n    \"CallbackMessageUsername\": \"admin\",\n    \"CallbackMessagePasswordToken\": \"password\"\n}",
									"options": {
										"raw": {
											"language": "json"
										}
									}
								},
								"url": {
									"raw": "https://api.telegent.com/v1.0/message/routes",
									"protocol": "https",
									"host": [
										"api",
										"telegent",
										"com"
									],
									"path": [
										"v1.0",
										"message",
										"routes"
									]
								},
								"description": "# Message Routing Configuration\n\n## POST /message/routes\n\nCreates a new message routing configuration for handling SMS/MMS communications.\n\n### Request\n\n#### Headers\n\n```\nContent-Type: application/json\nAuthorization: Bearer {your_api_token}\n\n ```\n\n#### Body Parameters\n\n| Parameter | Type | Required | Description |\n| --- | --- | --- | --- |\n| `RouteName` | string | Yes | Descriptive name for this message route |\n| `MessageUrl` | string | Yes | Webhook URL that will receive incoming messages |\n| `MessageUrlMethod` | string | Yes | HTTP method for the webhook (e.g., `POST`, `GET`) |\n| `MessageRouteEnabled` | boolean | Yes | Whether this route is active |\n| `MessageAuthenticationType` | string | No | Authentication type for the webhook (e.g., `Basic`, `Bearer`) |\n| `MessageUsername` | string | Conditional | Username for authentication (required if using Basic auth) |\n| `MessagePasswordToken` | string | Conditional | Password or token for authentication |\n| `CallbackMessageUrl` | string | No | URL for receiving delivery receipts and other callbacks |\n| `CallbackMessageUrlMethod` | string | No | HTTP method for the callback URL |\n| `CallbackMessageAuthenticationType` | string | No | Authentication type for callbacks |\n| `CallbackMessageUsername` | string | No | Username for callback authentication |\n| `CallbackMessagePasswordToken` | string | No | Password or token for callback authentication |\n\n### Sample Request\n\n``` json\n{\n    \"RouteName\": \"Main SMS Webhook\",\n    \"MessageUrl\": \"https://apiendpoint.com\",\n    \"MessageUrlMethod\": \"POST\",\n    \"MessageRouteEnabled\": true,\n    \"MessageAuthenticationType\": \"Basic\",\n    \"MessageUsername\": \"admin\",\n    \"MessagePasswordToken\": \"passwordORbearerToken\",\n    \"CallbackMessageUrl\": \"https://apiendpoint.com\",\n    \"CallbackMessageUrlMethod\": \"POST\",\n    \"CallbackMessageAuthenticationType\": \"Basic\",\n    \"CallbackMessageUsername\": \"admin\",\n    \"CallbackMessagePasswordToken\": \"password\"\n}\n\n ```\n\n### Responses\n\n#### 200 OK: Success\n\nReturns the created message route with its unique identifier.\n\n``` json\n{\n    \"MessageRouteId\": \"MRID-ad0ff867-57dc-4aeb-80e9-9d18349080e9\",\n    \"AccountId\": \"DID-eab92510-1040-45a5-bb9c-0bad927SDY878W\",\n    \"RouteName\": \"Main SMS Webhook\",\n    \"MessageUrl\": \"https://apiendpoint.com\",\n    \"MessageUrlMethod\": \"POST\",\n    \"MessageRouteEnabled\": false,\n    \"MessageAuthenticationType\": \"Basic\",\n    \"MessageUsername\": \"admin\",\n    \"MessagePasswordToken\": \"passwordORbearerToken\",\n    \"CallbackMessageUrl\": \"https://apiendpoint.com\",\n    \"CallbackMessageUrlMethod\": \"POST\",\n    \"CallbackMessageAuthenticationType\": \"Basic\",\n    \"CallbackMessageUsername\": \"admin\",\n    \"CallbackMessagePasswordToken\": \"password\"\n}\n\n ```\n\n##### Response Fields\n\n| Field | Type | Description |\n| --- | --- | --- |\n| `MessageRouteId` | string | Unique identifier for the created message route (format: MRID-xxx) |\n| `AccountId` | string | Your account identifier |\n| `RouteName` | string | Name of the message route |\n| `MessageUrl` | string | The URL that receives incoming messages |\n| `MessageUrlMethod` | string | HTTP method for the webhook URL |\n| `MessageRouteEnabled` | boolean | Whether the message route is active |\n| `MessageAuthenticationType` | string | Type of authentication used for the webhook |\n| `MessageUsername` | string | Username for webhook authentication |\n| `MessagePasswordToken` | string | Password or token for webhook authentication (masked for security) |\n| `CallbackMessageUrl` | string | URL that receives delivery receipts and other callbacks |\n| `CallbackMessageUrlMethod` | string | HTTP method for the callback URL |\n| `CallbackMessageAuthenticationType` | string | Type of authentication used for callbacks |\n| `CallbackMessageUsername` | string | Username for callback authentication |\n| `CallbackMessagePasswordToken` | string | Password or token for callback authentication (masked for security) |\n\n#### 400 Bad Request: Validation Error\n\n``` json\n{\n    \"Type\": \"https://tools.ietf.org/html/rfc7231#section-6.5.1\",\n    \"Title\": \"One or more validation errors occurred.\",\n    \"Status\": 400,\n    \"Errors\": {\n        \"$.MessageUrl\": [\"A valid URL is required for the message webhook.\"]\n    },\n    \"TraceId\": \"00-1234abcd5678efgh-abcdef123456-00\"\n}\n\n ```\n\n#### 401 Unauthorized: Authentication Error\n\n``` json\n{\n    \"Type\": \"https://tools.ietf.org/html/rfc7235#section-3.1\",\n    \"Title\": \"Unauthorized\",\n    \"Status\": 401,\n    \"TraceId\": \"00-1234abcd5678efgh-abcdef123456-00\"\n}\n\n ```\n\n### Usage Notes\n\n- The created `MessageRouteId` is required when provisioning or updating phone numbers to enable messaging capabilities.\n    \n- When setting up Basic authentication, both `MessageUsername` and `MessagePasswordToken` are required.\n    \n- For {{vault:bearer-token}}, only `MessagePasswordToken` is needed (containing the Bearer token).\n    \n- The `MessageRouteEnabled` parameter allows you to create routes in a disabled state before testing and enabling them.\n    \n- Callback URLs are used to receive status updates about message delivery, such as \"delivered\" or \"failed\" notifications.\n    \n- You can check created routes and their details using the `GET /account/message/routes` endpoint.\n    \n\n### Try It\n\n```\ncurl -X POST \"https://api.telegent.com/v1.0/message/routes\" \\\n  -H \"Content-Type: application/json\" \\\n  -H \"Authorization: Bearer YOUR_API_TOKEN\" \\\n  -d '{\n    \"RouteName\": \"Main SMS Webhook\",\n    \"MessageUrl\": \"https://apiendpoint.com\",\n    \"MessageUrlMethod\": \"POST\",\n    \"MessageRouteEnabled\": true,\n    \"MessageAuthenticationType\": \"Basic\",\n    \"MessageUsername\": \"admin\",\n    \"MessagePasswordToken\": \"passwordORbearerToken\",\n    \"CallbackMessageUrl\": \"https://apiendpoint.com\",\n    \"CallbackMessageUrlMethod\": \"POST\",\n    \"CallbackMessageAuthenticationType\": \"Basic\",\n    \"CallbackMessageUsername\": \"admin\",\n    \"CallbackMessagePasswordToken\": \"password\"\n}'\n\n ```"
							},
							"response": [
								{
									"name": "Create Message Route",
									"originalRequest": {
										"method": "POST",
										"header": [],
										"body": {
											"mode": "raw",
											"raw": "{\n    \"RouteName\": \"Main SMS Webhook\",\n    \"MessageUrl\": \"https://apiendpoint.com\",\n    \"MessageUrlMethod\": \"POST\",\n    \"MessageRouteEnabled\": true,\n    \"MessageAuthenticationType\": \"Basic\",\n    \"MessageUsername\": \"admin\",\n    \"MessagePasswordToken\": \"passwordORbearerToken\",\n    \"CallbackMessageUrl\": \"https://apiendpoint.com\",\n    \"CallbackMessageUrlMethod\": \"POST\",\n    \"CallbackMessageAuthenticationType\": \"Basic\",\n    \"CallbackMessageUsername\": \"admin\",\n    \"CallbackMessagePasswordToken\": \"password\"\n}",
											"options": {
												"raw": {
													"language": "json"
												}
											}
										},
										"url": {
											"raw": "https://api.telegent.com/v1.0/message/routes",
											"protocol": "https",
											"host": [
												"api",
												"telegent",
												"com"
											],
											"path": [
												"v1.0",
												"message",
												"routes"
											]
										}
									},
									"_postman_previewlanguage": "json",
									"header": [
										{
											"key": "Content-Type",
											"value": "application/json",
											"description": "",
											"type": "text"
										}
									],
									"cookie": [],
									"body": "{\n    \"MessageRouteId\": \"MRID-ad0ff867-57dc-4aeb-80e9-9d18349080e9\",\n    \"AccountId\": \"DID-eab92510-1040-45a5-bb9c-0bad927SDY878W\",\n    \"RouteName\": \"Main SMS Webhook\",\n    \"MessageUrl\": \"https://apiendpoint.com\",\n    \"MessageUrlMethod\": \"POST\",\n    \"MessageRouteEnabled\": false,\n    \"MessageAuthenticationType\": \"Basic\",\n    \"MessageUsername\": \"admin\",\n    \"MessagePasswordToken\": \"passwordORbearerToken\",\n    \"CallbackMessageUrl\": \"https://apiendpoint.com\",\n    \"CallbackMessageUrlMethod\": \"POST\",\n    \"CallbackMessageAuthenticationType\": \"Basic\",\n    \"CallbackMessageUsername\": \"admin\",\n    \"CallbackMessagePasswordToken\": \"password\"\n}"
								}
							]
						},
						{
							"name": "Update Message Route",
							"request": {
								"method": "POST",
								"header": [],
								"body": {
									"mode": "raw",
									"raw": "{\n    \"MessageRouteId\": \"MRID-01711e7e-c158-4de7-831f-673ab9fdaaa9\", //required for Route Update\n    \"RouteName\": \"Main SMS Webhook\",\n    \"MessageUrl\": \"https://apiendpoint.com\",\n    \"MessageUrlMethod\": \"GET\",\n    \"MessageRouteEnabled\": true,\n    \"MessageAuthenticationType\": \"Basic\",\n    \"MessageUsername\": \"admin\",\n    \"MessagePasswordToken\": \"passwordORbearerToken\",\n    \"CallbackMessageUrl\": \"https://apiendpoint.com\",\n    \"CallbackMessageUrlMethod\": \"POST\",\n    \"CallbackMessageAuthenticationType\": null,\n    \"CallbackMessageUsername\": null,\n    \"CallbackMessagePasswordToken\": null\n}",
									"options": {
										"raw": {
											"language": "json"
										}
									}
								},
								"url": {
									"raw": "https://api.telegent.com/v1.0/message/routes/update",
									"protocol": "https",
									"host": [
										"api",
										"telegent",
										"com"
									],
									"path": [
										"v1.0",
										"message",
										"routes",
										"update"
									]
								},
								"description": "# Update Message Route\n\n## POST /message/routes/update\n\nUpdates an existing message routing configuration with new settings.\n\n### Request\n\n#### Headers\n\n```\nContent-Type: application/json\nAuthorization: Bearer {your_api_token}\n\n ```\n\n#### Body Parameters\n\n| Parameter | Type | Required | Description |\n| --- | --- | --- | --- |\n| `MessageRouteId` | string | Yes | Unique identifier of the route to update |\n| `RouteName` | string | No | New name for the message route |\n| `MessageUrl` | string | No | New webhook URL that will receive incoming messages |\n| `MessageUrlMethod` | string | No | New HTTP method for the webhook |\n| `MessageRouteEnabled` | boolean | No | Whether this route should be active |\n| `MessageAuthenticationType` | string | No | Authentication type for the webhook |\n| `MessageUsername` | string | No | Username for webhook authentication |\n| `MessagePasswordToken` | string | No | Password or token for webhook authentication |\n| `CallbackMessageUrl` | string | No | URL for receiving delivery receipts and callbacks |\n| `CallbackMessageUrlMethod` | string | No | HTTP method for the callback URL |\n| `CallbackMessageAuthenticationType` | string | No | Authentication type for callbacks |\n| `CallbackMessageUsername` | string | No | Username for callback authentication |\n| `CallbackMessagePasswordToken` | string | No | Password or token for callback authentication |\n\n### Sample Request\n\n``` json\n{\n    \"MessageRouteId\": \"MRID-01711e7e-c158-4de7-831f-673ab9fdaaa9\",\n    \"RouteName\": \"Main SMS Webhook\",\n    \"MessageUrl\": \"https://apiendpoint.com\",\n    \"MessageUrlMethod\": \"GET\",\n    \"MessageRouteEnabled\": true,\n    \"MessageAuthenticationType\": \"Basic\",\n    \"MessageUsername\": \"admin\",\n    \"MessagePasswordToken\": \"passwordORbearerToken\",\n    \"CallbackMessageUrl\": \"https://apiendpoint.com\",\n    \"CallbackMessageUrlMethod\": \"POST\",\n    \"CallbackMessageAuthenticationType\": null,\n    \"CallbackMessageUsername\": null,\n    \"CallbackMessagePasswordToken\": null\n}\n\n ```\n\n### Responses\n\n#### 200 OK: Success\n\nReturns the updated message route configuration.\n\n``` json\n{\n    \"MessageRouteId\": \"MRID-01711e7e-c158-4de7-831f-673ab9fdaaa9\",\n    \"AccountId\": \"DID-1e8939ab-3f3c-4db1-89d7-956d80fd793j\",\n    \"RouteName\": \"Main SMS Webhook\",\n    \"MessageUrl\": \"https://apiendpoint.com\",\n    \"MessageUrlMethod\": \"GET\",\n    \"MessageRouteEnabled\": true,\n    \"MessageAuthenticationType\": \"Basic\",\n    \"MessageUsername\": \"admin\",\n    \"MessagePasswordToken\": \"passwordORbearerToken\",\n    \"CallbackMessageUrl\": \"https://apiendpoint.com\",\n    \"CallbackMessageUrlMethod\": \"POST\",\n    \"CallbackMessageAuthenticationType\": null,\n    \"CallbackMessageUsername\": null,\n    \"CallbackMessagePasswordToken\": null\n}\n\n ```\n\n##### Response Fields\n\n| Field | Type | Description |\n| --- | --- | --- |\n| `MessageRouteId` | string | Unique identifier of the message route |\n| `AccountId` | string | Your account identifier |\n| `RouteName` | string | Name of the message route |\n| `MessageUrl` | string | The URL that receives incoming messages |\n| `MessageUrlMethod` | string | HTTP method for the webhook URL |\n| `MessageRouteEnabled` | boolean | Whether the message route is active |\n| `MessageAuthenticationType` | string | Type of authentication used for the webhook |\n| `MessageUsername` | string | Username for webhook authentication |\n| `MessagePasswordToken` | string | Password or token for webhook authentication (masked for security) |\n| `CallbackMessageUrl` | string | URL that receives delivery receipts and callbacks |\n| `CallbackMessageUrlMethod` | string | HTTP method for the callback URL |\n| `CallbackMessageAuthenticationType` | string | Type of authentication used for callbacks |\n| `CallbackMessageUsername` | string | Username for callback authentication |\n| `CallbackMessagePasswordToken` | string | Password or token for callback authentication (masked for security) |\n\n#### 404 Not Found: Route Not Found\n\n``` json\n{\n    \"Type\": \"https://tools.ietf.org/html/rfc7231#section-6.5.4\",\n    \"Title\": \"Not Found\",\n    \"Status\": 404,\n    \"Detail\": \"Message route with ID 'MRID-01711e7e-c158-4de7-831f-673ab9fdaaa9' was not found.\",\n    \"TraceId\": \"00-1234abcd5678efgh-abcdef123456-00\"\n}\n\n ```\n\n#### 400 Bad Request: Validation Error\n\n``` json\n{\n    \"Type\": \"https://tools.ietf.org/html/rfc7231#section-6.5.1\",\n    \"Title\": \"One or more validation errors occurred.\",\n    \"Status\": 400,\n    \"Errors\": {\n        \"$.MessageUrl\": [\"A valid URL is required for the message webhook.\"]\n    },\n    \"TraceId\": \"00-1234abcd5678efgh-abcdef123456-00\"\n}\n\n ```\n\n#### 401 Unauthorized: Authentication Error\n\n``` json\n{\n    \"Type\": \"https://tools.ietf.org/html/rfc7235#section-3.1\",\n    \"Title\": \"Unauthorized\",\n    \"Status\": 401,\n    \"TraceId\": \"00-1234abcd5678efgh-abcdef123456-00\"\n}\n\n ```\n\n### Usage Notes\n\n- Only include the parameters you want to update in the request body.\n    \n- The `MessageRouteId` is required to identify which route to update.\n    \n- To disable or remove authentication, set the relevant authentication fields to `null`.\n    \n- Any phone numbers currently using this route will automatically use the updated configuration.\n    \n- You can temporarily disable a route by setting `MessageRouteEnabled` to `false`.\n    \n- Setting a field to `null` will remove that configuration from the route.\n    \n- After updating, it may take a few moments for the changes to propagate through the system.\n    \n\n### Try It\n\n```\ncurl -X POST \"https://api.telegent.com/v1.0/message/routes/update\" \\\n  -H \"Content-Type: application/json\" \\\n  -H \"Authorization: Bearer YOUR_API_TOKEN\" \\\n  -d '{\n    \"MessageRouteId\": \"MRID-01711e7e-c158-4de7-831f-673ab9fdaaa9\",\n    \"MessageUrlMethod\": \"GET\",\n    \"MessageRouteEnabled\": true,\n    \"CallbackMessageAuthenticationType\": null,\n    \"CallbackMessageUsername\": null,\n    \"CallbackMessagePasswordToken\": null\n}'\n\n ```"
							},
							"response": [
								{
									"name": "Update Message Route",
									"originalRequest": {
										"method": "POST",
										"header": [],
										"body": {
											"mode": "raw",
											"raw": "{\n    \"MessageRouteId\": \"MRID-01711e7e-c158-4de7-831f-673ab9fdaaa9\", //required for Route Update\n    \"RouteName\": \"Main SMS Webhook\",\n    \"MessageUrl\": \"https://apiendpoint.com\",\n    \"MessageUrlMethod\": \"GET\",\n    \"MessageRouteEnabled\": true,\n    \"MessageAuthenticationType\": \"Basic\",\n    \"MessageUsername\": \"admin\",\n    \"MessagePasswordToken\": \"passwordORbearerToken\",\n    \"CallbackMessageUrl\": \"https://apiendpoint.com\",\n    \"CallbackMessageUrlMethod\": \"POST\",\n    \"CallbackMessageAuthenticationType\": null,\n    \"CallbackMessageUsername\": null,\n    \"CallbackMessagePasswordToken\": null\n}",
											"options": {
												"raw": {
													"language": "json"
												}
											}
										},
										"url": {
											"raw": "https://api.telegent.com/v1.0/message/routes/update",
											"protocol": "https",
											"host": [
												"api",
												"telegent",
												"com"
											],
											"path": [
												"v1.0",
												"message",
												"routes",
												"update"
											]
										}
									},
									"_postman_previewlanguage": "json",
									"header": [
										{
											"key": "Content-Type",
											"value": "application/json",
											"description": "",
											"type": "text"
										}
									],
									"cookie": [],
									"body": "{\n    \"MessageRouteId\": \"MRID-01711e7e-c158-4de7-831f-673ab9fdaaa9\",\n    \"AccountId\": \"DID-1e8939ab-3f3c-4db1-89d7-956d80fd793j\",\n    \"RouteName\": \"Main SMS Webhook\",\n    \"MessageUrl\": \"https://apiendpoint.com\",\n    \"MessageUrlMethod\": \"GET\",\n    \"MessageRouteEnabled\": true,\n    \"MessageAuthenticationType\": \"Basic\",\n    \"MessageUsername\": \"admin\",\n    \"MessagePasswordToken\": \"passwordORbearerToken\",\n    \"CallbackMessageUrl\": \"https://apiendpoint.com\",\n    \"CallbackMessageUrlMethod\": \"POST\",\n    \"CallbackMessageAuthenticationType\": null,\n    \"CallbackMessageUsername\": null,\n    \"CallbackMessagePasswordToken\": null\n}"
								}
							]
						},
						{
							"name": "Message Route Details",
							"request": {
								"method": "GET",
								"header": [],
								"url": {
									"raw": "https://api.telegent.com/v1.0/message/routes?MessageRouteId={{MessageRouteId}}",
									"protocol": "https",
									"host": [
										"api",
										"telegent",
										"com"
									],
									"path": [
										"v1.0",
										"message",
										"routes"
									],
									"query": [
										{
											"key": "MessageRouteId",
											"value": "{{MessageRouteId}}"
										}
									]
								},
								"description": "# Get Message Route Details\n\n## GET /message/routes\n\nRetrieves the detailed configuration of a specific message route.\n\n### Request\n\n#### Headers\n\n```\nAuthorization: Bearer {your_api_token}\n\n ```\n\n#### Query Parameters\n\n| Parameter | Type | Required | Description |\n| --- | --- | --- | --- |\n| `MessageRouteId` | string | Yes | Unique identifier of the message route to retrieve |\n\n### Sample Request\n\n```\nGET https://api.telegent.com/v1.0/message/routes?MessageRouteId=MRID-73af1e73-d7b3-4696-bdd9-5b407d9e99ee\n\n ```\n\n### Responses\n\n#### 200 OK: Success\n\nReturns the detailed configuration of the specified message route.\n\n``` json\n{\n    \"MessageRouteId\": \"MRID-01711e7e-c158-4de7-831f-673ab9fdaaa9\",\n    \"AccountId\": \"DID-1e8939ab-3f3c-4db1-89d7-956d80fd793j\",\n    \"RouteName\": \"Main SMS Webhook\",\n    \"MessageUrl\": \"https://apiendpoint.com\",\n    \"MessageUrlMethod\": \"GET\",\n    \"MessageRouteEnabled\": true,\n    \"MessageAuthenticationType\": \"Basic\",\n    \"MessageUsername\": \"admin\",\n    \"MessagePasswordToken\": \"passwordORbearerToken\",\n    \"CallbackMessageUrl\": \"https://apiendpoint.com\",\n    \"CallbackMessageUrlMethod\": \"POST\",\n    \"CallbackMessageAuthenticationType\": null,\n    \"CallbackMessageUsername\": \"admin\",\n    \"CallbackMessagePasswordToken\": null\n}\n\n ```\n\n##### Response Fields\n\n| Field | Type | Description |\n| --- | --- | --- |\n| `MessageRouteId` | string | Unique identifier of the message route |\n| `AccountId` | string | Your account identifier |\n| `RouteName` | string | Name of the message route |\n| `MessageUrl` | string | The URL that receives incoming messages |\n| `MessageUrlMethod` | string | HTTP method for the webhook URL |\n| `MessageRouteEnabled` | boolean | Whether the message route is active |\n| `MessageAuthenticationType` | string | Type of authentication used for the webhook |\n| `MessageUsername` | string | Username for webhook authentication |\n| `MessagePasswordToken` | string | Password or token for webhook authentication (masked for security) |\n| `CallbackMessageUrl` | string | URL that receives delivery receipts and callbacks |\n| `CallbackMessageUrlMethod` | string | HTTP method for the callback URL |\n| `CallbackMessageAuthenticationType` | string | Type of authentication used for callbacks |\n| `CallbackMessageUsername` | string | Username for callback authentication |\n| `CallbackMessagePasswordToken` | string | Password or token for callback authentication (masked for security) |\n\n#### 404 Not Found: Route Not Found\n\n``` json\n{\n    \"Type\": \"https://tools.ietf.org/html/rfc7231#section-6.5.4\",\n    \"Title\": \"Not Found\",\n    \"Status\": 404,\n    \"Detail\": \"Message route with ID 'MRID-73af1e73-d7b3-4696-bdd9-5b407d9e99ee' was not found.\",\n    \"TraceId\": \"00-1234abcd5678efgh-abcdef123456-00\"\n}\n\n ```\n\n#### 401 Unauthorized: Authentication Error\n\n``` json\n{\n    \"Type\": \"https://tools.ietf.org/html/rfc7235#section-3.1\",\n    \"Title\": \"Unauthorized\",\n    \"Status\": 401,\n    \"TraceId\": \"00-1234abcd5678efgh-abcdef123456-00\"\n}\n\n ```\n\n### Usage Notes\n\n- Use this endpoint to verify the current configuration of a message route.\n    \n- The `MessageRouteId` parameter is case-sensitive and must match exactly.\n    \n- For security reasons, the actual authentication credentials may be partially masked in the response.\n    \n- You can retrieve a list of all your message routes using the `/account/message/routes` endpoint.\n    \n- If a route is not found, verify that you're using the correct `MessageRouteId` and that it has not been deleted.\n    \n- This endpoint is useful for confirming that a previous update operation completed successfully.\n    \n\n### Try It\n\n```\ncurl -X GET \"https://api.telegent.com/v1.0/message/routes?MessageRouteId=MRID-73af1e73-d7b3-4696-bdd9-5b407d9e99ee\" \\\n  -H \"Authorization: Bearer YOUR_API_TOKEN\"\n\n ```"
							},
							"response": [
								{
									"name": "Message Route Details",
									"originalRequest": {
										"method": "GET",
										"header": [],
										"url": {
											"raw": "https://api.telegent.com/v1.0/message/routes?MessageRouteId=MRID-73af1e73-d7b3-4696-bdd9-5b407d9e99ee",
											"protocol": "https",
											"host": [
												"api",
												"telegent",
												"com"
											],
											"path": [
												"v1.0",
												"message",
												"routes"
											],
											"query": [
												{
													"key": "MessageRouteId",
													"value": "MRID-73af1e73-d7b3-4696-bdd9-5b407d9e99ee"
												}
											]
										}
									},
									"_postman_previewlanguage": "json",
									"header": [
										{
											"key": "Content-Type",
											"value": "application/json",
											"description": "",
											"type": "text"
										}
									],
									"cookie": [],
									"body": "{\n    \"MessageRouteId\": \"MRID-01711e7e-c158-4de7-831f-673ab9fdaaa9\",\n    \"AccountId\": \"DID-1e8939ab-3f3c-4db1-89d7-956d80fd793j\",\n    \"RouteName\": \"Main SMS Webhook\",\n    \"MessageUrl\": \"https://apiendpoint.com\",\n    \"MessageUrlMethod\": \"GET\",\n    \"MessageRouteEnabled\": true,\n    \"MessageAuthenticationType\": \"Basic\",\n    \"MessageUsername\": \"admin\",\n    \"MessagePasswordToken\": \"passwordORbearerToken\",\n    \"CallbackMessageUrl\": \"https://apiendpoint.com\",\n    \"CallbackMessageUrlMethod\": \"POST\",\n    \"CallbackMessageAuthenticationType\": null,\n    \"CallbackMessageUsername\": \"admin\",\n    \"CallbackMessagePasswordToken\": null\n}"
								}
							]
						},
						{
							"name": "Message Account Routes List",
							"request": {
								"method": "GET",
								"header": [],
								"url": {
									"raw": "https://api.telegent.com/v1.0/account/message/routes",
									"protocol": "https",
									"host": [
										"api",
										"telegent",
										"com"
									],
									"path": [
										"v1.0",
										"account",
										"message",
										"routes"
									]
								},
								"description": "# List Account Message Routes\n\n## GET /account/message/routes\n\nRetrieves a list of all message routes configured for your account.\n\n### Request\n\n#### Headers\n\n```\nAuthorization: Bearer {your_api_token}\n\n ```\n\n### Sample Request\n\n```\nGET https://api.telegent.com/v1.0/account/message/routes\n\n ```\n\n### Responses\n\n#### 200 OK: Success\n\nReturns a list of all message routes configured in your account.\n\n``` json\n{\n    \"AccountID\": \"DID-eab92510-1040-45a5-bb9c-0bad927SDY878W\",\n    \"TotalRoutes\": 2,\n    \"Results\": [\n        {\n            \"MessageRouteId\": \"MRID-ad0ff867-57dc-4aeb-80e9-9d18349080e9\",\n            \"AccountID\": \"DID-eab92510-1040-45a5-bb9c-0bad927SDY878W\",\n            \"RouteName\": \"Main SMS Webhook\",\n            \"MessageUrl\": \"https://apiendpoint.com\",\n            \"MessageUrlMethod\": \"POST\",\n            \"MessageRouteEnabled\": false,\n            \"MessageAuthenticationType\": \"Basic\",\n            \"MessageUsername\": \"admin\",\n            \"MessagePasswordToken\": \"passwordORbearerToken\",\n            \"CallbackMessageUrl\": \"https://apiendpoint.com\",\n            \"CallbackMessageUrlMethod\": \"POST\",\n            \"CallbackMessageAuthenticationType\": \"Basic\",\n            \"CallbackMessageUsername\": \"admin\",\n            \"CallbackMessagePasswordToken\": \"password\"\n        },\n        {\n            \"MessageRouteId\": \"MRID-ad0ff867-57dc-4aeb-80e9-9d18349080e9\",\n            \"AccountID\": \"DID-eab92510-1040-45a5-bb9c-0bad927SDY878W\",\n            \"RouteName\": \"Main SMS Webhook\",\n            \"MessageUrl\": \"https://apiendpoint.com\",\n            \"MessageUrlMethod\": \"POST\",\n            \"MessageRouteEnabled\": false,\n            \"MessageAuthenticationType\": \"Basic\",\n            \"MessageUsername\": \"admin\",\n            \"MessagePasswordToken\": \"passwordORbearerToken\",\n            \"CallbackMessageUrl\": \"https://apiendpoint.com\",\n            \"CallbackMessageUrlMethod\": \"POST\",\n            \"CallbackMessageAuthenticationType\": \"Basic\",\n            \"CallbackMessageUsername\": \"admin\",\n            \"CallbackMessagePasswordToken\": \"password\"\n        }\n    ]\n}\n\n ```\n\n##### Response Fields\n\n| Field | Type | Description |\n| --- | --- | --- |\n| `AccountID` | string | Your account identifier |\n| `TotalRoutes` | integer | Total number of message routes in your account |\n| `Results` | array | List of message route objects |\n\n##### Message Route Object Fields\n\n| Field | Type | Description |\n| --- | --- | --- |\n| `MessageRouteId` | string | Unique identifier of the message route |\n| `AccountID` | string | Your account identifier |\n| `RouteName` | string | Name of the message route |\n| `MessageUrl` | string | The URL that receives incoming messages |\n| `MessageUrlMethod` | string | HTTP method for the webhook URL |\n| `MessageRouteEnabled` | boolean | Whether the message route is active |\n| `MessageAuthenticationType` | string | Type of authentication used for the webhook |\n| `MessageUsername` | string | Username for webhook authentication |\n| `MessagePasswordToken` | string | Password or token for webhook authentication (masked for security) |\n| `CallbackMessageUrl` | string | URL that receives delivery receipts and callbacks |\n| `CallbackMessageUrlMethod` | string | HTTP method for the callback URL |\n| `CallbackMessageAuthenticationType` | string | Type of authentication used for callbacks |\n| `CallbackMessageUsername` | string | Username for callback authentication |\n| `CallbackMessagePasswordToken` | string | Password or token for callback authentication (masked for security) |\n\n#### 401 Unauthorized: Authentication Error\n\n``` json\n{\n    \"Type\": \"https://tools.ietf.org/html/rfc7235#section-3.1\",\n    \"Title\": \"Unauthorized\",\n    \"Status\": 401,\n    \"TraceId\": \"00-1234abcd5678efgh-abcdef123456-00\"\n}\n\n ```\n\n### Usage Notes\n\n- Use this endpoint to view all message routes configured in your account.\n    \n- This is useful for selecting the appropriate route when provisioning or updating phone numbers.\n    \n- Authentication credentials in the response may be partially masked for security reasons.\n    \n- The `MessageRouteEnabled` field indicates whether each route is currently active.\n    \n- You can copy a `MessageRouteId` from this list to use with other endpoints.\n    \n- For detailed information about a specific route, use the `/message/routes` endpoint with a specific `MessageRouteId`.\n    \n- If you have many routes, consider implementing a naming convention that makes it easy to identify the purpose of each route.\n    \n\n### Try It\n\n```\ncurl -X GET \"https://api.telegent.com/v1.0/account/message/routes\" \\\n  -H \"Authorization: Bearer YOUR_API_TOKEN\"\n\n ```"
							},
							"response": [
								{
									"name": "Message Account Routes List",
									"originalRequest": {
										"method": "GET",
										"header": [],
										"url": {
											"raw": "https://api.telegent.com/v1.0/account/message/routes",
											"protocol": "https",
											"host": [
												"api",
												"telegent",
												"com"
											],
											"path": [
												"v1.0",
												"account",
												"message",
												"routes"
											]
										}
									},
									"_postman_previewlanguage": "json",
									"header": [
										{
											"key": "Content-Type",
											"value": "application/json",
											"description": "",
											"type": "text"
										}
									],
									"cookie": [],
									"body": "{\n    \"AccountID\": \"DID-eab92510-1040-45a5-bb9c-0bad927SDY878W\",\n    \"TotalRoutes\": 2,\n    \"Results\": [\n{\n    \"MessageRouteId\": \"MRID-ad0ff867-57dc-4aeb-80e9-9d18349080e9\",\n    \"AccountID\": \"DID-eab92510-1040-45a5-bb9c-0bad927SDY878W\",\n    \"RouteName\": \"Main SMS Webhook\",\n    \"MessageUrl\": \"https://apiendpoint.com\",\n    \"MessageUrlMethod\": \"POST\",\n    \"MessageRouteEnabled\": false,\n    \"MessageAuthenticationType\": \"Basic\",\n    \"MessageUsername\": \"admin\",\n    \"MessagePasswordToken\": \"passwordORbearerToken\",\n    \"CallbackMessageUrl\": \"https://apiendpoint.com\",\n    \"CallbackMessageUrlMethod\": \"POST\",\n    \"CallbackMessageAuthenticationType\": \"Basic\",\n    \"CallbackMessageUsername\": \"admin\",\n    \"CallbackMessagePasswordToken\": \"password\"\n},\n{\n    \"MessageRouteId\": \"MRID-ad0ff867-57dc-4aeb-80e9-9d18349080e9\",\n    \"AccountID\": \"DID-eab92510-1040-45a5-bb9c-0bad927SDY878W\",\n    \"RouteName\": \"Main SMS Webhook\",\n    \"MessageUrl\": \"https://apiendpoint.com\",\n    \"MessageUrlMethod\": \"POST\",\n    \"MessageRouteEnabled\": false,\n    \"MessageAuthenticationType\": \"Basic\",\n    \"MessageUsername\": \"admin\",\n    \"MessagePasswordToken\": \"passwordORbearerToken\",\n    \"CallbackMessageUrl\": \"https://apiendpoint.com\",\n    \"CallbackMessageUrlMethod\": \"POST\",\n    \"CallbackMessageAuthenticationType\": \"Basic\",\n    \"CallbackMessageUsername\": \"admin\",\n    \"CallbackMessagePasswordToken\": \"password\"\n}\n    ]\n}"
								}
							]
						},
						{
							"name": "Send Outbound Message",
							"request": {
								"method": "POST",
								"header": [],
								"body": {
									"mode": "raw",
									"raw": "{\n    \"CampaignId\": \"JCID-dsuhofh3882\",\n    \"To\":\n    [\n        {\n            \"Number\": \"+18015737111\"\n        },\n        {\n            \"Number\": \"+18014271919\"\n        }\n    ],\n    \"From\": \"+18018018011\",\n    \"Owner\": \"+18018018011\",\n    \"Body\": \"Hello there!!!\",\n    \"MmsMedia\":\n    [\n        {\n            \"MediaUrl\": \"https://results2.com\"\n        },\n        {\n            \"MediaUrl\": \"https://results.com\"\n        }\n    ],\n    \"MmsBase64\":\n    [\n        {\n            \"Base64\":\"dkjjkdflajdfjo3ji3jjljfkjaskjfad\",\n            \"BaseType\": \"audio/wav\"\n        },\n        {\n            \"Base64\":\"dkjjkdflajdfjo3ji3jjljfkjaskjfad\",\n            \"BaseType\": \"video/mpg\"\n        }\n    ]\n}",
									"options": {
										"raw": {
											"language": "json"
										}
									}
								},
								"url": {
									"raw": "https://api.telegent.com/v1.0/message/outbound",
									"protocol": "https",
									"host": [
										"api",
										"telegent",
										"com"
									],
									"path": [
										"v1.0",
										"message",
										"outbound"
									]
								},
								"description": "## POST /message/outbound\n\nSends an outbound SMS or MMS message from your phone number to one or more recipients.\n\n### Request\n\n#### Headers\n\n```\nContent-Type: application/json\nAuthorization: Bearer {your_api_token}\n\n ```\n\n#### Body Parameters\n\n| Parameter | Type | Required | Description |\n| --- | --- | --- | --- |\n| `CampaignId` | string | No | Optional identifier for tracking message campaigns |\n| `To` | array | Yes | Array of recipient phone numbers |\n| `To[].Number` | string | Yes | Phone number in E.164 format (e.g., +12125551234) |\n| `From` | string | Yes | Sender's phone number in E.164 format |\n| `Owner` | string | Yes | Phone number that owns the conversation |\n| `Body` | string | Yes | Text content of the message |\n| `MmsMedia` | array | No | Array of media URLs for MMS (if sending multimedia) |\n| `MmsMedia[].MediaUrl` | string | Yes (if in array) | URL to media content for MMS |\n| `MmsBase64` | array | No | Array of base64-encoded media for MMS |\n| `MmsBase64[].Base64` | string | Yes (if in array) | Base64-encoded media content |\n| `MmsBase64[].BaseType` | string | Yes (if in array) | MIME type of the media (e.g., audio/wav, image/jpeg) |\n\n### Sample Request - SMS\n\n``` json\n{\n    \"To\": [\n        {\n            \"Number\": \"+12016093801\"\n        }\n    ],\n    \"From\": \"+18018018011\",\n    \"Owner\": \"+18018018011\",\n    \"Body\": \"Hello there!!!\"\n}\n\n ```\n\n### Sample Request - MMS\n\n``` json\n{\n    \"CampaignId\": \"JCID-dsuhofh3882\",\n    \"To\": [\n        {\n            \"Number\": \"+12017540706\"\n        },\n        {\n            \"Number\": \"+12137880121\"\n        }\n    ],\n    \"From\": \"+18018018011\",\n    \"Owner\": \"+18018018011\",\n    \"Body\": \"Hello there!!!\",\n    \"MmsMedia\": [\n        {\n            \"MediaUrl\": \"https://results2.com\"\n        },\n        {\n            \"MediaUrl\": \"https://results.com\"\n        }\n    ],\n    \"MmsBase64\": [\n        {\n            \"Base64\": \"dkjjkdflajdfjo3ji3jjljfkjaskjfad\",\n            \"BaseType\": \"audio/wav\"\n        },\n        {\n            \"Base64\": \"dkjjkdflajdfjo3ji3jjljfkjaskjfad\",\n            \"BaseType\": \"video/mpg\"\n        }\n    ]\n}\n\n ```\n\n### Responses\n\n#### 200 OK: Success - SMS\n\nReturns details about the sent SMS message.\n\n``` json\n{\n    \"MessageId\": \"1116\",\n    \"Direction\": \"OUTBOUND\",\n    \"Type\": \"a2p\",\n    \"CampaignId\": null,\n    \"Cost\": 0.0000,\n    \"To\": [\n        {\n            \"Number\": \"+12016093801\"\n        }\n    ],\n    \"From\": \"+18018018011\",\n    \"Owner\": \"+18018018011\",\n    \"Body\": \"Hello there!!!\",\n    \"Country\": \"United States\",\n    \"CreatedOn\": \"2025-05-14T17:30:02.817\",\n    \"MessageType\": \"sms\",\n    \"MmsMedia\": [],\n    \"MmsBase64\": [],\n    \"Status\": \"Queued\"\n}\n\n ```\n\n#### 200 OK: Success - MMS\n\nReturns details about the sent MMS message.\n\n``` json\n{\n    \"MessageId\": \"TMID-00348008102307aK01\",\n    \"Direction\": \"Outbound\",\n    \"Type\": \"p2p\",\n    \"CampaignId\": \"TCID-dsuhofh3882\",\n    \"Cost\": 0.0045,\n    \"Status\": \"Queued\",\n    \"To\": [\n        {\n            \"Number\": \"+12016093801\"\n        },\n        {\n            \"Number\": \"+12232233180\"\n        }\n    ],\n    \"From\": \"+18018018011\",\n    \"Owner\": \"+18018018011\",\n    \"Body\": \"Hello there!!!\",\n    \"CreatedOn\": \"16:45:59 MST 2025-01-23\",\n    \"MessageType\": \"mms\",\n    \"MmsMedia\": [\n        {\n            \"MediaUrl\": \"https://results2.com\"\n        },\n        {\n            \"MediaUrl\": \"https://results.com\"\n        }\n    ],\n    \"MmsBase64\": [\n        {\n            \"Base64\": \"dkjjkdflajdfjo3ji3jjljfkjaskjfad\",\n            \"BaseType\": \"audio/wav\"\n        },\n        {\n            \"Base64\": \"dkjjkdflajdfjo3ji3jjljfkjaskjfad\",\n            \"BaseType\": \"video/mpg\"\n        }\n    ]\n}\n\n ```\n\n##### Response Fields\n\n| Field | Type | Description |\n| --- | --- | --- |\n| `MessageId` | string | Unique identifier for the message |\n| `Direction` | string | Direction of the message (always \"OUTBOUND\" or \"Outbound\") |\n| `Type` | string | Type of message (p2p or a2p) |\n| `CampaignId` | string | Campaign identifier if provided |\n| `Cost` | number | Cost of sending the message |\n| `Status` | string | Current status of the message (typically \"Queued\") |\n| `To` | array | Recipients of the message |\n| `From` | string | Sender's phone number |\n| `Owner` | string | Phone number that owns the conversation |\n| `Body` | string | Text content of the message |\n| `Country`/`Region` | string | Country or region of the recipient |\n| `CreatedOn` | string | Timestamp when the message was created |\n| `MessageType` | string | Type of message (sms or mms) |\n| `MmsMedia` | array | Media URLs for MMS messages |\n| `MmsBase64` | array | Base64-encoded media for MMS messages |\n\n#### 400 Bad Request: Validation Error\n\n``` json\n{\n    \"Type\": \"https://tools.ietf.org/html/rfc7231#section-6.5.1\",\n    \"Title\": \"One or more validation errors occurred.\",\n    \"Status\": 400,\n    \"Errors\": {\n        \"$.From\": [\"The From number must be in E.164 format and be a valid number in your account.\"]\n    },\n    \"TraceId\": \"00-1234abcd5678efgh-abcdef123456-00\"\n}\n\n ```\n\n#### 401 Unauthorized: Authentication Error\n\n``` json\n{\n    \"Type\": \"https://tools.ietf.org/html/rfc7235#section-3.1\",\n    \"Title\": \"Unauthorized\",\n    \"Status\": 401,\n    \"TraceId\": \"00-1234abcd5678efgh-abcdef123456-00\"\n}\n\n ```\n\n### Usage Notes\n\n- The `From` number must be a valid phone number in your account with messaging enabled.\n    \n- All phone numbers should be in E.164 format (e.g., +12125551234).\n    \n- The `Owner` field establishes message thread ownership and is typically the same as the `From` number.\n    \n- For SMS messages, only include the `Body` parameter.\n    \n- For MMS messages, you can include `MmsMedia` URLs, `MmsBase64` encoded content, or both.\n    \n- When sending MMS with base64 content, ensure you specify the correct MIME type in `BaseType`.\n    \n- The `CampaignId` parameter is optional but useful for tracking campaigns and message groups.\n    \n- The `Status` field in the response indicates the initial status. Status updates may be delivered to your callback URL.\n    \n- The `Cost` field indicates the cost of sending the message.\n    \n- You can send a message to multiple recipients by adding more objects to the `To` array.\n    \n- When sending to multiple recipients, a separate message is generated for each recipient.\n    \n\n### Try It\n\n```\ncurl -X POST \"https://api.telegent.com/v1.0/message/outbound\" \\\n  -H \"Content-Type: application/json\" \\\n  -H \"Authorization: Bearer YOUR_API_TOKEN\" \\\n  -d '{\n    \"To\": [\n        {\n            \"Number\": \"+12016093801\"\n        }\n    ],\n    \"From\": \"+18018018011\",\n    \"Owner\": \"+18018018011\",\n    \"Body\": \"Hello there!!!\"\n}'\n\n ```"
							},
							"response": [
								{
									"name": "Send Outbound Message - SMS",
									"originalRequest": {
										"method": "POST",
										"header": [],
										"body": {
											"mode": "raw",
											"raw": "{\n    \"To\":\n    [\n        {\n            \"Number\": \"+12016093801\"\n        }\n    ],\n    \"From\": \"+18018018011\",\n    \"Owner\": \"+18018018011\",\n    \"Body\": \"Hello there!!!\"\n}",
											"options": {
												"raw": {
													"language": "json"
												}
											}
										},
										"url": {
											"raw": "https://api.telegent.com/v1.0/message/outbound",
											"protocol": "https",
											"host": [
												"api",
												"telegent",
												"com"
											],
											"path": [
												"v1.0",
												"message",
												"outbound"
											]
										}
									},
									"_postman_previewlanguage": "json",
									"header": [
										{
											"key": "Content-Type",
											"value": "application/json",
											"description": "",
											"type": "text"
										}
									],
									"cookie": [],
									"body": "{\n    \"MessageId\": \"1116\",\n    \"Direction\": \"OUTBOUND\",\n    \"Type\": \"a2p\",\n    \"CampaignId\": null,\n    \"Cost\": 0.0000,\n    \"To\": \n    [\n        {\n            \"Number\": \"+12016093801\"\n        }\n    ],\n    \"From\": \"+18018018011\",\n    \"Owner\": \"+18018018011\",\n    \"Body\": \"Hello there!!!\",\n    \"Country\": \"United States\",\n    \"CreatedOn\": \"2025-05-14T17:30:02.817\",\n    \"MessageType\": \"sms\",\n    \"MmsMedia\": [],\n    \"MmsBase64\": [],\n    \"Status\": \"Queued\"\n}"
								},
								{
									"name": "Send Outbound Message - MMS",
									"originalRequest": {
										"method": "POST",
										"header": [],
										"body": {
											"mode": "raw",
											"raw": "{\n    \"CampaignID\": \"JCID-dsuhofh3882\",\n    \"To\":\n    [\n        {\n            \"Number\": \"+12017540706\"\n        },\n        {\n            \"Number\": \"+12137880121\"\n        }\n    ],\n    \"From\": \"+18018018011\",\n    \"Owner\": \"+18018018011\",\n    \"Body\": \"Hello there!!!\",\n    \"MmsMedia\":\n    [\n        {\n            \"MediaUrl\": \"https://results2.com\"\n        },\n        {\n            \"MediaUrl\": \"https://results.com\"\n        }\n    ],\n    \"MmsBase64\":\n    [\n        {\n            \"Base64\":\"dkjjkdflajdfjo3ji3jjljfkjaskjfad\",\n            \"BaseType\": \"audio/wav\"\n        },\n        {\n            \"Base64\":\"dkjjkdflajdfjo3ji3jjljfkjaskjfad\",\n            \"BaseType\": \"video/mpg\"\n        }\n    ]\n}",
											"options": {
												"raw": {
													"language": "json"
												}
											}
										},
										"url": {
											"raw": "https://api.telegent.com/v1.0/message/outbound",
											"protocol": "https",
											"host": [
												"api",
												"telegent",
												"com"
											],
											"path": [
												"v1.0",
												"message",
												"outbound"
											]
										}
									},
									"_postman_previewlanguage": "json",
									"header": [
										{
											"key": "Content-Type",
											"value": "application/json",
											"description": "",
											"type": "text"
										}
									],
									"cookie": [],
									"body": "{\n    \"MessageId\": \"TMID-00348008102307aK01\",\n    \"Direction\": \"Outbound\",\n    \"Type\": \"p2p\",\n    \"CampaignId\": \"TCID-dsuhofh3882\",\n    \"Cost\": 0.0045,\n    \"Status\": \"Queued\",\n    \"To\":\n    [\n        {\n            \"Number\": \"+12016093801\"\n        },\n        {\n            \"Number\": \"+12232233180\"\n        }\n    ],\n    \"From\": \"+18018018011\",\n    \"Owner\": \"+18018018011\",\n    \"Body\": \"Hello there!!!\",\n    \"CreatedOn\": \"16:45:59 MST 2025-01-23\",\n    \"MessageType\": \"mms\",\n    \"MmsMedia\":\n    [\n        {\n            \"MediaUrl\": \"https://results2.com\"\n        },\n        {\n            \"MediaUrl\": \"https://results.com\"\n        }\n    ],\n    \"MmsBase64\":\n    [\n        {\n            \"Base64\":\"dkjjkdflajdfjo3ji3jjljfkjaskjfad\",\n            \"BaseType\": \"audio/wav\"\n        },\n        {\n            \"Base64\":\"dkjjkdflajdfjo3ji3jjljfkjaskjfad\",\n            \"BaseType\": \"video/mpg\"\n        }\n    ]\n}  \n"
								}
							]
						},
						{
							"name": "Message Details",
							"request": {
								"method": "GET",
								"header": [],
								"url": {
									"raw": "https://api.telegent.com/v1.0/message/details?MessageId=TMID-948AFE64-A7A9-45D4-A30A-DB7CFB57A2B6",
									"protocol": "https",
									"host": [
										"api",
										"telegent",
										"com"
									],
									"path": [
										"v1.0",
										"message",
										"details"
									],
									"query": [
										{
											"key": "MessageId",
											"value": "TMID-948AFE64-A7A9-45D4-A30A-DB7CFB57A2B6"
										}
									]
								},
								"description": "# Get Message Details\n\n## GET /message/details\n\nRetrieves detailed information about a specific message by its ID.\n\n### Request\n\n#### Headers\n\n```\nAuthorization: Bearer {your_api_token}\n\n ```\n\n#### Query Parameters\n\n| Parameter | Type | Required | Description |\n| --- | --- | --- | --- |\n| `MessageId` | string | Yes | Unique identifier of the message to retrieve |\n\n### Sample Request\n\n```\nGET https://api.telegent.com/v1.0/message/details?MessageId=TMID-948AFE64-A7A9-45D4-A30A-DB7CFB57A2B6\n\n ```\n\n### Responses\n\n#### 200 OK: Success - SMS\n\nReturns detailed information about the SMS message.\n\n``` json\n{\n    \"MessageId\": \"TMID-948AFE64-A7A9-45D4-A30A-DB7CFB57A2B6\",\n    \"Direction\": \"OUTBOUND\",\n    \"Type\": \"p2p\",\n    \"CampaignId\": \"JCID-dsuhofh3882\",\n    \"Cost\": 0.0000,\n    \"To\": \"+18015737111\",\n    \"From\": \"+18018018011\",\n    \"Body\": \"Hello there!!!\",\n    \"Region\": \"United States\",\n    \"CreatedOn\": \"2025-05-15T20:15:37.157\",\n    \"MessageType\": \"sms\",\n    \"Status\": \"Queued\"\n}\n\n ```\n\n#### 200 OK: Success - MMS\n\nReturns detailed information about the MMS message, including media content.\n\n``` json\n{\n    \"MessageId\": \"TMID-948AFE64-A7A9-45D4-A30A-DB7CFB57A2B6\",\n    \"Direction\": \"OUTBOUND\",\n    \"Type\": \"p2p\",\n    \"CampaignId\": \"JCID-dsuhofh3882\",\n    \"Cost\": 0.0000,\n    \"To\": \"+18015737111\",\n    \"From\": \"+18018018011\",\n    \"Body\": \"Hello there!!!\",\n    \"Region\": \"United States\",\n    \"CreatedOn\": \"2025-05-15T20:15:37.157\",\n    \"MessageType\": \"mms\",\n    \"MmsMedia\": [\n        {\n            \"MediaUrl\": \"https://results.com\"\n        }\n    ],\n    \"Status\": \"Delivered\"\n}\n\n ```\n\n##### Response Fields\n\n| Field | Type | Description |\n| --- | --- | --- |\n| `MessageId` | string | Unique identifier of the message |\n| `Direction` | string | Direction of the message (\"INBOUND\" or \"OUTBOUND\") |\n| `Type` | string | Type of message (p2p or a2p) |\n| `CampaignId` | string | Campaign identifier if provided when sending |\n| `Cost` | number | Cost of sending the message |\n| `To` | string | Recipient's phone number |\n| `From` | string | Sender's phone number |\n| `Body` | string | Text content of the message |\n| `Region` | string | Country or region of the recipient |\n| `CreatedOn` | string | Timestamp when the message was created |\n| `MessageType` | string | Type of message (sms or mms) |\n| `MmsMedia` | array | Media URLs (only present for MMS messages) |\n| `Status` | string | Current status of the message (Queued, Sent, Delivered, Failed, etc.) |\n\n#### 404 Not Found: Message Not Found\n\n``` json\n{\n    \"Type\": \"https://tools.ietf.org/html/rfc7231#section-6.5.4\",\n    \"Title\": \"Not Found\",\n    \"Status\": 404,\n    \"Detail\": \"Message with ID 'TMID-948AFE64-A7A9-45D4-A30A-DB7CFB57A2B6' was not found.\",\n    \"TraceId\": \"00-1234abcd5678efgh-abcdef123456-00\"\n}\n\n ```\n\n#### 401 Unauthorized: Authentication Error\n\n``` json\n{\n    \"Type\": \"https://tools.ietf.org/html/rfc7235#section-3.1\",\n    \"Title\": \"Unauthorized\",\n    \"Status\": 401,\n    \"TraceId\": \"00-1234abcd5678efgh-abcdef123456-00\"\n}\n\n ```\n\n### Usage Notes\n\n- The `MessageId` parameter is case-sensitive and must match exactly.\n    \n- Use this endpoint to track the status of a specific message.\n    \n- The `Status` field indicates the current state of the message in the delivery process.\n    \n- For MMS messages, media content URLs or base64 data will be included in the response.\n    \n- Message details are typically retained for a limited period of time (e.g., 30-90 days).\n    \n- This endpoint is useful for confirming delivery, checking message status, and troubleshooting failed messages.\n    \n- To search for messages by phone number instead of message ID, use the `/message/search` endpoint.\n    \n- The `Cost` field provides the actual cost incurred for sending the message.\n    \n- If a message is not found, verify that the MessageId is correct and that the message was sent within the retention period.\n    \n\n### Try It\n\n```\ncurl -X GET \"https://api.telegent.com/v1.0/message/details?MessageId=TMID-948AFE64-A7A9-45D4-A30A-DB7CFB57A2B6\" \\\n  -H \"Authorization: Bearer YOUR_API_TOKEN\"\n\n ```"
							},
							"response": [
								{
									"name": "Message Details - SMS",
									"originalRequest": {
										"method": "GET",
										"header": [],
										"url": {
											"raw": "https://api.telegent.com/v1.0/messages/details?messageID=TMID-00348008102307aT03",
											"protocol": "https",
											"host": [
												"api",
												"telegent",
												"com"
											],
											"path": [
												"v1.0",
												"messages",
												"details"
											],
											"query": [
												{
													"key": "messageID",
													"value": "TMID-00348008102307aT03"
												}
											]
										}
									},
									"_postman_previewlanguage": "json",
									"header": [
										{
											"key": "Content-Type",
											"value": "application/json",
											"description": "",
											"type": "text"
										}
									],
									"cookie": [],
									"body": "    \"MessageId\": \"TMID-948AFE64-A7A9-45D4-A30A-DB7CFB57A2B6\",\n    \"Direction\": \"OUTBOUND\",\n    \"Type\": \"p2p\",\n    \"CampaignId\": \"JCID-dsuhofh3882\",\n    \"Cost\": 0.0000,\n    \"To\": \"+18015737111\",\n    \"From\": \"+18018018011\",\n    \"Body\": \"Hello there!!!\",\n    \"Region\": \"United States\",\n    \"CreatedOn\": \"2025-05-15T20:15:37.157\",\n    \"MessageType\": \"sms\",\n    \"Status\": \"Queued\"\n}"
								},
								{
									"name": "Message Details - MMS",
									"originalRequest": {
										"method": "GET",
										"header": [],
										"url": {
											"raw": "https://api.telegent.com/v1.0/messages/details?messageID=TMID-00348008102307aT03",
											"protocol": "https",
											"host": [
												"api",
												"telegent",
												"com"
											],
											"path": [
												"v1.0",
												"messages",
												"details"
											],
											"query": [
												{
													"key": "messageID",
													"value": "TMID-00348008102307aT03"
												}
											]
										}
									},
									"_postman_previewlanguage": "json",
									"header": [
										{
											"key": "Content-Type",
											"value": "application/json",
											"description": "",
											"type": "text"
										}
									],
									"cookie": [],
									"body": "    \"MessageId\": \"TMID-948AFE64-A7A9-45D4-A30A-DB7CFB57A2B6\",\n    \"Direction\": \"OUTBOUND\",\n    \"Type\": \"p2p\",\n    \"CampaignId\": \"JCID-dsuhofh3882\",\n    \"Cost\": 0.0000,\n    \"To\": \"+18015737111\",\n    \"From\": \"+18018018011\",\n    \"Body\": \"Hello there!!!\",\n    \"Region\": \"United States\",\n    \"CreatedOn\": \"2025-05-15T20:15:37.157\",\n    \"MessageType\": \"sms\",\n    \"Status\": \"Queued\"\n}"
								}
							]
						},
						{
							"name": "Message Search",
							"event": [
								{
									"listen": "test",
									"script": {
										"exec": [
											"// Test to check for PascalCase on all input and output parameters",
											"pm.test(\"All input and output parameters are in PascalCase\", function () {",
											"    var responseJSON = pm.response.json();",
											"    ",
											"    // Check request query parameters",
											"    pm.expect(pm.request.url.query.all()).to.be.pascalCase;",
											"",
											"    // Check response body keys",
											"    Object.keys(responseJSON).forEach((key) => {",
											"        pm.expect(key).to.be.pascalCase;",
											"    });",
											"});",
											""
										],
										"type": "text/javascript",
										"packages": {}
									}
								}
							],
							"request": {
								"method": "GET",
								"header": [],
								"url": {
									"raw": "https://api.telegent.com/v1.0/message/search?phoneNumber=18018018011",
									"protocol": "https",
									"host": [
										"api",
										"telegent",
										"com"
									],
									"path": [
										"v1.0",
										"message",
										"search"
									],
									"query": [
										{
											"key": "phoneNumber",
											"value": "18018018011"
										}
									]
								},
								"description": "# Search Messages\n\n## GET /message/search\n\nRetrieves all messages associated with a specific phone number.\n\n### Request\n\n#### Headers\n\n```\nAuthorization: Bearer {your_api_token}\n```\n\n#### Query Parameters\n\n| Parameter | Type | Required | Description |\n|-----------|------|----------|-------------|\n| `PhoneNumber` | string | Yes | Phone number to search for in message records |\n| `PageNumber` | integer | No | Page number for paginated results (starts at 1) |\n| `PageSize` | integer | No | Number of messages per page |\n| `StartDate` | string | No | Filter messages from this date (format: YYYY-MM-DD) |\n| `EndDate` | string | No | Filter messages to this date (format: YYYY-MM-DD) |\n| `Direction` | string | No | Filter by message direction (Inbound, Outbound) |\n| `MessageType` | string | No | Filter by message type (sms, mms) |\n\n### Sample Request\n\n```\nGET https://api.telegent.com/v1.0/message/search?PhoneNumber=18018018011\n```\n\n### Responses\n\n#### 200 OK: Success\n\nReturns a list of messages associated with the specified phone number.\n\n```json\n{\n    \"PhoneNumber\": \"+18015555555\",\n    \"ResultsTotalRecords\": 2,\n    \"ResultsPages\": 1,\n    \"Results\": [\n        {\n            \"MessageId\": \"TMID-00348008102307aT03\",\n            \"Direction\": \"Inbound\",\n            \"Type\": \"a2p\",\n            \"CampaignId\": \"JCID-dsuhofh3882\",\n            \"Cost\": \"$0.0045\",\n            \"Status\": \"Received\",\n            \"To\": [\n                {\n                    \"Number\": \"+12016093801\"\n                },\n                {\n                    \"Number\": \"+12232233180\"\n                }\n            ],\n            \"From\": \"+18018018011\",\n            \"Owner\": \"+18018018011\",\n            \"Body\": \"Hello there!!!\",\n            \"MmsMedia\": [\n                {\n                    \"MediaUrl\": \"https://results2.com\"\n                },\n                {\n                    \"MediaUrl\": \"https://results.com\"\n                }\n            ],\n            \"MmsBase64\": [\n                {\n                    \"Base64\": \"dkjjkdflajdfjo3ji3jjljfkjaskjfad\",\n                    \"BaseType\": \"audio/wav\"\n                },\n                {\n                    \"Base64\": \"dkjjkdflajdfjo3ji3jjljfkjaskjfad\",\n                    \"BaseType\": \"video/mpg\"\n                }\n            ]\n        },\n        {\n            \"MessageId\": \"TMID-00348008102307aT04\",\n            \"Direction\": \"Inbound\",\n            \"Type\": \"a2p\",\n            \"CampaignId\": \"JCID-dsuhofh3882\",\n            \"Cost\": \"$0.0045\",\n            \"Status\": \"Received\",\n            \"To\": [\n                {\n                    \"Number\": \"+12016093801\"\n                },\n                {\n                    \"Number\": \"+12232233180\"\n                }\n            ],\n            \"From\": \"+18018018011\",\n            \"Owner\": \"+18018018011\",\n            \"Body\": \"Another TEST!!!\",\n            \"MmsMedia\": [\n                {\n                    \"MediaUrl\": \"https://results2.com\"\n                },\n                {\n                    \"MediaUrl\": \"https://results.com\"\n                }\n            ],\n            \"MmsBase64\": [\n                {\n                    \"Base64\": \"dkjjkdflajdfjo3ji3jjljfkjaskjfad\",\n                    \"BaseType\": \"audio/wav\"\n                },\n                {\n                    \"Base64\": \"dkjjkdflajdfjo3ji3jjljfkjaskjfad\",\n                    \"BaseType\": \"video/mpg\"\n                }\n            ]\n        }\n    ]\n}\n```\n\n##### Response Fields\n\n| Field | Type | Description |\n|-------|------|-------------|\n| `PhoneNumber` | string | The phone number used for the search |\n| `ResultsTotalRecords` | integer | Total number of messages found |\n| `ResultsPages` | integer | Total number of pages available |\n| `Results` | array | List of message objects |\n\n##### Message Object Fields\n\n| Field | Type | Description |\n|-------|------|-------------|\n| `MessageId` | string | Unique identifier of the message |\n| `Direction` | string | Direction of the message (Inbound or Outbound) |\n| `Type` | string | Type of message (p2p or a2p) |\n| `CampaignId` | string | Campaign identifier if provided |\n| `Cost` | string | Cost of the message (formatted with currency symbol) |\n| `Status` | string | Current status of the message |\n| `To` | array | Recipients of the message |\n| `From` | string | Sender's phone number |\n| `Owner` | string | Phone number that owns the conversation |\n| `Body` | string | Text content of the message |\n| `MmsMedia` | array | Media URLs for MMS messages (if applicable) |\n| `MmsBase64` | array | Base64-encoded media for MMS messages (if applicable) |\n\n#### 400 Bad Request: Invalid Phone Number\n\n```json\n{\n    \"Type\": \"https://tools.ietf.org/html/rfc7231#section-6.5.1\",\n    \"Title\": \"One or more validation errors occurred.\",\n    \"Status\": 400,\n    \"Errors\": {\n        \"$.PhoneNumber\": [\"Invalid phone number format.\"]\n    },\n    \"TraceId\": \"00-1234abcd5678efgh-abcdef123456-00\"\n}\n```\n\n#### 401 Unauthorized: Authentication Error\n\n```json\n{\n    \"Type\": \"https://tools.ietf.org/html/rfc7235#section-3.1\",\n    \"Title\": \"Unauthorized\",\n    \"Status\": 401,\n    \"TraceId\": \"00-1234abcd5678efgh-abcdef123456-00\"\n}\n```\n\n### Usage Notes\n\n- The `PhoneNumber` parameter can be provided with or without the \"+\" prefix.\n- The search matches messages where the specified phone number appears as either the sender or recipient.\n- Results are paginated; use the `PageNumber` and `PageSize` parameters to navigate through large result sets.\n- For targeted searches, use the optional filter parameters like `StartDate`, `EndDate`, `Direction`, and `MessageType`.\n- Message history is typically retained for a limited period (e.g., 30-90 days).\n- The `ResultsTotalRecords` field indicates the total number of messages that match your search criteria.\n- The `ResultsPages` field indicates how many pages of results are available.\n- For large result sets, consider using more specific search criteria to narrow down the results.\n- If searching for recent messages, allow a few minutes for them to be indexed in the search system.\n\n### Try It\n\n```\ncurl -X GET \"https://api.telegent.com/v1.0/message/search?PhoneNumber=18018018011\" \\\n  -H \"Authorization: Bearer YOUR_API_TOKEN\"\n```"
							},
							"response": [
								{
									"name": "Message Search",
									"originalRequest": {
										"method": "GET",
										"header": [],
										"url": {
											"raw": "https://api.telegent.com/v1.0/messages/search?PhoneNumber=18015555555",
											"protocol": "https",
											"host": [
												"api",
												"telegent",
												"com"
											],
											"path": [
												"v1.0",
												"messages",
												"search"
											],
											"query": [
												{
													"key": "PhoneNumber",
													"value": "18015555555"
												}
											]
										}
									},
									"_postman_previewlanguage": "json",
									"header": [
										{
											"key": "Content-Type",
											"value": "application/json",
											"description": "",
											"type": "text"
										}
									],
									"cookie": [],
									"body": "{\n    \"PhoneNumber\": \"+18015555555\",\n    \"ResultsTotalRecords\": 2,\n    \"ResultsPages\": 1,\n    \"Results\":[\n    {\n    \"MessageID\": \"TMID-00348008102307aT03\",\n    \"Direction\": \"Inbound\",\n    \"Type\": \"a2p\",\n    \"CampaignID\": \"JCID-dsuhofh3882\",\n    \"Cost\": \"$0.0045\",\n    \"Status\": \"Received\",\n    \"To\":\n    [\n        {\n            \"Number\": \"+12016093801\"\n        },\n        {\n            \"Number\": \"+12232233180\"\n        }\n    ],\n    \"From\": \"+18018018011\",\n    \"Owner\": \"+18018018011\",\n    \"Body\": \"Hello there!!!\",\n    \"MmsMedia\":\n    [\n        {\n            \"MediaUrl\": \"https://results2.com\"\n        },\n        {\n            \"MediaUrl\": \"https://results.com\"\n        }\n    ],\n    \"MmsBase64\":\n    [\n        {\n            \"Base64\":\"dkjjkdflajdfjo3ji3jjljfkjaskjfad\",\n            \"BaseType\": \"audio/wav\"\n        },\n        {\n            \"Base64\":\"dkjjkdflajdfjo3ji3jjljfkjaskjfad\",\n            \"BaseType\": \"video/mpg\"\n        }\n    ]\n},\n    {\n    \"MessageID\": \"TMID-00348008102307aT04\",\n    \"Direction\": \"Inbound\",\n    \"Type\": \"a2p\",\n    \"CampaignID\": \"JCID-dsuhofh3882\",\n    \"Cost\": \"$0.0045\",\n    \"Status\": \"Received\",\n    \"To\":\n    [\n        {\n            \"Number\": \"+12016093801\"\n        },\n        {\n            \"Number\": \"+12232233180\"\n        }\n    ],\n    \"From\": \"+18018018011\",\n    \"Owner\": \"+18018018011\",\n    \"Body\": \"Another TEST!!!\",\n    \"MmsMedia\":\n    [\n        {\n            \"MediaUrl\": \"https://results2.com\"\n        },\n        {\n            \"MediaUrl\": \"https://results.com\"\n        }\n    ],\n    \"MmsBase64\":\n    [\n        {\n            \"Base64\":\"dkjjkdflajdfjo3ji3jjljfkjaskjfad\",\n            \"BaseType\": \"audio/wav\"\n        },\n        {\n            \"Base64\":\"dkjjkdflajdfjo3ji3jjljfkjaskjfad\",\n            \"BaseType\": \"video/mpg\"\n        }\n    ]\n}\n]\n}"
								}
							]
						},
						{
							"name": "Delete Message Route",
							"request": {
								"method": "POST",
								"header": [],
								"body": {
									"mode": "raw",
									"raw": "{\n    \"MessageRouteId\": \"MRID-73af1e73-d7b3-4696-bdd9-5b407c96fc8a\"\n}",
									"options": {
										"raw": {
											"language": "json"
										}
									}
								},
								"url": {
									"raw": "https://api.telegent.com/v1.0/message/routes/delete",
									"protocol": "https",
									"host": [
										"api",
										"telegent",
										"com"
									],
									"path": [
										"v1.0",
										"message",
										"routes",
										"delete"
									]
								},
								"description": "# Delete Message Route\n\n## POST /message/routes/delete\n\nPermanently deletes a message routing configuration from your account.\n\n### Request\n\n#### Headers\n\n```\nContent-Type: application/json\nAuthorization: Bearer {your_api_token}\n\n ```\n\n#### Body Parameters\n\n| Parameter | Type | Required | Description |\n| --- | --- | --- | --- |\n| `MessageRouteId` | string | Yes | Unique identifier of the message route to delete |\n\n### Sample Request\n\n``` json\n{\n    \"MessageRouteId\": \"MRID-73af1e73-d7b3-4696-bdd9-5b407c96fc8a\"\n}\n\n ```\n\n### Responses\n\n#### 200 OK: Success\n\nReturns confirmation that the message route was deleted.\n\n``` json\n{\n    \"MessageRouteStatus\": \"Deleted\",\n    \"MRID\": \"MRID-73af1e73-d7b3-4696-bdd9-5b407c96fc8a\"\n}\n\n ```\n\n##### Response Fields\n\n| Field | Type | Description |\n| --- | --- | --- |\n| `MessageRouteStatus` | string | Status of the operation (should be \"Deleted\") |\n| `MRID` | string | Unique identifier of the deleted message route |\n\n#### 404 Not Found: Route Not Found\n\n``` json\n{\n    \"Type\": \"https://tools.ietf.org/html/rfc7231#section-6.5.4\",\n    \"Title\": \"Not Found\",\n    \"Status\": 404,\n    \"Detail\": \"Message route with ID 'MRID-73af1e73-d7b3-4696-bdd9-5b407c96fc8a' was not found.\",\n    \"TraceId\": \"00-1234abcd5678efgh-abcdef123456-00\"\n}\n\n ```\n\n#### 400 Bad Request: Route In Use\n\n``` json\n{\n    \"Type\": \"https://tools.ietf.org/html/rfc7231#section-6.5.1\",\n    \"Title\": \"Bad Request\",\n    \"Status\": 400,\n    \"Detail\": \"Cannot delete message route as it is currently assigned to one or more phone numbers.\",\n    \"TraceId\": \"00-1234abcd5678efgh-abcdef123456-00\"\n}\n\n ```\n\n#### 401 Unauthorized: Authentication Error\n\n``` json\n{\n    \"Type\": \"https://tools.ietf.org/html/rfc7235#section-3.1\",\n    \"Title\": \"Unauthorized\",\n    \"Status\": 401,\n    \"TraceId\": \"00-1234abcd5678efgh-abcdef123456-00\"\n}\n\n ```\n\n### Usage Notes\n\n- Deleting a message route is permanent and cannot be undone.\n    \n- Before deleting a message route, ensure it is not currently assigned to any phone numbers.\n    \n- To check which phone numbers are using a message route, use the `/numbers/inventory` endpoint and filter by the MessageRouteId.\n    \n- If you need to delete a message route that is in use, first update those phone numbers to use a different message route.\n    \n- Instead of deleting a route, consider updating it or disabling it by setting `MessageRouteEnabled` to `false` if you may need it again in the future.\n    \n- After deleting a route, any references to its MessageRouteId will no longer be valid.\n    \n- Deleting unused message routes helps keep your account organized and prevents confusion when provisioning new numbers.\n    \n\n### Try It\n\n```\ncurl -X POST \"https://api.telegent.com/v1.0/message/routes/delete\" \\\n  -H \"Content-Type: application/json\" \\\n  -H \"Authorization: Bearer YOUR_API_TOKEN\" \\\n  -d '{\n    \"MessageRouteId\": \"MRID-73af1e73-d7b3-4696-bdd9-5b407c96fc8a\"\n}'\n\n ```"
							},
							"response": [
								{
									"name": "Delete Message Route",
									"originalRequest": {
										"method": "POST",
										"header": [],
										"body": {
											"mode": "raw",
											"raw": "{\n    \"MRID\": \"MRID-73af1e73-d7b3-4696-bdd9-5b407c96fc8a\"\n}",
											"options": {
												"raw": {
													"language": "json"
												}
											}
										},
										"url": {
											"raw": "https://api.telegent.com/v1.0/message/routes/delete",
											"protocol": "https",
											"host": [
												"api",
												"telegent",
												"com"
											],
											"path": [
												"v1.0",
												"message",
												"routes",
												"delete"
											]
										}
									},
									"_postman_previewlanguage": "json",
									"header": [
										{
											"key": "Content-Type",
											"value": "application/json",
											"description": "",
											"type": "text"
										}
									],
									"cookie": [],
									"body": "{\n    \"MessageRouteStatus\": \"Deleted\",\n    \"MRID\": \"MRID-73af1e73-d7b3-4696-bdd9-5b407c96fc8a\"\n}"
								}
							]
						}
					],
					"description": "# Intelligent Messaging API Documentation\n\nThis section details the management of messaging services, including route configuration, sending messages, and retrieving message histories.\n\n## Key Workflow\n\n1. **Set up a messaging infrastructure**:  \n    \n    - Create a Message Route to get a `MessageRouteId`\n        \n    - Associate this route with your phone numbers\n        \n    - Send outbound messages and receive inbound messages\n        \n    - Track message history and delivery status\n        \n\n## Main Endpoints\n\n### Message Route Management\n\n- **Create Message Route**: `POST /message/routes`\n    \n    - Creates a webhook configuration for handling incoming messages and callbacks\n        \n    - Returns a `MessageRouteId` that can be used when provisioning or updating phone numbers\n        \n    - Configure authentication, webhooks, and callback URLs\n        \n- **Update Message Route**: `POST /message/routes/update`\n    \n    - Modifies an existing message route's configuration\n        \n    - Requires the `MessageRouteId` to identify which route to update\n        \n- **Get Message Route Details**: `GET /message/routes?MessageRouteId={MessageRouteId}`\n    \n    - Retrieves the detailed configuration of a specific message route\n        \n- **List Account Message Routes**: `GET /account/message/routes`\n    \n    - Returns all message routes configured for your account\n        \n    - Useful for selecting appropriate routes for phone numbers\n        \n- **Delete Message Route**: `POST /message/routes/delete`\n    \n    - Permanently removes a message route configuration\n        \n    - Cannot delete routes currently assigned to phone numbers\n        \n\n### Messaging Operations\n\n- **Send Outbound Message**: `POST /message/outbound`\n    \n    - Sends SMS or MMS messages to one or more recipients\n        \n    - Supports text messages, media URLs, and base64-encoded media\n        \n    - Returns a unique `MessageId` for tracking\n        \n- **Get Message Details**: `GET /message/details?MessageId={MessageId}`\n    \n    - Retrieves comprehensive information about a specific message\n        \n    - Includes delivery status, cost, and content details\n        \n- **Search Messages**: `GET /message/search?PhoneNumber={PhoneNumber}`\n    \n    - Searches for all messages associated with a specific phone number\n        \n    - Supports filtering by date, direction, and message type\n        \n\n## Configuration Best Practices\n\n1. **Message Route Setup**:\n    \n    - Create separate routes for different messaging use cases (e.g., notifications, support, marketing)\n        \n    - Set appropriate authentication on your webhooks to ensure security\n        \n    - Configure callback URLs to receive delivery status updates\n        \n2. **Sending Messages**:\n    \n    - Always use phone numbers in E.164 format (e.g., +12125551234)\n        \n    - For bulk messaging, consider using the `CampaignId` parameter for tracking\n        \n    - Keep MMS media sizes reasonable to ensure delivery\n        \n3. **Message Monitoring**:\n    \n    - Use the search and details endpoints to track message delivery\n        \n    - Monitor delivery status through your configured callback URLs\n        \n    - Regularly check message history for failed deliveries\n        \n\n## Integration Workflow\n\n1. First, create a Message Route using `POST /message/routes` to establish how incoming messages will be handled\n    \n2. Use the returned `MessageRouteId` when provisioning or updating phone numbers via the Intelligent Mobile Numbers API\n    \n3. Send outbound messages using `POST /message/outbound` from your enabled phone numbers\n    \n4. Track message delivery with `GET /message/details` or through your configured callback URL\n    \n5. Search message history with `GET /message/search` for reporting or troubleshooting\n    \n\nThis API provides a comprehensive platform for building messaging-enabled applications with detailed delivery tracking, multimedia support, and flexible routing configurations."
				},
				{
					"name": "Intelligent Voice Routing",
					"item": [
						{
							"name": "Create Voice Route",
							"event": [
								{
									"listen": "test",
									"script": {
										"exec": [
											"pm.test(\"Response has Call_Route_ID\", function () {",
											"    pm.response.to.have.property(\"json\");",
											"    let jsonData = pm.response.json();",
											"    pm.expect(jsonData).to.have.property(\"CallRouteId\");",
											"});",
											"",
											"pm.test(\"Extract and store Call_Route_ID as CRID\", function () {",
											"    let jsonData = pm.response.json();",
											"    let CallRouteId = jsonData.CallRouteId;",
											"    pm.collectionVariables.set(\"CallRouteId\", CallRouteId);",
											"    console.log(\"👉 Stored CRID:\", CallRouteId);",
											"});",
											""
										],
										"type": "text/javascript",
										"packages": {}
									}
								}
							],
							"request": {
								"method": "POST",
								"header": [],
								"body": {
									"mode": "raw",
									"raw": "{\n    \"RouteName\": \"Main SIP Trunk\",\n    \"RouteType\": \"Trunk\", //options include \"Trunk\", \"URL\", \"Forward\"\n    \"VoiceUrl\": \"https://domain.com\",\n    \"VoiceUrlMethod\": \"POST\",\n    \"VocieAuthenticationType\": \"Basic\",\n    \"VoiceUsername\": \"admin\",\n    \"VoicePasswordToken\": \"passwordORbearerToken\",\n    \"CallbackVoiceUrl\": \"https://apiendpoint.com\",\n    \"CallbackVoiceUrlMethod\": \"POST\",\n    \"TrunkIp1\": \"20.87.87.87\",\n    \"TrunkIp2\": \"20.87.87.86\",\n    \"TrunkPort1\": \"5061\",\n    \"TrunkPort2\": \"5060\",\n    \"TrunkTransport1\": \"UDP\",\n    \"TrunkTransport2\": \"TCP\",\n    \"TrunkUri1\": \"https://pstn.joonto.com\",\n    \"TrunkUri2\": \"https://pstn2.joonto.com\",\n    \"TrunkEnabled1\": true,\n    \"TrunkEnabled2\": false,\n    \"Trunk1Priortiy\": 10,\n    \"Trunk1Weight\": 10,\n    \"Trunk2Priortiy\": 20,\n    \"Trunk2Weight\": 20,\n    \"HeaderManipulation\":\"HMI8802029\",\n    \"EnableSipRefer\": true,\n    \"TransferCallerId\": \"Transferee/Transferor\",\n    \"SymmetricRtp\": true,\n    \"EnableTrpSecureTrunk\": true,\n    \"EnablePstnTransfer\": true,\n    \"IpWhitelist\": [{\"IpAddress\": \"20.20.10.10\"}, {\"IpAddress\": \"20.20.10.20\"}],\n    \"CnamLookup\": true,\n    \"TerminationUriSubdomain\": \"client\",\n    \"EnableCallStreaming\": true,\n    \"WssUri\": \"wss://192.67.88.2\",\n    \"RouteEnabled\": true\n}",
									"options": {
										"raw": {
											"language": "json"
										}
									}
								},
								"url": {
									"raw": "https://api.telegent.com/v1.0/voice/routes",
									"protocol": "https",
									"host": [
										"api",
										"telegent",
										"com"
									],
									"path": [
										"v1.0",
										"voice",
										"routes"
									]
								},
								"description": "# Voice Route Configuration\n\n## POST /voice/routes\n\nCreates a new voice routing configuration for handling calls to your phone numbers.\n\n### Request\n\n#### Headers\n\n```\nContent-Type: application/json\nAuthorization: Bearer {your_api_token}\n\n ```\n\n#### Body Parameters\n\n| Parameter | Type | Required | Description |\n| --- | --- | --- | --- |\n| `RouteName` | string | Yes | Descriptive name for this voice route |\n| `RouteType` | string | Yes | Type of routing. Valid values: `Trunk`, `URL`, `Forward` |\n| `VoiceUrl` | string | Conditional | Webhook URL that will receive voice events (required for `URL` route type) |\n| `VoiceUrlMethod` | string | Conditional | HTTP method for the webhook (required for `URL` route type) |\n| `VocieAuthenticationType` | string | No | Authentication type for the webhook (e.g., `Basic`, `Bearer`) |\n| `VoiceUsername` | string | Conditional | Username for webhook authentication |\n| `VoicePasswordToken` | string | Conditional | Password or token for webhook authentication |\n| `CallbackVoiceUrl` | string | No | URL for receiving call status callbacks |\n| `CallbackVoiceUrlMethod` | string | No | HTTP method for the callback URL |\n| `TrunkIp1` | string | Conditional | Primary SIP trunk IP address (required for `Trunk` route type) |\n| `TrunkIp2` | string | No | Backup SIP trunk IP address |\n| `TrunkPort1` | string | Conditional | Primary SIP trunk port (required for `Trunk` route type) |\n| `TrunkPort2` | string | No | Backup SIP trunk port |\n| `TrunkTransport1` | string | Conditional | Primary transport protocol (e.g., `UDP`, `TCP`) (required for `Trunk` route type) |\n| `TrunkTransport2` | string | No | Backup transport protocol |\n| `TrunkUri1` | string | Conditional | Primary SIP URI (required for `Trunk` route type) |\n| `TrunkUri2` | string | No | Backup SIP URI |\n| `TrunkEnabled1` | boolean | Conditional | Whether primary trunk is active (required for `Trunk` route type) |\n| `TrunkEnabled2` | boolean | No | Whether backup trunk is active |\n| `Trunk1Priortiy` | integer | No | Priority value for primary trunk (lower value = higher priority) |\n| `Trunk1Weight` | integer | No | Weight value for primary trunk (load balancing) |\n| `Trunk2Priortiy` | integer | No | Priority value for backup trunk |\n| `Trunk2Weight` | integer | No | Weight value for backup trunk |\n| `HeaderManipulation` | string | No | Header manipulation identifier |\n| `EnableSipRefer` | boolean | No | Whether SIP REFER is enabled |\n| `TransferCallerId` | string | No | Caller ID behavior during transfers (e.g., `Transferee/Transferor`) |\n| `SymmetricRtp` | boolean | No | Whether symmetric RTP is enabled |\n| `EnableTrpSecureTrunk` | boolean | No | Whether TRP secure trunk is enabled |\n| `EnablePstnTransfer` | boolean | No | Whether PSTN transfers are allowed |\n| `IpWhitelist` | array | No | List of whitelisted IP addresses |\n| `IpWhitelist[].IpAddress` | string | Yes (if in array) | IP address to whitelist |\n| `CnamLookup` | boolean | No | Whether CNAM lookup is enabled |\n| `TerminationUriSubdomain` | string | No | Subdomain for termination URIs |\n| `EnableCallStreaming` | boolean | No | Whether call streaming is enabled |\n| `WssUri` | string | No | WebSocket Secure URI for call streaming |\n| `RouteEnabled` | boolean | No | Whether this route is active |\n\n### Sample Request\n\n``` json\n{\n    \"RouteName\": \"Main SIP Trunk\",\n    \"RouteType\": \"Trunk\",\n    \"VoiceUrl\": \"https://domain.com\",\n    \"VoiceUrlMethod\": \"POST\",\n    \"VocieAuthenticationType\": \"Basic\",\n    \"VoiceUsername\": \"admin\",\n    \"VoicePasswordToken\": \"passwordORbearerToken\",\n    \"CallbackVoiceUrl\": \"https://apiendpoint.com\",\n    \"CallbackVoiceUrlMethod\": \"POST\",\n    \"TrunkIp1\": \"20.87.87.87\",\n    \"TrunkIp2\": \"20.87.87.86\",\n    \"TrunkPort1\": \"5061\",\n    \"TrunkPort2\": \"5060\",\n    \"TrunkTransport1\": \"UDP\",\n    \"TrunkTransport2\": \"TCP\",\n    \"TrunkUri1\": \"https://pstn.joonto.com\",\n    \"TrunkUri2\": \"https://pstn2.joonto.com\",\n    \"TrunkEnabled1\": true,\n    \"TrunkEnabled2\": false,\n    \"Trunk1Priortiy\": 10,\n    \"Trunk1Weight\": 10,\n    \"Trunk2Priortiy\": 20,\n    \"Trunk2Weight\": 20,\n    \"HeaderManipulation\": \"HMI8802029\",\n    \"EnableSipRefer\": true,\n    \"TransferCallerId\": \"Transferee/Transferor\",\n    \"SymmetricRtp\": true,\n    \"EnableTrpSecureTrunk\": true,\n    \"EnablePstnTransfer\": true,\n    \"IpWhitelist\": [{\"IpAddress\": \"20.20.10.10\"}, {\"IpAddress\": \"20.20.10.20\"}],\n    \"CnamLookup\": true,\n    \"TerminationUriSubdomain\": \"client\",\n    \"EnableCallStreaming\": true,\n    \"WssUri\": \"wss://192.67.88.2\",\n    \"RouteEnabled\": true\n}\n\n ```\n\n### Responses\n\n#### 200 OK: Success\n\nReturns the created voice route with its unique identifier.\n\n``` json\n{\n    \"CallRouteId\": \"CRID-509de94f-79cc-429b-a317-2102654dabbb\",\n    \"AccountId\": \"DID-1e8939ab-3f3c-4db1-89d7-956d80fd793j\",\n    \"RouteName\": \"Main SIP Trunk\",\n    \"RouteType\": \"Trunk\",\n    \"VoiceUrl\": \"https://domain.com\",\n    \"VoiceUrlMethod\": \"POST\",\n    \"TrunkIp1\": \"20.87.87.87\",\n    \"TrunkIp2\": \"20.87.87.86\",\n    \"TrunkPort1\": \"5061\",\n    \"TrunkPort2\": \"5060\",\n    \"TrunkTransport1\": \"UDP\",\n    \"TrunkTransport2\": \"TCP\",\n    \"TrunkUri1\": \"https://pstn.joonto.com\",\n    \"TrunkUri2\": \"https://pstn2.joonto.com\",\n    \"TrunkEnabled1\": true,\n    \"TrunkEnabled2\": false,\n    \"Trunk1Priortiy\": 10,\n    \"Trunk1Weight\": 10,\n    \"Trunk2Priortiy\": 20,\n    \"Trunk2Weight\": 20,\n    \"HeaderManipulation\": \"HMI8802029\",\n    \"EnableSipRefer\": true,\n    \"TransferCallerId\": \"Transferee/Transferor\",\n    \"SymmetricRtp\": true,\n    \"EnableTrpSecureTrunk\": true,\n    \"EnablePstnTransfer\": true,\n    \"CnamLookup\": true,\n    \"TerminationUriSubdomain\": \"client\",\n    \"EnableCallStreaming\": true,\n    \"WssUri\": \"wss://192.67.88.2\",\n    \"IpWhiteList\": []\n}\n\n ```\n\n##### Response Fields\n\n| Field | Type | Description |\n| --- | --- | --- |\n| `CallRouteId` | string | Unique identifier for the created voice route (format: CRID-xxx) |\n| `AccountId` | string | Your account identifier |\n| Other fields | various | Mirror the request parameters with any system-applied defaults |\n\n#### 400 Bad Request: Validation Error\n\n``` json\n{\n    \"Type\": \"https://tools.ietf.org/html/rfc7231#section-6.5.1\",\n    \"Title\": \"One or more validation errors occurred.\",\n    \"Status\": 400,\n    \"Errors\": {\n        \"$.RouteType\": [\"Route type must be one of: Trunk, URL, Forward\"]\n    },\n    \"TraceId\": \"00-1234abcd5678efgh-abcdef123456-00\"\n}\n\n ```\n\n#### 401 Unauthorized: Authentication Error\n\n``` json\n{\n    \"Type\": \"https://tools.ietf.org/html/rfc7235#section-3.1\",\n    \"Title\": \"Unauthorized\",\n    \"Status\": 401,\n    \"TraceId\": \"00-1234abcd5678efgh-abcdef123456-00\"\n}\n\n ```\n\n### Usage Notes\n\n- The created `CallRouteId` is required when provisioning or updating phone numbers to enable voice capabilities.\n    \n- Required parameters depend on the `RouteType` chosen:\n    \n    - `Trunk`: Requires trunk configuration parameters like IP addresses, ports, and transport protocols\n        \n    - `URL`: Requires webhook configuration parameters like URL and method\n        \n    - `Forward`: Requires destination number for call forwarding\n        \n- For SIP trunk configurations, you can provide primary and backup trunk settings for redundancy.\n    \n- The `IpWhitelist` can be used to restrict which IP addresses are allowed to connect to your voice services.\n    \n- When setting up Basic authentication, both `VoiceUsername` and `VoicePasswordToken` are required.\n    \n- For {{vault:bearer-token}}, only `VoicePasswordToken` is needed (containing the Bearer token).\n    \n- Priority and weight values are used for load balancing between primary and backup trunks.\n    \n- The `RouteEnabled` parameter allows you to create routes in a disabled state before testing and enabling them.\n    \n- Callback URLs are used to receive status updates about calls, such as call completion or failure.\n    \n\n### Try It\n\n```\ncurl -X POST \"https://api.telegent.com/v1.0/voice/routes\" \\\n  -H \"Content-Type: application/json\" \\\n  -H \"Authorization: Bearer YOUR_API_TOKEN\" \\\n  -d '{\n    \"RouteName\": \"Main SIP Trunk\",\n    \"RouteType\": \"Trunk\",\n    \"TrunkIp1\": \"20.87.87.87\",\n    \"TrunkPort1\": \"5061\",\n    \"TrunkTransport1\": \"UDP\",\n    \"TrunkUri1\": \"https://pstn.joonto.com\",\n    \"TrunkEnabled1\": true,\n    \"RouteEnabled\": true\n}'\n\n ```"
							},
							"response": [
								{
									"name": "Create Voice Route",
									"originalRequest": {
										"method": "POST",
										"header": [],
										"body": {
											"mode": "raw",
											"raw": "{\n    \"RouteName\": \"Main SIP Trunk\",\n    \"RouteType\": \"Trunk\", //options include \"Trunk\", \"URL\", \"Forward\"\n    \"VoiceUrl\": \"https://domain.com\",\n    \"VoiceUrlMethod\": \"POST\",\n    \"VocieAuthenticationType\": \"Basic\",\n    \"VoiceUsername\": \"admin\",\n    \"VoicePasswordToken\": \"passwordORbearerToken\",\n    \"CallbackVoiceUrl\": \"https://apiendpoint.com\",\n    \"CallbackVoiceUrlMethod\": \"POST\",\n    \"TrunkIp1\": \"20.87.87.87\",\n    \"TrunkIp2\": \"20.87.87.86\",\n    \"TrunkPort1\": \"5061\",\n    \"TrunkPort2\": \"5060\",\n    \"TrunkTransport1\": \"UDP\",\n    \"TrunkTransport2\": \"TCP\",\n    \"TrunkUri1\": \"https://pstn.joonto.com\",\n    \"TrunkUri2\": \"https://pstn2.joonto.com\",\n    \"TrunkEnabled1\": true,\n    \"TrunkEnabled2\": false,\n    \"Trunk1Priortiy\": 10,\n    \"Trunk1Weight\": 10,\n    \"Trunk2Priortiy\": 20,\n    \"Trunk2Weight\": 20,\n    \"HeaderManipulation\":\"HMI8802029\",\n    \"EnableSipRefer\": true,\n    \"TransferCallerId\": \"Transferee/Transferor\",\n    \"SymmetricRtp\": true,\n    \"EnableTrpSecureTrunk\": true,\n    \"EnablePstnTransfer\": true,\n    \"IpWhitelist\": [{\"IpAddress\": \"20.20.10.10\"}, {\"IpAddress\": \"20.20.10.20\"}],\n    \"CnamLookup\": true,\n    \"TerminationUriSubdomain\": \"client\",\n    \"EnableCallStreaming\": true,\n    \"WssUri\": \"wss://192.67.88.2\",\n    \"RouteEnabled\": true\n}",
											"options": {
												"raw": {
													"language": "json"
												}
											}
										},
										"url": {
											"raw": "https://api.telegent.com/v1.0/voice/routes",
											"protocol": "https",
											"host": [
												"api",
												"telegent",
												"com"
											],
											"path": [
												"v1.0",
												"voice",
												"routes"
											]
										}
									},
									"_postman_previewlanguage": "json",
									"header": [
										{
											"key": "Content-Type",
											"value": "application/json",
											"description": "",
											"type": "text"
										}
									],
									"cookie": [],
									"body": "{\n    \"CallRouteId\": \"CRID-509de94f-79cc-429b-a317-2102654dabbb\",\n    \"AccountId\": \"DID-1e8939ab-3f3c-4db1-89d7-956d80fd793j\",\n    \"RouteName\": \"Main SIP Trunk\",\n    \"RouteType\": \"Trunk\",\n    \"VoiceUrl\": \"https://domain.com\",\n    \"VoiceUrlMethod\": \"POST\",\n    \"TrunkIp1\": \"20.87.87.87\",\n    \"TrunkIp2\": \"20.87.87.86\",\n    \"TrunkPort1\": \"5061\",\n    \"TrunkPort2\": \"5060\",\n    \"TrunkTransport1\": \"UDP\",\n    \"TrunkTransport2\": \"TCP\",\n    \"TrunkUri1\": \"https://pstn.joonto.com\",\n    \"TrunkUri2\": \"https://pstn2.joonto.com\",\n    \"TrunkEnabled1\": true,\n    \"TrunkEnabled2\": false,\n    \"Trunk1Priortiy\": 10,\n    \"Trunk1Weight\": 10,\n    \"Trunk2Priortiy\": 20,\n    \"Trunk2Weight\": 20,\n    \"HeaderManipulation\": \"HMI8802029\",\n    \"EnableSipRefer\": true,\n    \"TransferCallerId\": \"Transferee/Transferor\",\n    \"SymmetricRtp\": true,\n    \"EnableTrpSecureTrunk\": true,\n    \"EnablePstnTransfer\": true,\n    \"CnamLookup\": true,\n    \"TerminationUriSubdomain\": \"client\",\n    \"EnableCallStreaming\": true,\n    \"WssUri\": \"wss://192.67.88.2\",\n    \"IpWhiteList\": []\n}"
								}
							]
						},
						{
							"name": "Update Voice Route",
							"request": {
								"method": "POST",
								"header": [],
								"body": {
									"mode": "raw",
									"raw": "{\n    \"CallRouteId\": \"{{CallRouteId}}\", //Required\n    \"RouteName\": \"Main SIP Trunk\",\n    \"RouteType\": \"Trunk\", //options include \"Trunk\", \"URL\", \"Forward\"\n    \"VoiceUrl\": \"https://domain.com\",\n    \"VoiceUrlMethod\": \"GET\",\n    \"VocieAuthenticationType\": \"Basic\",\n    \"VoiceUsername\": \"admin\",\n    \"VoicePasswordToken\": \"passwordORbearerToken\",\n    \"CallbackVoiceUrl\": \"https://apiendpoint.com\",\n    \"CallbackVoiceUrlMethod\": \"POST\",\n    \"TrunkIp1\": \"20.87.87.87\",\n    \"TrunkIp2\": \"20.87.87.86\",\n    \"TrunkPort1\": \"5061\",\n    \"TrunkPort2\": \"5060\",\n    \"TrunkTransport1\": \"UDP\",\n    \"TrunkTransport2\": \"TCP\",\n    \"TrunkUri1\": \"https://pstn.joonto.com\",\n    \"TrunkUri2\": \"https://pstn2.joonto.com\",\n    \"TrunkEnabled1\": true,\n    \"TrunkEnabled2\": false,\n    \"Trunk1Priortiy\": 10,\n    \"Trunk1Weight\": 10,\n    \"Trunk2Priortiy\": 20,\n    \"Trunk2Weight\": 20,\n    \"HeaderManipulation\":\"HMI8802029\",\n    \"EnableSipRefer\": true,\n    \"TransferCallerId\": \"Transferee/Transferor\",\n    \"SymmetricRtp\": true,\n    \"EnableTrpSecureTrunk\": true,\n    \"EnablePstnTransfer\": true,\n    \"IpWhitelist\": [{\"IpAddress\": \"20.20.10.10\"}, {\"IpAddress\": \"20.20.10.20\"}],\n    \"CnamLookup\": true,\n    \"TerminationUriSubdomain\": \"client\",\n    \"EnableCallStreaming\": true,\n    \"WssUri\": \"wss://192.67.88.2\",\n    \"RouteEnabled\": true\n}",
									"options": {
										"raw": {
											"language": "json"
										}
									}
								},
								"url": {
									"raw": "https://api.telegent.com/v1.0/voice/routes/update",
									"protocol": "https",
									"host": [
										"api",
										"telegent",
										"com"
									],
									"path": [
										"v1.0",
										"voice",
										"routes",
										"update"
									]
								},
								"description": "# Update Voice Route\n\n## POST /voice/routes/update\n\nUpdates an existing voice routing configuration with new settings.\n\n### Request\n\n#### Headers\n\n```\nContent-Type: application/json\nAuthorization: Bearer {your_api_token}\n\n ```\n\n#### Body Parameters\n\n| Parameter | Type | Required | Description |\n| --- | --- | --- | --- |\n| `CallRouteId` | string | Yes | Unique identifier of the voice route to update |\n| `RouteName` | string | No | New name for the voice route |\n| `RouteType` | string | No | Type of routing. Valid values: `Trunk`, `URL`, `Forward` |\n| `VoiceUrl` | string | No | Webhook URL that will receive voice events |\n| `VoiceUrlMethod` | string | No | HTTP method for the webhook |\n| `VocieAuthenticationType` | string | No | Authentication type for the webhook |\n| `VoiceUsername` | string | No | Username for webhook authentication |\n| `VoicePasswordToken` | string | No | Password or token for webhook authentication |\n| `CallbackVoiceUrl` | string | No | URL for receiving call status callbacks |\n| `CallbackVoiceUrlMethod` | string | No | HTTP method for the callback URL |\n| `TrunkIp1` | string | No | Primary SIP trunk IP address |\n| `TrunkIp2` | string | No | Backup SIP trunk IP address |\n| `TrunkPort1` | string | No | Primary SIP trunk port |\n| `TrunkPort2` | string | No | Backup SIP trunk port |\n| `TrunkTransport1` | string | No | Primary transport protocol (e.g., `UDP`, `TCP`) |\n| `TrunkTransport2` | string | No | Backup transport protocol |\n| `TrunkUri1` | string | No | Primary SIP URI |\n| `TrunkUri2` | string | No | Backup SIP URI |\n| `TrunkEnabled1` | boolean | No | Whether primary trunk is active |\n| `TrunkEnabled2` | boolean | No | Whether backup trunk is active |\n| `Trunk1Priortiy` | integer | No | Priority value for primary trunk |\n| `Trunk1Weight` | integer | No | Weight value for primary trunk |\n| `Trunk2Priortiy` | integer | No | Priority value for backup trunk |\n| `Trunk2Weight` | integer | No | Weight value for backup trunk |\n| `HeaderManipulation` | string | No | Header manipulation identifier |\n| `EnableSipRefer` | boolean | No | Whether SIP REFER is enabled |\n| `TransferCallerId` | string | No | Caller ID behavior during transfers |\n| `SymmetricRtp` | boolean | No | Whether symmetric RTP is enabled |\n| `EnableTrpSecureTrunk` | boolean | No | Whether TRP secure trunk is enabled |\n| `EnablePstnTransfer` | boolean | No | Whether PSTN transfers are allowed |\n| `IpWhitelist` | array | No | List of whitelisted IP addresses |\n| `IpWhitelist[].IpAddress` | string | Yes (if in array) | IP address to whitelist |\n| `CnamLookup` | boolean | No | Whether CNAM lookup is enabled |\n| `TerminationUriSubdomain` | string | No | Subdomain for termination URIs |\n| `EnableCallStreaming` | boolean | No | Whether call streaming is enabled |\n| `WssUri` | string | No | WebSocket Secure URI for call streaming |\n| `RouteEnabled` | boolean | No | Whether this route is active |\n\n### Sample Request\n\n``` json\n{\n    \"CallRouteId\": \"CRID-993804Ar09099\",\n    \"RouteName\": \"Main SIP Trunk\",\n    \"RouteType\": \"Trunk\",\n    \"VoiceUrl\": \"https://domain.com\",\n    \"VoiceUrlMethod\": \"GET\",\n    \"VocieAuthenticationType\": \"Basic\",\n    \"VoiceUsername\": \"admin\",\n    \"VoicePasswordToken\": \"passwordORbearerToken\",\n    \"CallbackVoiceUrl\": \"https://apiendpoint.com\",\n    \"CallbackVoiceUrlMethod\": \"POST\",\n    \"TrunkIp1\": \"20.87.87.87\",\n    \"TrunkIp2\": \"20.87.87.86\",\n    \"TrunkPort1\": \"5061\",\n    \"TrunkPort2\": \"5060\",\n    \"TrunkTransport1\": \"UDP\",\n    \"TrunkTransport2\": \"TCP\",\n    \"TrunkUri1\": \"https://pstn.joonto.com\",\n    \"TrunkUri2\": \"https://pstn2.joonto.com\",\n    \"TrunkEnabled1\": true,\n    \"TrunkEnabled2\": false,\n    \"Trunk1Priortiy\": 10,\n    \"Trunk1Weight\": 10,\n    \"Trunk2Priortiy\": 20,\n    \"Trunk2Weight\": 20,\n    \"HeaderManipulation\": \"HMI8802029\",\n    \"EnableSipRefer\": true,\n    \"TransferCallerId\": \"Transferee/Transferor\",\n    \"SymmetricRtp\": true,\n    \"EnableTrpSecureTrunk\": true,\n    \"EnablePstnTransfer\": true,\n    \"IpWhitelist\": [{\"IpAddress\": \"20.20.10.10\"}, {\"IpAddress\": \"20.20.10.20\"}],\n    \"CnamLookup\": true,\n    \"TerminationUriSubdomain\": \"client\",\n    \"EnableCallStreaming\": true,\n    \"WssUri\": \"wss://192.67.88.2\",\n    \"RouteEnabled\": true\n}\n\n ```\n\n### Responses\n\n#### 200 OK: Success\n\nReturns the updated voice route configuration.\n\n``` json\n{\n    \"CallRouteId\": \"CRID-509de94f-79cc-429b-a317-2102654dabbb\",\n    \"AccountId\": \"DID-1e8939ab-3f3c-4db1-89d7-956d80fd793j\",\n    \"RouteName\": \"Main SIP Trunk\",\n    \"RouteType\": \"Trunk\",\n    \"VoiceUrl\": \"https://domain.com\",\n    \"VoiceUrlMethod\": \"GET\",\n    \"TrunkIp1\": \"20.87.87.87\",\n    \"TrunkIp2\": \"20.87.87.86\",\n    \"TrunkPort1\": \"5061\",\n    \"TrunkPort2\": \"5060\",\n    \"TrunkTransport1\": \"UDP\",\n    \"TrunkTransport2\": \"TCP\",\n    \"TrunkUri1\": \"https://pstn.joonto.com\",\n    \"TrunkUri2\": \"https://pstn2.joonto.com\",\n    \"TrunkEnabled1\": true,\n    \"TrunkEnabled2\": false,\n    \"Trunk1Priortiy\": 10,\n    \"Trunk1Weight\": 10,\n    \"Trunk2Priortiy\": 20,\n    \"Trunk2Weight\": 20,\n    \"HeaderManipulation\": \"HMI8802029\",\n    \"EnableSipRefer\": true,\n    \"TransferCallerId\": \"Transferee/Transferor\",\n    \"SymmetricRtp\": true,\n    \"EnableTrpSecureTrunk\": true,\n    \"EnablePstnTransfer\": true,\n    \"CnamLookup\": true,\n    \"TerminationUriSubdomain\": \"client\",\n    \"EnableCallStreaming\": true,\n    \"WssUri\": \"wss://192.67.88.2\",\n    \"IpWhiteList\": []\n}\n\n ```\n\n##### Response Fields\n\n| Field | Type | Description |\n| --- | --- | --- |\n| `CallRouteId` | string | Unique identifier of the voice route |\n| `AccountId` | string | Your account identifier |\n| Other fields | various | Reflect the updated configuration with any system-applied defaults |\n\n#### 404 Not Found: Route Not Found\n\n``` json\n{\n    \"Type\": \"https://tools.ietf.org/html/rfc7231#section-6.5.4\",\n    \"Title\": \"Not Found\",\n    \"Status\": 404,\n    \"Detail\": \"Voice route with ID 'CRID-993804Ar09099' was not found.\",\n    \"TraceId\": \"00-1234abcd5678efgh-abcdef123456-00\"\n}\n\n ```\n\n#### 400 Bad Request: Validation Error\n\n``` json\n{\n    \"Type\": \"https://tools.ietf.org/html/rfc7231#section-6.5.1\",\n    \"Title\": \"One or more validation errors occurred.\",\n    \"Status\": 400,\n    \"Errors\": {\n        \"$.RouteType\": [\"Route type must be one of: Trunk, URL, Forward\"]\n    },\n    \"TraceId\": \"00-1234abcd5678efgh-abcdef123456-00\"\n}\n\n ```\n\n#### 401 Unauthorized: Authentication Error\n\n``` json\n{\n    \"Type\": \"https://tools.ietf.org/html/rfc7235#section-3.1\",\n    \"Title\": \"Unauthorized\",\n    \"Status\": 401,\n    \"TraceId\": \"00-1234abcd5678efgh-abcdef123456-00\"\n}\n\n ```\n\n### Usage Notes\n\n- Only include the parameters you want to update in the request body.\n    \n- The `CallRouteId` is required to identify which route to update.\n    \n- To change the route type (e.g., from `Trunk` to `URL`), ensure you provide all required parameters for the new route type.\n    \n- Any phone numbers currently using this route will automatically use the updated configuration.\n    \n- You can temporarily disable a route by setting `RouteEnabled` to `false`.\n    \n- After updating, it may take a few moments for the changes to propagate through the system.\n    \n- When updating SIP trunk settings, consider whether active calls might be affected.\n    \n- If you're changing authentication settings, ensure your systems are updated to use the new credentials.\n    \n- For security-critical changes (like IP whitelists), verify the configuration is correct before enabling the route.\n    \n- When changing webhook URLs, make sure the new endpoints are properly set up to handle incoming requests.\n    \n\n### Try It\n\n```\ncurl -X POST \"https://api.telegent.com/v1.0/voice/routes/update\" \\\n  -H \"Content-Type: application/json\" \\\n  -H \"Authorization: Bearer YOUR_API_TOKEN\" \\\n  -d '{\n    \"CallRouteId\": \"CRID-993804Ar09099\",\n    \"VoiceUrlMethod\": \"GET\",\n    \"RouteEnabled\": true\n}'\n\n ```"
							},
							"response": [
								{
									"name": "Update Voice Route",
									"originalRequest": {
										"method": "POST",
										"header": [],
										"body": {
											"mode": "raw",
											"raw": "{\n    \"CallRouteId\": \"CRID-993804Ar09099\", //Required\n    \"RouteName\": \"Main SIP Trunk\",\n    \"RouteType\": \"Trunk\", //options include \"Trunk\", \"URL\", \"Forward\"\n    \"VoiceUrl\": \"https://domain.com\",\n    \"VoiceUrlMethod\": \"POST\",\n    \"VocieAuthenticationType\": \"Basic\",\n    \"VoiceUsername\": \"admin\",\n    \"VoicePasswordToken\": \"passwordORbearerToken\",\n    \"CallbackVoiceUrl\": \"https://apiendpoint.com\",\n    \"CallbackVoiceUrlMethod\": \"POST\",\n    \"TrunkIp1\": \"20.87.87.87\",\n    \"TrunkIp2\": \"20.87.87.86\",\n    \"TrunkPort1\": \"5061\",\n    \"TrunkPort2\": \"5060\",\n    \"TrunkTransport1\": \"UDP\",\n    \"TrunkTransport2\": \"TCP\",\n    \"TrunkUri1\": \"https://pstn.joonto.com\",\n    \"TrunkUri2\": \"https://pstn2.joonto.com\",\n    \"TrunkEnabled1\": true,\n    \"TrunkEnabled2\": false,\n    \"Trunk1Priortiy\": 10,\n    \"Trunk1Weight\": 10,\n    \"Trunk2Priortiy\": 20,\n    \"Trunk2Weight\": 20,\n    \"HeaderManipulation\":\"HMI8802029\",\n    \"EnableSipRefer\": true,\n    \"TransferCallerId\": \"Transferee/Transferor\",\n    \"SymmetricRtp\": true,\n    \"EnableTrpSecureTrunk\": true,\n    \"EnablePstnTransfer\": true,\n    \"IpWhitelist\": [{\"IpAddress\": \"20.20.10.10\"}, {\"IpAddress\": \"20.20.10.20\"}],\n    \"CnamLookup\": true,\n    \"TerminationUriSubdomain\": \"client\",\n    \"EnableCallStreaming\": true,\n    \"WssUri\": \"wss://192.67.88.2\",\n    \"RouteEnabled\": true\n}",
											"options": {
												"raw": {
													"language": "json"
												}
											}
										},
										"url": {
											"raw": "https://api.telegent.com/v1.0/voice/routes/update",
											"protocol": "https",
											"host": [
												"api",
												"telegent",
												"com"
											],
											"path": [
												"v1.0",
												"voice",
												"routes",
												"update"
											]
										}
									},
									"_postman_previewlanguage": "json",
									"header": [
										{
											"key": "Content-Type",
											"value": "application/json",
											"description": "",
											"type": "text"
										}
									],
									"cookie": [],
									"body": "{\n    \"CallRouteId\": \"CRID-509de94f-79cc-429b-a317-2102654dabbb\",\n    \"AccountId\": \"DID-1e8939ab-3f3c-4db1-89d7-956d80fd793j\",\n    \"RouteName\": \"Main SIP Trunk\",\n    \"RouteType\": \"Trunk\",\n    \"VoiceUrl\": \"https://domain.com\",\n    \"VoiceUrlMethod\": \"GET\",\n    \"TrunkIp1\": \"20.87.87.87\",\n    \"TrunkIp2\": \"20.87.87.86\",\n    \"TrunkPort1\": \"5061\",\n    \"TrunkPort2\": \"5060\",\n    \"TrunkTransport1\": \"UDP\",\n    \"TrunkTransport2\": \"TCP\",\n    \"TrunkUri1\": \"https://pstn.joonto.com\",\n    \"TrunkUri2\": \"https://pstn2.joonto.com\",\n    \"TrunkEnabled1\": true,\n    \"TrunkEnabled2\": false,\n    \"Trunk1Priortiy\": 10,\n    \"Trunk1Weight\": 10,\n    \"Trunk2Priortiy\": 20,\n    \"Trunk2Weight\": 20,\n    \"HeaderManipulation\": \"HMI8802029\",\n    \"EnableSipRefer\": true,\n    \"TransferCallerId\": \"Transferee/Transferor\",\n    \"SymmetricRtp\": true,\n    \"EnableTrpSecureTrunk\": true,\n    \"EnablePstnTransfer\": true,\n    \"CnamLookup\": true,\n    \"TerminationUriSubdomain\": \"client\",\n    \"EnableCallStreaming\": true,\n    \"WssUri\": \"wss://192.67.88.2\",\n    \"IpWhiteList\": []\n}"
								}
							]
						},
						{
							"name": "Voice Route Details",
							"request": {
								"method": "GET",
								"header": [],
								"url": {
									"raw": "https://api.telegent.com/v1.0/voice/routes?CallRouteID=CRID-509de94f-79cc-429b-a317-2102654dabbb",
									"protocol": "https",
									"host": [
										"api",
										"telegent",
										"com"
									],
									"path": [
										"v1.0",
										"voice",
										"routes"
									],
									"query": [
										{
											"key": "CallRouteID",
											"value": "CRID-509de94f-79cc-429b-a317-2102654dabbb"
										}
									]
								},
								"description": "# Get Voice Route Details\n\n## GET /voice/routes\n\nRetrieves the detailed configuration of a specific voice route.\n\n### Request\n\n#### Headers\n\n```\nAuthorization: Bearer {your_api_token}\n```\n\n#### Query Parameters\n\n| Parameter | Type | Required | Description |\n|-----------|------|----------|-------------|\n| `CallRouteId` | string | Yes | Unique identifier of the voice route to retrieve |\n\n### Sample Request\n\n```\nGET https://api.telegent.com/v1.0/voice/routes?CallRouteId=CRID-509de94f-79cc-429b-a317-2102654dabbb\n```\n\n### Responses\n\n#### 200 OK: Success\n\nReturns the detailed configuration of the specified voice route.\n\n```json\n{\n    \"CallRouteId\": \"CRID-509de94f-79cc-429b-a317-2102654dabbb\",\n    \"AccountId\": \"DID-1e8939ab-3f3c-4db1-89d7-956d80fd793j\",\n    \"RouteName\": \"Main SIP Trunk\",\n    \"RouteType\": \"Trunk\",\n    \"VoiceUrl\": \"https://domain.com\",\n    \"VoiceUrlMethod\": \"GET\",\n    \"TrunkIp1\": \"20.87.87.87\",\n    \"TrunkIp2\": \"20.87.87.86\",\n    \"TrunkPort1\": \"5061\",\n    \"TrunkPort2\": \"5060\",\n    \"TrunkTransport1\": \"UDP\",\n    \"TrunkTransport2\": \"TCP\",\n    \"TrunkUri1\": \"https://pstn.joonto.com\",\n    \"TrunkUri2\": \"https://pstn2.joonto.com\",\n    \"TrunkEnabled1\": true,\n    \"TrunkEnabled2\": false,\n    \"Trunk1Priortiy\": 10,\n    \"Trunk1Weight\": 10,\n    \"Trunk2Priortiy\": 20,\n    \"Trunk2Weight\": 20,\n    \"HeaderManipulation\": \"HMI8802029\",\n    \"EnableSipRefer\": true,\n    \"TransferCallerId\": \"Transferee/Transferor\",\n    \"SymmetricRtp\": true,\n    \"EnableTrpSecureTrunk\": true,\n    \"EnablePstnTransfer\": true,\n    \"CnamLookup\": true,\n    \"TerminationUriSubdomain\": \"client\",\n    \"EnableCallStreaming\": true,\n    \"WssUri\": \"wss://192.67.88.2\",\n    \"IpWhiteList\": []\n}\n```\n\n##### Response Fields\n\n| Field | Type | Description |\n|-------|------|-------------|\n| `CallRouteId` | string | Unique identifier of the voice route |\n| `AccountId` | string | Your account identifier |\n| `RouteName` | string | Name of the voice route |\n| `RouteType` | string | Type of routing (Trunk, URL, Forward) |\n| `VoiceUrl` | string | Webhook URL that receives voice events |\n| `VoiceUrlMethod` | string | HTTP method for the webhook URL |\n| `TrunkIp1` | string | Primary SIP trunk IP address |\n| `TrunkIp2` | string | Backup SIP trunk IP address |\n| `TrunkPort1` | string | Primary SIP trunk port |\n| `TrunkPort2` | string | Backup SIP trunk port |\n| `TrunkTransport1` | string | Primary transport protocol |\n| `TrunkTransport2` | string | Backup transport protocol |\n| `TrunkUri1` | string | Primary SIP URI |\n| `TrunkUri2` | string | Backup SIP URI |\n| `TrunkEnabled1` | boolean | Whether primary trunk is active |\n| `TrunkEnabled2` | boolean | Whether backup trunk is active |\n| `Trunk1Priortiy` | integer | Priority value for primary trunk |\n| `Trunk1Weight` | integer | Weight value for primary trunk |\n| `Trunk2Priortiy` | integer | Priority value for backup trunk |\n| `Trunk2Weight` | integer | Weight value for backup trunk |\n| `HeaderManipulation` | string | Header manipulation identifier |\n| `EnableSipRefer` | boolean | Whether SIP REFER is enabled |\n| `TransferCallerId` | string | Caller ID behavior during transfers |\n| `SymmetricRtp` | boolean | Whether symmetric RTP is enabled |\n| `EnableTrpSecureTrunk` | boolean | Whether TRP secure trunk is enabled |\n| `EnablePstnTransfer` | boolean | Whether PSTN transfers are allowed |\n| `CnamLookup` | boolean | Whether CNAM lookup is enabled |\n| `TerminationUriSubdomain` | string | Subdomain for termination URIs |\n| `EnableCallStreaming` | boolean | Whether call streaming is enabled |\n| `WssUri` | string | WebSocket Secure URI for call streaming |\n| `IpWhiteList` | array | List of whitelisted IP addresses |\n\n#### 404 Not Found: Route Not Found\n\n```json\n{\n    \"Type\": \"https://tools.ietf.org/html/rfc7231#section-6.5.4\",\n    \"Title\": \"Not Found\",\n    \"Status\": 404,\n    \"Detail\": \"Voice route with ID 'CRID-509de94f-79cc-429b-a317-2102654dabbb' was not found.\",\n    \"TraceId\": \"00-1234abcd5678efgh-abcdef123456-00\"\n}\n```\n\n#### 401 Unauthorized: Authentication Error\n\n```json\n{\n    \"Type\": \"https://tools.ietf.org/html/rfc7235#section-3.1\",\n    \"Title\": \"Unauthorized\",\n    \"Status\": 401,\n    \"TraceId\": \"00-1234abcd5678efgh-abcdef123456-00\"\n}\n```\n\n### Usage Notes\n\n- Use this endpoint to verify the current configuration of a voice route.\n- The `CallRouteId` parameter is case-sensitive and must match exactly.\n- For security reasons, authentication credentials may be partially masked in the response.\n- You can retrieve a list of all your voice routes using the `/account/voice/routes` endpoint.\n- This endpoint is useful for confirming that a previous update operation completed successfully.\n- The response will include all parameters relevant to the route type, but some fields may be null or absent if not applicable.\n- Use this information to troubleshoot voice routing issues or to plan configuration changes.\n- The `IpWhiteList` shows which IP addresses are allowed to connect to your voice services.\n- Check the `TrunkEnabled1` and `TrunkEnabled2` fields to confirm whether your trunks are active.\n\n### Try It\n\n```\ncurl -X GET \"https://api.telegent.com/v1.0/voice/routes?CallRouteId=CRID-509de94f-79cc-429b-a317-2102654dabbb\" \\\n  -H \"Authorization: Bearer YOUR_API_TOKEN\"\n```"
							},
							"response": [
								{
									"name": "Voice Route Details",
									"originalRequest": {
										"method": "GET",
										"header": [
											{
												"key": "Pop-Token",
												"value": "{{Pop-Token}}",
												"type": "text"
											}
										],
										"url": {
											"raw": "https://api.telegent.com/v1.0/voice/routes?CallRouteID={{CallRouteId}}",
											"protocol": "https",
											"host": [
												"api",
												"telegent",
												"com"
											],
											"path": [
												"v1.0",
												"voice",
												"routes"
											],
											"query": [
												{
													"key": "CallRouteID",
													"value": "{{CallRouteId}}"
												}
											]
										}
									},
									"_postman_previewlanguage": "json",
									"header": [
										{
											"key": "Content-Type",
											"value": "application/json",
											"description": "",
											"type": "text"
										}
									],
									"cookie": [],
									"body": "{\n    \"CallRouteId\": \"CRID-509de94f-79cc-429b-a317-2102654dabbb\",\n    \"AccountId\": \"DID-1e8939ab-3f3c-4db1-89d7-956d80fd793j\",\n    \"RouteName\": \"Main SIP Trunk\",\n    \"RouteType\": \"Trunk\",\n    \"VoiceUrl\": \"https://domain.com\",\n    \"VoiceUrlMethod\": \"GET\",\n    \"TrunkIp1\": \"20.87.87.87\",\n    \"TrunkIp2\": \"20.87.87.86\",\n    \"TrunkPort1\": \"5061\",\n    \"TrunkPort2\": \"5060\",\n    \"TrunkTransport1\": \"UDP\",\n    \"TrunkTransport2\": \"TCP\",\n    \"TrunkUri1\": \"https://pstn.joonto.com\",\n    \"TrunkUri2\": \"https://pstn2.joonto.com\",\n    \"TrunkEnabled1\": true,\n    \"TrunkEnabled2\": false,\n    \"Trunk1Priortiy\": 10,\n    \"Trunk1Weight\": 10,\n    \"Trunk2Priortiy\": 20,\n    \"Trunk2Weight\": 20,\n    \"HeaderManipulation\": \"HMI8802029\",\n    \"EnableSipRefer\": true,\n    \"TransferCallerId\": \"Transferee/Transferor\",\n    \"SymmetricRtp\": true,\n    \"EnableTrpSecureTrunk\": true,\n    \"EnablePstnTransfer\": true,\n    \"CnamLookup\": true,\n    \"TerminationUriSubdomain\": \"client\",\n    \"EnableCallStreaming\": true,\n    \"WssUri\": \"wss://192.67.88.2\",\n    \"IpWhiteList\": []\n}"
								}
							]
						},
						{
							"name": "Voice Account Routes List",
							"request": {
								"method": "GET",
								"header": [],
								"url": {
									"raw": "https://api.telegent.com/v1.0/account/voice/routes",
									"protocol": "https",
									"host": [
										"api",
										"telegent",
										"com"
									],
									"path": [
										"v1.0",
										"account",
										"voice",
										"routes"
									]
								},
								"description": "# List Account Voice Routes\n\n## GET /account/voice/routes\n\nRetrieves a list of all voice routes configured for your account.\n\n### Request\n\n#### Headers\n\n```\nAuthorization: Bearer {your_api_token}\n```\n\n### Sample Request\n\n```\nGET https://api.telegent.com/v1.0/account/voice/routes\n```\n\n### Responses\n\n#### 200 OK: Success\n\nReturns a list of all voice routes configured in your account.\n\n```json\n{\n    \"AccountId\": \"DID-1e8939ab-3f3c-4db1-89d7-956d80fd793j203805880870238\",\n    \"TotalRoutes\": 2,\n    \"Results\": [\n        {\n            \"CallRouteStatus\": \"Active\",\n            \"CallRouteId\": \"CRID-993804Ar09099\",\n            \"AccountId\": \"DID-1e8939ab-3f3c-4db1-89d7-956d80fd793j203805880870238\",\n            \"RouteName\": \"Main SIP Trunk\",\n            \"RouteType\": \"Trunk\",\n            \"VoiceUrlMethod\": \"POST\",\n            \"TrunkIp1\": \"20.87.87.87\",\n            \"TrunkIp2\": \"20.87.87.86\",\n            \"TrunkPort1\": \"5061\",\n            \"TrunkPort2\": \"5060\",\n            \"TrunkTransport1\": \"UDP\",\n            \"TrunkTransport2\": \"TCP\",\n            \"TrunkUri1\": \"https://pstn.joonto.com\",\n            \"TrunkUri2\": \"https://pstn2.joonto.com\",\n            \"TrunkEnabled1\": true,\n            \"TrunkEnabled2\": false,\n            \"Trunk1Priortiy\": 10,\n            \"Trunk1Weight\": 10,\n            \"Trunk2Priortiy\": 20,\n            \"Trunk2Weight\": 20,\n            \"HeaderManipulation\": \"HMI8802029\",\n            \"EnableSipRefer\": true,\n            \"TransferCallerId\": \"Transferee/Transferor\",\n            \"SymmetricRtp\": true,\n            \"EnableTrpSecureTrunk\": true,\n            \"EnablePstnTransfer\": true,\n            \"IpWhitelist\": [{\"IpAddress\": \"20.20.10.10\"}, {\"IpAddress\": \"20.20.10.20\"}],\n            \"CnamLookup\": true,\n            \"TerminationUriSubdomain\": \"client\",\n            \"EnableCallStreaming\": true,\n            \"WssUri\": \"wss://192.67.88.2\",\n            \"RouteEnabled\": true\n        },\n        {\n            \"CallRouteStatus\": \"Active\",\n            \"CallRouteId\": \"CRID-993804Ar09093\",\n            \"AccountId\": \"DID-1e8939ab-3f3c-4db1-89d7-956d80fd793j203805880870238\",\n            \"RouteName\": \"Main SIP Trunk Secondary\",\n            \"RouteType\": \"Trunk\",\n            \"VoiceUrlMethod\": \"POST\",\n            \"TrunkIp1\": \"20.87.87.87\",\n            \"TrunkIp2\": \"20.87.87.86\",\n            \"TrunkPort1\": \"5061\",\n            \"TrunkPort2\": \"5060\",\n            \"TrunkTransport1\": \"UDP\",\n            \"TrunkTransport2\": \"TCP\",\n            \"TrunkUri1\": \"https://pstn.joonto.com\",\n            \"TrunkUri2\": \"https://pstn2.joonto.com\",\n            \"TrunkEnabled1\": true,\n            \"TrunkEnabled2\": false,\n            \"Trunk1Priortiy\": 10,\n            \"Trunk1Weight\": 10,\n            \"Trunk2Priortiy\": 20,\n            \"Trunk2Weight\": 20,\n            \"HeaderManipulation\": \"HMI8802029\",\n            \"EnableSipRefer\": true,\n            \"TransferCallerId\": \"Transferee/Transferor\",\n            \"SymmetricRtp\": true,\n            \"EnableTrpSecureTrunk\": true,\n            \"EnablePstnTransfer\": true,\n            \"IpWhitelist\": [{\"IpAddress\": \"20.20.10.10\"}, {\"IpAddress\": \"20.20.10.20\"}],\n            \"CnamLookup\": true,\n            \"TerminationUriSubdomain\": \"client\",\n            \"EnableCallStreaming\": true,\n            \"WssUri\": \"wss://192.67.88.2\",\n            \"RouteEnabled\": true\n        }\n    ]\n}\n```\n\n##### Response Fields\n\n| Field | Type | Description |\n|-------|------|-------------|\n| `AccountId` | string | Your account identifier |\n| `TotalRoutes` | integer | Total number of voice routes in your account |\n| `Results` | array | List of voice route objects |\n\n##### Voice Route Object Fields\n\n| Field | Type | Description |\n|-------|------|-------------|\n| `CallRouteStatus` | string | Current status of the voice route (e.g., \"Active\") |\n| `CallRouteId` | string | Unique identifier of the voice route |\n| `AccountId` | string | Your account identifier |\n| `RouteName` | string | Name of the voice route |\n| `RouteType` | string | Type of routing (Trunk, URL, Forward) |\n| `VoiceUrlMethod` | string | HTTP method for the webhook URL (if applicable) |\n| `TrunkIp1` | string | Primary SIP trunk IP address (if applicable) |\n| `TrunkIp2` | string | Backup SIP trunk IP address (if applicable) |\n| `TrunkPort1` | string | Primary SIP trunk port (if applicable) |\n| `TrunkPort2` | string | Backup SIP trunk port (if applicable) |\n| `TrunkTransport1` | string | Primary transport protocol (if applicable) |\n| `TrunkTransport2` | string | Backup transport protocol (if applicable) |\n| `TrunkUri1` | string | Primary SIP URI (if applicable) |\n| `TrunkUri2` | string | Backup SIP URI (if applicable) |\n| `TrunkEnabled1` | boolean | Whether primary trunk is active (if applicable) |\n| `TrunkEnabled2` | boolean | Whether backup trunk is active (if applicable) |\n| `Trunk1Priortiy` | integer | Priority value for primary trunk (if applicable) |\n| `Trunk1Weight` | integer | Weight value for primary trunk (if applicable) |\n| `Trunk2Priortiy` | integer | Priority value for backup trunk (if applicable) |\n| `Trunk2Weight` | integer | Weight value for backup trunk (if applicable) |\n| `HeaderManipulation` | string | Header manipulation identifier (if applicable) |\n| `EnableSipRefer` | boolean | Whether SIP REFER is enabled (if applicable) |\n| `TransferCallerId` | string | Caller ID behavior during transfers (if applicable) |\n| `SymmetricRtp` | boolean | Whether symmetric RTP is enabled (if applicable) |\n| `EnableTrpSecureTrunk` | boolean | Whether TRP secure trunk is enabled (if applicable) |\n| `EnablePstnTransfer` | boolean | Whether PSTN transfers are allowed (if applicable) |\n| `IpWhitelist` | array | List of whitelisted IP addresses (if applicable) |\n| `CnamLookup` | boolean | Whether CNAM lookup is enabled (if applicable) |\n| `TerminationUriSubdomain` | string | Subdomain for termination URIs (if applicable) |\n| `EnableCallStreaming` | boolean | Whether call streaming is enabled (if applicable) |\n| `WssUri` | string | WebSocket Secure URI for call streaming (if applicable) |\n| `RouteEnabled` | boolean | Whether this route is active (if applicable) |\n\n#### 401 Unauthorized: Authentication Error\n\n```json\n{\n    \"Type\": \"https://tools.ietf.org/html/rfc7235#section-3.1\",\n    \"Title\": \"Unauthorized\",\n    \"Status\": 401,\n    \"TraceId\": \"00-1234abcd5678efgh-abcdef123456-00\"\n}\n```\n\n### Usage Notes\n\n- Use this endpoint to view all voice routes configured in your account.\n- This is useful for selecting the appropriate voice route when provisioning or updating phone numbers.\n- Authentication credentials in the response may be partially masked for security reasons.\n- The `CallRouteStatus` field indicates whether each route is currently active and available for use.\n- You can copy a `CallRouteId` from this list to use with other endpoints like `/voice/routes` for detailed information.\n- The fields displayed for each route will depend on the route type (Trunk, URL, or Forward).\n- Routes with `RouteEnabled` set to `false` are configured but not actively processing calls.\n- For SIP trunk routes, check the `TrunkEnabled1` and `TrunkEnabled2` values to see which trunks are actively handling calls.\n- If you have many routes, consider implementing a naming convention that makes it easy to identify the purpose of each route.\n- This endpoint is useful for auditing your voice routing configuration and identifying unused or duplicate routes.\n\n### Try It\n\n```\ncurl -X GET \"https://api.telegent.com/v1.0/account/voice/routes\" \\\n  -H \"Authorization: Bearer YOUR_API_TOKEN\"\n```"
							},
							"response": [
								{
									"name": "Account Routes List",
									"originalRequest": {
										"method": "GET",
										"header": [],
										"url": {
											"raw": "https://api.telegent.com/v1.0/account/voice/routes",
											"protocol": "https",
											"host": [
												"api",
												"telegent",
												"com"
											],
											"path": [
												"v1.0",
												"account",
												"voice",
												"routes"
											]
										}
									},
									"_postman_previewlanguage": "json",
									"header": [
										{
											"key": "Content-Type",
											"value": "application/json",
											"description": "",
											"type": "text"
										}
									],
									"cookie": [],
									"body": "{\n    \"AccountID\": \"DID-1e8939ab-3f3c-4db1-89d7-956d80fd793j203805880870238\",\n    \"TotalRoutes\": 2,\n    \"Results\": [\n{\n    \"CallRouteStatus\": \"Active\"\n    \"CallRouteId\": \"CRID-993804Ar09099\",\n    \"AccountID\": \"DID-1e8939ab-3f3c-4db1-89d7-956d80fd793j203805880870238\",\n    \"RouteName\": \"Main SIP Trunk\",\n    \"RouteType\": \"Trunk\",\n    \"VoiceUrlMethod\": \"POST\",\n    \"TrunkIp1\": \"20.87.87.87\",\n    \"TrunkIp2\": \"20.87.87.86\",\n    \"TrunkPort1\": \"5061\",\n    \"TrunkPort2\": \"5060\",\n    \"TrunkTransport1\": \"UDP\",\n    \"TrunkTransport2\": \"TCP\",\n    \"TrunkUri1\": \"https://pstn.joonto.com\",\n    \"TrunkUri2\": \"https://pstn2.joonto.com\",\n    \"TrunkEnabled1\": true,\n    \"TrunkEnabled2\": false,\n    \"Trunk1Priortiy\": 10,\n    \"Trunk1Weight\": 10,\n    \"Trunk2Priortiy\": 20,\n    \"Trunk2Weight\": 20,\n    \"HeaderManipulation\":\"HMI8802029\",\n    \"EnableSipRefer\": true,\n    \"TransferCallerId\": \"Transferee/Transferor\",\n    \"SymmetricRtp\": true,\n    \"EnableTrpSecureTrunk\": true,\n    \"EnablePstnTransfer\": true,\n    \"IpWhitelist\": [{\"IpAddress\": \"20.20.10.10\"}, {\"IpAddress\": \"20.20.10.20\"}],\n    \"CnamLookup\": true,\n    \"TerminationUriSubdomain\": \"client\",\n    \"EnableCallStreaming\": true,\n    \"WssUri\": \"wss://192.67.88.2\",\n    \"RouteEnabled\": true\n},\n{\n    \"CallRouteStatus\": \"Active\",\n    \"CallRouteId\": \"CRID-993804Ar09093\",\n    \"AccountID\": \"DID-1e8939ab-3f3c-4db1-89d7-956d80fd793j203805880870238\",\n    \"RouteName\": \"Main SIP Trunk Secondary\",\n    \"RouteType\": \"Trunk\",\n    \"VoiceUrlMethod\": \"POST\",\n    \"TrunkIp1\": \"20.87.87.87\",\n    \"TrunkIp2\": \"20.87.87.86\",\n    \"TrunkPort1\": \"5061\",\n    \"TrunkPort2\": \"5060\",\n    \"TrunkTransport1\": \"UDP\",\n    \"TrunkTransport2\": \"TCP\",\n    \"TrunkUri1\": \"https://pstn.joonto.com\",\n    \"TrunkUri2\": \"https://pstn2.joonto.com\",\n    \"TrunkEnabled1\": true,\n    \"TrunkEnabled2\": false,\n    \"Trunk1Priortiy\": 10,\n    \"Trunk1Weight\": 10,\n    \"Trunk2Priortiy\": 20,\n    \"Trunk2Weight\": 20,\n    \"HeaderManipulation\":\"HMI8802029\",\n    \"EnableSipRefer\": true,\n    \"TransferCallerId\": \"Transferee/Transferor\",\n    \"SymmetricRtp\": true,\n    \"EnableTrpSecureTrunk\": true,\n    \"EnablePstnTransfer\": true,\n    \"IpWhitelist\": [{\"IpAddress\": \"20.20.10.10\"}, {\"IpAddress\": \"20.20.10.20\"}],\n    \"CnamLookup\": true,\n    \"TerminationUriSubdomain\": \"client\",\n    \"EnableCallStreaming\": true,\n    \"WssUri\": \"wss://192.67.88.2\",\n    \"RouteEnabled\": true\n}\n    ]\n}"
								}
							]
						},
						{
							"name": "Delete Voice Route",
							"request": {
								"method": "POST",
								"header": [],
								"body": {
									"mode": "raw",
									"raw": "{\n    \"CallRouteId\": \"{{CallRouteId}}\"\n}",
									"options": {
										"raw": {
											"language": "json"
										}
									}
								},
								"url": {
									"raw": "https://api.telegent.com/v1.0/voice/routes/delete",
									"protocol": "https",
									"host": [
										"api",
										"telegent",
										"com"
									],
									"path": [
										"v1.0",
										"voice",
										"routes",
										"delete"
									]
								},
								"description": "# Delete Voice Route\n\n## POST /voice/routes/delete\n\nPermanently deletes a voice routing configuration from your account.\n\n### Request\n\n#### Headers\n\n```\nContent-Type: application/json\nAuthorization: Bearer {your_api_token}\n```\n\n#### Body Parameters\n\n| Parameter | Type | Required | Description |\n|-----------|------|----------|-------------|\n| `CallRouteId` | string | Yes | Unique identifier of the voice route to delete |\n\n### Sample Request\n\n```json\n{\n    \"CallRouteId\": \"CRID-4dec6beb-3985-444b-8c06-8baa70dc1416\"\n}\n```\n\n### Responses\n\n#### 200 OK: Success\n\nReturns confirmation that the voice route was deleted.\n\n```json\n{\n    \"CallRouteStatus\": \"Deleted\",\n    \"CallRouteId\": \"CRID-4dec6beb-3985-444b-8c06-8baa70dc1416\"\n}\n```\n\n##### Response Fields\n\n| Field | Type | Description |\n|-------|------|-------------|\n| `CallRouteStatus` | string | Status of the operation (should be \"Deleted\") |\n| `CallRouteId` | string | Unique identifier of the deleted voice route |\n\n#### 404 Not Found: Route Not Found\n\n```json\n{\n    \"Type\": \"https://tools.ietf.org/html/rfc7231#section-6.5.4\",\n    \"Title\": \"Not Found\",\n    \"Status\": 404,\n    \"Detail\": \"Voice route with ID 'CRID-4dec6beb-3985-444b-8c06-8baa70dc1416' was not found.\",\n    \"TraceId\": \"00-1234abcd5678efgh-abcdef123456-00\"\n}\n```\n\n#### 400 Bad Request: Route In Use\n\n```json\n{\n    \"Type\": \"https://tools.ietf.org/html/rfc7231#section-6.5.1\",\n    \"Title\": \"Bad Request\",\n    \"Status\": 400,\n    \"Detail\": \"Cannot delete voice route as it is currently assigned to one or more phone numbers.\",\n    \"TraceId\": \"00-1234abcd5678efgh-abcdef123456-00\"\n}\n```\n\n#### 401 Unauthorized: Authentication Error\n\n```json\n{\n    \"Type\": \"https://tools.ietf.org/html/rfc7235#section-3.1\",\n    \"Title\": \"Unauthorized\",\n    \"Status\": 401,\n    \"TraceId\": \"00-1234abcd5678efgh-abcdef123456-00\"\n}\n```\n\n### Usage Notes\n\n- Deleting a voice route is permanent and cannot be undone.\n- Before deleting a voice route, ensure it is not currently assigned to any phone numbers.\n- To check which phone numbers are using a voice route, use the `/numbers/inventory` endpoint and filter by the CallRouteId.\n- If you need to delete a voice route that is in use, first update those phone numbers to use a different voice route.\n- Instead of deleting a route, consider updating it or disabling it by setting `RouteEnabled` to `false` if you may need it again in the future.\n- After deleting a route, any references to its CallRouteId will no longer be valid.\n- Deleting unused voice routes helps keep your account organized and prevents confusion when provisioning new numbers.\n- For SIP trunk routes, ensure that no active calls are using the route before deletion.\n- Deletion of voice routes may affect billing if there are associated costs with maintaining the route.\n- If you're consolidating your voice routing, consider creating a replacement route first and testing it before deleting the old route.\n\n### Try It\n\n```\ncurl -X POST \"https://api.telegent.com/v1.0/voice/routes/delete\" \\\n  -H \"Content-Type: application/json\" \\\n  -H \"Authorization: Bearer YOUR_API_TOKEN\" \\\n  -d '{\n    \"CallRouteId\": \"CRID-4dec6beb-3985-444b-8c06-8baa70dc1416\"\n}'\n```"
							},
							"response": [
								{
									"name": "Delete Voice Route",
									"originalRequest": {
										"method": "POST",
										"header": [],
										"body": {
											"mode": "raw",
											"raw": "{\n    \"CallRouteId\": \"CRID-4dec6beb-3985-444b-8c06-8baa70dc1416\"\n}",
											"options": {
												"raw": {
													"language": "json"
												}
											}
										},
										"url": {
											"raw": "https://api.telegent.com/v1.0/voice/routes/delete",
											"protocol": "https",
											"host": [
												"api",
												"telegent",
												"com"
											],
											"path": [
												"v1.0",
												"voice",
												"routes",
												"delete"
											]
										}
									},
									"_postman_previewlanguage": "json",
									"header": [
										{
											"key": "Content-Type",
											"value": "application/json",
											"description": "",
											"type": "text"
										}
									],
									"cookie": [],
									"body": "{\n    \"CallRouteStatus\": \"Deleted\",\n    \"CallRouteId\": \"CRID-4dec6beb-3985-444b-8c06-8baa70dc1416\"\n}"
								}
							]
						}
					],
					"description": "# Intelligent Voice Routing API Documentation\n\nThis section details the management of voice routing configurations, including SIP trunks, webhook integrations, and call handling settings.\n\n## Key Workflow\n\n1. **Set up a voice infrastructure**:\n    - Create a Voice Route to get a `CallRouteId`\n        \n    - Associate this route with your phone numbers\n        \n    - Configure call handling based on your requirements\n        \n    - Manage SIP trunks, webhooks, or forwarding rules\n        \n\n## Main Endpoints\n\n### Voice Route Management\n\n- **Create Voice Route**: `POST /voice/routes`\n    \n    - Creates a new voice routing configuration\n        \n    - Supports multiple route types: Trunk, URL, or Forward\n        \n    - Returns a `CallRouteId` that can be used when provisioning or updating phone numbers\n        \n    - Configures SIP trunk details, webhooks, and call handling behaviors\n        \n- **Update Voice Route**: `POST /voice/routes/update`\n    \n    - Modifies an existing voice route's configuration\n        \n    - Requires the `CallRouteId` to identify which route to update\n        \n    - Can change any aspect of the route, including its type\n        \n- **Get Voice Route Details**: `GET /voice/routes?CallRouteID={CallRouteId}`\n    \n    - Retrieves the detailed configuration of a specific voice route\n        \n    - Useful for confirming current settings or troubleshooting\n        \n- **List Account Voice Routes**: `GET /account/voice/routes`\n    \n    - Returns all voice routes configured for your account\n        \n    - Provides status information and configuration details\n        \n    - Useful for selecting appropriate routes for phone numbers\n        \n- **Delete Voice Route**: `POST /voice/routes/delete`\n    \n    - Permanently removes a voice route configuration\n        \n    - Cannot delete routes currently assigned to phone numbers\n        \n\n## Route Types\n\nThe Intelligent Voice Routing API supports three primary route types, each with its own configuration requirements:\n\n1. **Trunk Routes**: Connect to SIP trunks for voice termination\n    \n    - Configure primary and backup trunk servers\n        \n    - Set priorities and weights for load balancing\n        \n    - Control protocol settings (UDP, TCP, TLS)\n        \n    - Manage IP whitelisting and security options\n        \n2. **URL Routes**: Forward calls to webhook endpoints\n    \n    - Configure webhook URLs and methods\n        \n    - Set up authentication for secure webhooks\n        \n    - Manage callback URLs for call status updates\n        \n    - Control advanced call handling features\n        \n3. **Forward Routes**: Set up simple call forwarding\n    \n    - Direct calls to another destination number\n        \n    - Configure fallback options\n        \n    - Set up call screening and filtering\n        \n\n## Configuration Best Practices\n\n1. **SIP Trunk Setup**:\n    \n    - Always configure backup trunks for redundancy\n        \n    - Use appropriate priority and weight settings for load distribution\n        \n    - Consider using secure transport protocols (TLS) for sensitive voice traffic\n        \n    - Implement IP whitelisting to restrict trunk access\n        \n2. **Webhook Integration**:\n    \n    - Use secure (HTTPS) endpoints for voice webhooks\n        \n    - Implement proper authentication on webhook endpoints\n        \n    - Configure callback URLs to receive call status updates\n        \n    - Ensure your webhook servers have sufficient capacity to handle call volumes\n        \n3. **Call Control Features**:\n    \n    - Configure CNAM lookup for caller ID information\n        \n    - Set appropriate SIP REFER behavior for call transfers\n        \n    - Enable or disable PSTN transfers based on your requirements\n        \n    - Consider call streaming options for recording or analytics\n        \n\n## Integration Workflow\n\n1. First, create a Voice Route using `POST /voice/routes` to establish how calls will be handled\n    \n2. Use the returned `CallRouteId` when provisioning or updating phone numbers via the Intelligent Mobile Numbers API\n    \n3. Verify your voice route configuration with `GET /voice/routes` to ensure everything is set correctly\n    \n4. Test calling functionality with your configured phone numbers\n    \n5. Monitor call behavior and adjust settings as needed with `POST /voice/routes/update`\n    \n\nThis API provides a comprehensive platform for building advanced voice applications, from simple call forwarding to complex SIP trunk integrations with high availability and detailed call control capabilities."
				}
			],
			"description": "Released May 15, 2025",
			"event": [
				{
					"listen": "prerequest",
					"script": {
						"type": "text/javascript",
						"packages": {},
						"exec": [
							""
						]
					}
				},
				{
					"listen": "test",
					"script": {
						"type": "text/javascript",
						"packages": {},
						"exec": [
							""
						]
					}
				}
			]
		}
	],
	"auth": {
		"type": "bearer",
		"bearer": [
			{
				"key": "token",
				"value": "{{Token}}",
				"type": "string"
			}
		]
	},
	"event": [
		{
			"listen": "prerequest",
			"script": {
				"type": "text/javascript",
				"packages": {},
				"exec": [
					"(async () => {",
					"  try {",
					"    // Get base URL from environment or use default",
					"    const base = pm.environment.get('BaseUrl') || \"https://api.telegent.com/v1.0\";",
					"    console.log('Using base URL:', base);",
					"    const tokenUrl = `${base}/oauth2/tokens`;",
					"",
					"    // Get the current request URL to extract API endpoint",
					"    const rawUrl = pm.request.url.toString();",
					"    const resolved = pm.variables.replaceIn(rawUrl);",
					"    const apiEp = resolved.split('?')[0];",
					"",
					"    // Retrieve credentials from environment or collection variables",
					"    const accountKey = pm.variables.get('AccountKey');",
					"    const accountSecret = pm.variables.get('AccountSecret');",
					"",
					"    console.log('Credential diagnostic:');",
					"    console.log('AccountKey:', accountKey);",
					"    console.log('AccountSecret:', accountSecret);",
					"",
					"    if (!accountKey || !accountSecret) {",
					"      console.error('❌ Authentication failed: Missing AccountKey or AccountSecret.');",
					"      console.error('Please set these values as environment or collection variables.');",
					"      return;",
					"    }",
					"",
					"    // Request token",
					"    const resp = await pm.sendRequest({",
					"      url: tokenUrl,",
					"      method: 'POST',",
					"      header: { 'Content-Type': 'application/json' },",
					"      body: {",
					"        mode: 'raw',",
					"        raw: JSON.stringify({",
					"          AccountKey: accountKey,",
					"          AccountSecret: accountSecret,",
					"          ApiEndpoint: apiEp",
					"        })",
					"      }",
					"    });",
					"",
					"    const json = resp.json();",
					"    console.log('Token response status:', resp.code);",
					"    console.log('Full token response:', JSON.stringify(json, null, 2));",
					"",
					"    // Try multiple formats to extract token",
					"    const jwt = json.Token || json.token || json?.Data?.AccessToken;",
					"",
					"    if (!jwt) {",
					"      console.error('❌ No token in response; HTTP status:', resp.code);",
					"      if (json.Successful === false || json.Message) {",
					"        console.error('Authentication failed. Error:', json.Message || 'Unknown error');",
					"      }",
					"    } else {",
					"      console.log('✅ Token successfully retrieved');",
					"",
					"      // Store token in environment or collection",
					"      if (pm.environment.has('Token')) {",
					"        pm.environment.set('Token', jwt);",
					"      } else {",
					"        pm.collectionVariables.set('Token', jwt);",
					"      }",
					"",
					"      // Set token manually for the upcoming request",
					"      pm.request.headers.upsert({",
					"        key: 'Authorization',",
					"        value: `Bearer ${jwt}`",
					"      });",
					"    }",
					"",
					"  } catch (error) {",
					"    console.error('❌ Error in pre-request script:', error.message);",
					"  }",
					"})();",
					""
				]
			}
		},
		{
			"listen": "test",
			"script": {
				"type": "text/javascript",
				"packages": {},
				"exec": [
					""
				]
			}
		}
	],
	"variable": [
		{
			"key": "Token",
			"value": ""
		},
		{
			"key": "CRID",
			"value": ""
		},
		{
			"key": "MRID",
			"value": ""
		},
		{
			"key": "OrderId",
			"value": ""
		},
		{
			"key": "TCID",
			"value": ""
		},
		{
			"key": "PHONE_NUMBER",
			"value": ""
		},
		{
			"key": "MRID_1",
			"value": ""
		},
		{
			"key": "CRID_1",
			"value": ""
		},
		{
			"key": "Mrid",
			"value": ""
		},
		{
			"key": "CallRouteId",
			"value": ""
		},
		{
			"key": "MessageRouteId",
			"value": ""
		}
	]
}